Workbook

Sheet TOTAL MOD working excl biomass
A1: Details of power purchase cost per unit for MOD on the basis of rates available from bills of March 2026
B2: Name of Generating Stations | C2: Energy Charges Rate for MOD Purpose Rs./kwh | D2: FCA Rs./kwh | E2: Effective Energy Charges (Rs./kwh) | F2: Transmission Losses beyond MP periphery (%) | G2: Variable cost incl. losses | H2: Cess on Intrastate sales | I2: ED & Cess on Auxiliary Consumption | J2: Trading Margin | K2: Transmission charges | L2: FGD / Change in Law | M2: Normative fixed cost for URS | N2: Incentive p.u. | O2: Effective rate in Rs./kwh
G4: (Rs. per kwh)
A5: A | B5: B | C5: C | D5: D | E5: E=C+D | F5: F | G5: G=E/((100%-F)) | H5: H | I5: I | J5: J | K5: K | L5: L | M5: M | N5: N | O5: O=sum(G:N)
A6: 1 | B6: Arya Energy Limited (Biomass) | C6: 4.38 | E6: =C6+D6 -> 4.38 | G6: =E6/((100%-F6)) -> 4.38 | I6: =VLOOKUP(B6,'fixed cost'!$B$4:$R$116,17,0) -> 0 | O6: =SUM(G6:N6) -> 4.38 | P6: 4.38 | Q6: =C6-P6 -> 0 | R6: =Q6/P6 -> 0
A7: =A6+1 -> 2 | B7: ATPS (210MW) Chachai | C7: 1.829 | D7: 0 | E7: =C7+D7 -> 1.829 | G7: =E7/((100%-F7)) -> 1.829 | I7: =VLOOKUP(B7,'fixed cost'!$B$4:$R$116,17,0) -> 0 | O7: =SUM(G7:N7) -> 1.829 | P7: 1.913 | Q7: =C7-P7 -> -0.084 | R7: =Q7/P7 -> -0.043910089
A8: 2 | B8: ATPS (210MW) Chachai | C8: =C7 -> 1.829 | E8: =C8+D8 -> 1.829 | G8: =E8/((100%-F8)) -> 1.829 | I8: =VLOOKUP(B8,'fixed cost'!$B$4:$R$116,17,0) -> 0 | N8: 0.55 | O8: =SUM(G8:N8) -> 2.379 | P8: 1.913 | Q8: =C8-P8 -> -0.084 | R8: =Q8/P8 -> -0.043910089
A9: 2 | B9: ATPS (210MW) Chachai | C9: =C8 -> 1.829 | E9: =C9+D9 -> 1.829 | G9: =E9/((100%-F9)) -> 1.829 | I9: =VLOOKUP(B9,'fixed cost'!$B$4:$R$116,17,0) -> 0 | N9: 0.75 | O9: =SUM(G9:N9) -> 2.579 | P9: 1.913 | Q9: =C9-P9 -> -0.084 | R9: =Q9/P9 -> -0.043910089
A10: 3 | B10: Bansagar-I HPS | C10: 0.602 | E10: =C10+D10 -> 0.602 | G10: =E10/((100%-F10)) -> 0.602 | I10: =VLOOKUP(B10,'fixed cost'!$B$4:$R$116,17,0) -> 0 | O10: =SUM(G10:N10) -> 0.602 | P10: 0.602 | Q10: =C10-P10 -> 0 | R10: =Q10/P10 -> 0
A11: =+A10+1 -> 4 | B11: Bansagar-II HPS | C11: 0.457 | E11: =C11+D11 -> 0.457 | G11: =E11/((100%-F11)) -> 0.457 | I11: =VLOOKUP(B11,'fixed cost'!$B$4:$R$116,17,0) -> 0 | O11: =SUM(G11:N11) -> 0.457 | P11: 0.457 | Q11: =C11-P11 -> 0 | R11: =Q11/P11 -> 0
A12: =+A11+1 -> 5 | B12: Bansagar-III HPS | C12: 0.722 | E12: =C12+D12 -> 0.722 | G12: =E12/((100%-F12)) -> 0.722 | I12: =VLOOKUP(B12,'fixed cost'!$B$4:$R$116,17,0) -> 0 | O12: =SUM(G12:N12) -> 0.722 | P12: 0.722 | Q12: =C12-P12 -> 0 | R12: =Q12/P12 -> 0
A13: =+A12+1 -> 6 | B13: Bargi HPS | C13: 0.19 | E13: =C13+D13 -> 0.19 | G13: =E13/((100%-F13)) -> 0.19 | I13: =VLOOKUP(B13,'fixed cost'!$B$4:$R$116,17,0) -> 0 | O13: =SUM(G13:N13) -> 0.19 | P13: 0.19 | Q13: =C13-P13 -> 0 | R13: =Q13/P13 -> 0
A14: =+A13+1 -> 7 | B14: Birsinghpur HPS | C14: 0.589 | E14: =C14+D14 -> 0.589 | G14: =E14/((100%-F14)) -> 0.589 | I14: =VLOOKUP(B14,'fixed cost'!$B$4:$R$116,17,0) -> 0 | O14: =SUM(G14:N14) -> 0.589 | P14: 0.589 | Q14: =C14-P14 -> 0 | R14: =Q14/P14 -> 0
A15: 8 | B15: BLA | C15: 3.752 | E15: =C15+D15 -> 3.752 | G15: =E15/((100%-F15)) -> 3.752 | H15: 0.15 | I15: =VLOOKUP(B15,'fixed cost'!$B$4:$R$116,17,0) -> 0.08001 | O15: =SUM(G15:N15) -> 3.98201 | P15: 3.761 | Q15: =C15-P15 -> -0.009 | R15: =Q15/P15 -> -0.0023929806
A16: 9 | B16: BLA II | C16: 4.037 | E16: =C16+D16 -> 4.037 | G16: =E16/((100%-F16)) -> 4.037 | H16: 0.15 | I16: =VLOOKUP(B16,'fixed cost'!$B$4:$R$116,17,0) -> 0.08001 | O16: =SUM(G16:N16) -> 4.26701 | P16: 4.037 | Q16: =C16-P16 -> 0 | R16: =Q16/P16 -> 0
A17: 10 | B17: DVC (CTPS) (STOA LOI) | C17: 2.745 | E17: =C17+D17 -> 2.745 | F17: 0.0442 | G17: =E17/((100%-F17)) -> 2.8719397 | I17: =VLOOKUP(B17,'fixed cost'!$B$4:$R$116,17,0) -> 0 | K17: 0.024 | O17: =SUM(G17:N17) -> 2.8959397 | P17: 2.745 | Q17: =C17-P17 -> 0 | R17: =Q17/P17 -> 0
A18: 11 | B18: DVC (DTPS) (STOA LOI) | C18: 3.085 | D18: 0.165 | E18: =C18+D18 -> 3.25 | F18: =F17 -> 0.0442 | G18: =E18/((100%-F18)) -> 3.4002929 | I18: =VLOOKUP(B18,'fixed cost'!$B$4:$R$116,17,0) -> 0 | K18: 0 | L18: 0.07 | O18: =SUM(G18:N18) -> 3.4702929 | P18: 3.124 | Q18: =C18-P18 -> -0.039 | R18: =Q18/P18 -> -0.012483995
A19: 12 | B19: Mahan Energen Ltd. (5%) | C19: 2.488 | D19: -0.03 | E19: =C19+D19 -> 2.458 | F19: =F18 -> 0.0442 | G19: =E19/((100%-F19)) -> 2.5716677 | H19: 0.15 | I19: =VLOOKUP(B19,'fixed cost'!$B$4:$R$116,17,0) -> 0 | O19: =SUM(G19:N19) -> 2.7216677 | P19: 2.488 | Q19: =C19-P19 -> 0 | R19: =Q19/P19 -> 0
A20: 13 | B20: Gadarwara | C20: 3.119 | D20: 0.032 | E20: =C20+D20 -> 3.151 | F20: =F19 -> 0.0442 | G20: =E20/((100%-F20)) -> 3.2967148 | H20: 0.15 | I20: =VLOOKUP(B20,'fixed cost'!$B$4:$R$116,17,0) -> 0.058995 | L20: 0.65 | O20: =SUM(G20:N20) -> 4.1557098 | P20: 3.137 | Q20: =C20-P20 -> -0.018 | R20: =Q20/P20 -> -0.0057379662
A21: =A20+1 -> 14 | B21: Gadarwara | C21: =C20 -> 3.119 | D21: =D20 -> 0.032 | E21: =C21+D21 -> 3.151 | F21: =F20 -> 0.0442 | G21: =E21/((100%-F21)) -> 3.2967148 | H21: =H20 -> 0.15 | I21: =VLOOKUP(B21,'fixed cost'!$B$4:$R$116,17,0) -> 0.058995 | L21: =L20 -> 0.65 | M21: =VLOOKUP(B21,'fixed cost'!$B$4:$H$116,7,0) -> 2.0601461 | O21: =SUM(G21:N21) -> 6.2158559 | P21: 3.137 | Q21: =C21-P21 -> -0.018 | R21: =Q21/P21 -> -0.0057379662
A22: =A21+1 -> 15 | B22: GANDHAR (APM) | C22: 2.098 | E22: =C22+D22 -> 2.098 | F22: =F21 -> 0.0442 | G22: =E22/((100%-F22)) -> 2.1950199 | I22: =VLOOKUP(B22,'fixed cost'!$B$4:$R$116,17,0) -> 0 | O22: =SUM(G22:N22) -> 2.1950199 | P22: 2.098 | Q22: =C22-P22 -> 0 | R22: =Q22/P22 -> 0
A23: =A22+1 -> 16 | B23: GANDHAR (APM) | C23: =C22 -> 2.098 | D23: =D22 -> 0 | E23: =C23+D23 -> 2.098 | F23: =F22 -> 0.0442 | G23: =E23/((100%-F23)) -> 2.1950199 | I23: =VLOOKUP(B23,'fixed cost'!$B$4:$R$116,17,0) -> 0 | M23: =VLOOKUP(B23,'fixed cost'!$B$4:$H$116,7,0) -> 1.0465902 | O23: =SUM(G23:N23) -> 3.2416101 | P23: 2.098 | Q23: =C23-P23 -> 0 | R23: =Q23/P23 -> 0
A24: =A23+1 -> 17 | B24: GANDHAR (CLNG) | C24: 8.915 | E24: =C24+D24 -> 8.915 | F24: =F23 -> 0.0442 | G24: =E24/((100%-F24)) -> 9.3272651 | I24: =VLOOKUP(B24,'fixed cost'!$B$4:$R$116,17,0) -> 0 | O24: =SUM(G24:N24) -> 9.3272651 | P24: 8.915 | Q24: =C24-P24 -> 0 | R24: =Q24/P24 -> 0
A25: =A24+1 -> 18 | B25: GANDHAR (CLNG) | C25: =C24 -> 8.915 | D25: =D24 -> 0 | E25: =C25+D25 -> 8.915 | F25: =F24 -> 0.0442 | G25: =E25/((100%-F25)) -> 9.3272651 | I25: =VLOOKUP(B25,'fixed cost'!$B$4:$R$116,17,0) -> 0 | M25: =VLOOKUP(B25,'fixed cost'!$B$4:$H$116,7,0) -> 1.0465902 | O25: =SUM(G25:N25) -> 10.373855 | P25: 8.915 | Q25: =C25-P25 -> 0 | R25: =Q25/P25 -> 0
A26: =A25+1 -> 19 | B26: GANDHAR (LNG) | C26: 9.693 | D26: 3.353 | E26: =C26+D26 -> 13.046 | F26: =F25 -> 0.0442 | G26: =E26/((100%-F26)) -> 13.649299 | I26: =VLOOKUP(B26,'fixed cost'!$B$4:$R$116,17,0) -> 0 | O26: =SUM(G26:N26) -> 13.649299 | P26: 9.654 | Q26: =C26-P26 -> 0.039 | R26: =Q26/P26 -> 0.0040397763
A27: =A26+1 -> 20 | B27: GANDHAR (LNG) | C27: =C26 -> 9.693 | D27: =D26 -> 3.353 | E27: =C27+D27 -> 13.046 | F27: =F26 -> 0.0442 | G27: =E27/((100%-F27)) -> 13.649299 | I27: =VLOOKUP(B27,'fixed cost'!$B$4:$R$116,17,0) -> 0 | M27: =VLOOKUP(B27,'fixed cost'!$B$4:$H$116,7,0) -> 1.0465902 | O27: =SUM(G27:N27) -> 14.695889 | P27: 9.654 | Q27: =C27-P27 -> 0.039 | R27: =Q27/P27 -> 0.0040397763
A28: =A27+1 -> 21 | B28: GANDHAR (NAPM) | C28: 29.718 | E28: =C28+D28 -> 29.718 | F28: =F27 -> 0.0442 | G28: =E28/((100%-F28)) -> 31.092279 | I28: =VLOOKUP(B28,'fixed cost'!$B$4:$R$116,17,0) -> 0 | O28: =SUM(G28:N28) -> 31.092279 | P28: 29.718 | Q28: =C28-P28 -> 0 | R28: =Q28/P28 -> 0
A29: =A28+1 -> 22 | B29: GANDHAR (NAPM) | C29: =C28 -> 29.718 | D29: =D28 -> 0 | E29: =C29+D29 -> 29.718 | F29: =F28 -> 0.0442 | G29: =E29/((100%-F29)) -> 31.092279 | I29: =VLOOKUP(B29,'fixed cost'!$B$4:$R$116,17,0) -> 0 | M29: =VLOOKUP(B29,'fixed cost'!$B$4:$H$116,7,0) -> 1.0465902 | O29: =SUM(G29:N29) -> 32.138869 | P29: 29.718 | Q29: =C29-P29 -> 0 | R29: =Q29/P29 -> 0
A30: =A29+1 -> 23 | B30: Gandhi Sagar HPS | C30: 0.238 | E30: =C30+D30 -> 0.238 | G30: =E30/((100%-F30)) -> 0.238 | I30: =VLOOKUP(B30,'fixed cost'!$B$4:$R$116,17,0) -> 0 | O30: =SUM(G30:N30) -> 0.238 | P30: 0.238 | Q30: =C30-P30 -> 0 | R30: =Q30/P30 -> 0
A31: =A30+1 -> 24 | B31: ISP & OSP (25:11) | C31: =((1.856*25)+(2.326*11))/(25+11) -> 1.9996111 | E31: =C31+D31 -> 1.9996111 | G31: =E31/((100%-F31)) -> 1.9996111 | H31: 0.15 | I31: ='fixed cost'!R57 -> 0.00882 | O31: =SUM(G31:N31) -> 2.1584311 | P31: 1.9996111 | Q31: =C31-P31 -> 0 | R31: =Q31/P31 -> 0
A32: =A31+1 -> 25 | B32: Jawahar Sagar (Inter state project) | C32: 1.51 | E32: =C32+D32 -> 1.51 | G32: =E32/((100%-F32)) -> 1.51 | I32: =VLOOKUP(B32,'fixed cost'!$B$4:$R$116,17,0) -> 0 | O32: =SUM(G32:N32) -> 1.51 | P32: 1.51 | Q32: =C32-P32 -> 0 | R32: =Q32/P32 -> 0
A33: =A32+1 -> 26 | B33: Jhabua Power | C33: 2.606 | D33: -0.0099 | E33: =C33+D33 -> 2.5961 | F33: =F29 -> 0.0442 | G33: =E33/((100%-F33)) -> 2.716154 | H33: 0.15 | O33: =SUM(G33:N33) -> 2.866154 | P33: 2.599 | Q33: =C33-P33 -> 0.007 | R33: =Q33/P33 -> 0.0026933436
A34: =A33+1 -> 27 | B34: Jhinna HPS | C34: 0.608 | E34: =C34+D34 -> 0.608 | G34: =E34/((100%-F34)) -> 0.608 | I34: =VLOOKUP(B34,'fixed cost'!$B$4:$R$116,17,0) -> 0 | O34: =SUM(G34:N34) -> 0.608 | P34: 0.608 | Q34: =C34-P34 -> 0 | R34: =Q34/P34 -> 0
A35: =A34+1 -> 28 | B35: JP Bina | C35: 3.376 | E35: =C35+D35 -> 3.376 | G35: =E35/((100%-F35)) -> 3.376 | H35: 0.15 | I35: =VLOOKUP(B35,'fixed cost'!$B$4:$R$116,17,0) -> 0.06477 | O35: =SUM(G35:N35) -> 3.59077 | P35: 3.376 | Q35: =C35-P35 -> 0 | R35: =Q35/P35 -> 0
A36: =A35+1 -> 29 | B36: JP Nigrie | C36: 0.705 | E36: =C36+D36 -> 0.705 | F36: =F33 -> 0.0442 | G36: =E36/((100%-F36)) -> 0.73760201 | H36: 0.15 | I36: =VLOOKUP(B36,'fixed cost'!$B$4:$R$116,17,0) -> 0.040005 | O36: =SUM(G36:N36) -> 0.92760701 | P36: 0.68 | Q36: =C36-P36 -> 0.025 | R36: =Q36/P36 -> 0.036764706
A37: =A36+1 -> 30 | B37: KAHALGAON-II | C37: 2.702 | D37: 0.05799 | E37: =C37+D37 -> 2.75999 | F37: =F36 -> 0.0442 | G37: =E37/((100%-F37)) -> 2.8876229 | I37: =VLOOKUP(B37,'fixed cost'!$B$4:$R$116,17,0) -> 0 | O37: =SUM(G37:N37) -> 2.8876229 | P37: 2.702 | Q37: =C37-P37 -> 0 | R37: =Q37/P37 -> 0
A38: =A37+1 -> 31 | B38: KAHALGAON-II | C38: =C37 -> 2.702 | D38: =D37 -> 0.05799 | E38: =C38+D38 -> 2.75999 | F38: =F37 -> 0.0442 | G38: =E38/((100%-F38)) -> 2.8876229 | I38: =VLOOKUP(B38,'fixed cost'!$B$4:$R$116,17,0) -> 0 | M38: =VLOOKUP(B38,'fixed cost'!$B$4:$H$116,7,0) -> 0.92016616 | O38: =SUM(G38:N38) -> 3.8077891 | P38: 2.702 | Q38: =C38-P38 -> 0 | R38: =Q38/P38 -> 0
A39: =A38+1 -> 32 | B39: KAHALGAON-II | C39: =C38 -> 2.702 | D39: =D38 -> 0.05799 | E39: =C39+D39 -> 2.75999 | F39: =F38 -> 0.0442 | G39: =E39/((100%-F39)) -> 2.8876229 | I39: =VLOOKUP(B39,'fixed cost'!$B$4:$R$116,17,0) -> 0 | N39: 0.55 | O39: =SUM(G39:N39) -> 3.4376229 | P39: 2.702 | Q39: =C39-P39 -> 0 | R39: =Q39/P39 -> 0
A40: =A39+1 -> 33 | B40: KAHALGAON-II | C40: =C39 -> 2.702 | D40: =D39 -> 0.05799 | E40: =C40+D40 -> 2.75999 | F40: =F39 -> 0.0442 | G40: =E40/((100%-F40)) -> 2.8876229 | I40: =VLOOKUP(B40,'fixed cost'!$B$4:$R$116,17,0) -> 0 | N40: 0.75 | O40: =SUM(G40:N40) -> 3.6376229 | P40: 2.702 | Q40: =C40-P40 -> 0 | R40: =Q40/P40 -> 0
A41: =A38+1 -> 32 | B41: KAWAS (APM) | C41: 1.597 | E41: =C41+D41 -> 1.597 | F41: =F38 -> 0.0442 | G41: =E41/((100%-F41)) -> 1.6708516 | I41: =VLOOKUP(B41,'fixed cost'!$B$4:$R$116,17,0) -> 0 | O41: =SUM(G41:N41) -> 1.6708516 | P41: 1.597 | Q41: =C41-P41 -> 0 | R41: =Q41/P41 -> 0
A42: =A41+1 -> 33 | B42: KAWAS (APM) | C42: =C41 -> 1.597 | D42: =D41 -> 0 | E42: =C42+D42 -> 1.597 | F42: =F41 -> 0.0442 | G42: =E42/((100%-F42)) -> 1.6708516 | I42: =VLOOKUP(B42,'fixed cost'!$B$4:$R$116,17,0) -> 0 | M42: =VLOOKUP(B42,'fixed cost'!$B$4:$H$116,7,0) -> 0.85915096 | O42: =SUM(G42:N42) -> 2.5300026 | P42: 1.597 | Q42: =C42-P42 -> 0 | R42: =Q42/P42 -> 0
A43: =A42+1 -> 34 | B43: KAWAS (CLNG) | C43: 8.954 | E43: =C43+D43 -> 8.954 | F43: =F42 -> 0.0442 | G43: =E43/((100%-F43)) -> 9.3680686 | I43: =VLOOKUP(B43,'fixed cost'!$B$4:$R$116,17,0) -> 0 | O43: =SUM(G43:N43) -> 9.3680686 | P43: 8.954 | Q43: =C43-P43 -> 0 | R43: =Q43/P43 -> 0
A44: =A43+1 -> 35 | B44: KAWAS (CLNG) | C44: =C43 -> 8.954 | E44: =C44+D44 -> 8.954 | F44: =F43 -> 0.0442 | G44: =E44/((100%-F44)) -> 9.3680686 | I44: =VLOOKUP(B44,'fixed cost'!$B$4:$R$116,17,0) -> 0 | M44: =VLOOKUP(B44,'fixed cost'!$B$4:$H$116,7,0) -> 0.85915096 | O44: =SUM(G44:N44) -> 10.22722 | P44: 8.954 | Q44: =C44-P44 -> 0 | R44: =Q44/P44 -> 0
A45: =A44+1 -> 36 | B45: KAWAS (LNG) | C45: 9.578 | E45: =C45+D45 -> 9.578 | F45: =F44 -> 0.0442 | G45: =E45/((100%-F45)) -> 10.020925 | I45: =VLOOKUP(B45,'fixed cost'!$B$4:$R$116,17,0) -> 0 | O45: =SUM(G45:N45) -> 10.020925 | P45: 9.578 | Q45: =C45-P45 -> 0 | R45: =Q45/P45 -> 0
A46: =A45+1 -> 37 | B46: KAWAS (LNG) | C46: =C45 -> 9.578 | D46: =D45 -> 0 | E46: =C46+D46 -> 9.578 | F46: =F45 -> 0.0442 | G46: =E46/((100%-F46)) -> 10.020925 | I46: =VLOOKUP(B46,'fixed cost'!$B$4:$R$116,17,0) -> 0 | M46: =VLOOKUP(B46,'fixed cost'!$B$4:$H$116,7,0) -> 0.85915096 | O46: =SUM(G46:N46) -> 10.880076 | P46: 9.578 | Q46: =C46-P46 -> 0 | R46: =Q46/P46 -> 0
A47: =A46+1 -> 38 | B47: KAWAS (Liquid) | C47: 24.043 | E47: =C47+D47 -> 24.043 | F47: =F46 -> 0.0442 | G47: =E47/((100%-F47)) -> 25.154844 | I47: =VLOOKUP(B47,'fixed cost'!$B$4:$R$116,17,0) -> 0 | O47: =SUM(G47:N47) -> 25.154844 | P47: 24.043 | Q47: =C47-P47 -> 0 | R47: =Q47/P47 -> 0
A48: =A47+1 -> 39 | B48: KAWAS (Liquid) | C48: =C47 -> 24.043 | D48: =D47 -> 0 | E48: =C48+D48 -> 24.043 | F48: =F47 -> 0.0442 | G48: =E48/((100%-F48)) -> 25.154844 | I48: =VLOOKUP(B48,'fixed cost'!$B$4:$R$116,17,0) -> 0 | M48: =VLOOKUP(B48,'fixed cost'!$B$4:$H$116,7,0) -> 0.85915096 | O48: =SUM(G48:N48) -> 26.013995 | P48: 24.043 | Q48: =C48-P48 -> 0 | R48: =Q48/P48 -> 0
A49: =A46+1 -> 38 | B49: KAWAS (NAPM) | C49: 35.627 | E49: =C49+D49 -> 35.627 | F49: =F48 -> 0.0442 | G49: =E49/((100%-F49)) -> 37.274534 | I49: =VLOOKUP(B49,'fixed cost'!$B$4:$R$116,17,0) -> 0 | O49: =SUM(G49:N49) -> 37.274534 | P49: 35.627 | Q49: =C49-P49 -> 0 | R49: =Q49/P49 -> 0
A50: =A49+1 -> 39 | B50: KAWAS (NAPM) | C50: =C49 -> 35.627 | D50: =D49 -> 0 | E50: =E49 -> 35.627 | F50: =F49 -> 0.0442 | G50: =E50/((100%-F50)) -> 37.274534 | I50: =VLOOKUP(B50,'fixed cost'!$B$4:$R$116,17,0) -> 0 | M50: =VLOOKUP(B50,'fixed cost'!$B$4:$H$116,7,0) -> 0.85915096 | O50: =SUM(G50:N50) -> 38.133685 | P50: 35.627 | Q50: =C50-P50 -> 0 | R50: =Q50/P50 -> 0
A51: =A48+1 -> 40 | B51: Khargone | C51: 3.201 | D51: -0.023 | E51: =C51+D51 -> 3.178 | F51: =F50 -> 0.0442 | G51: =E51/((100%-F51)) -> 3.3249634 | H51: 0.15 | I51: =VLOOKUP(B51,'fixed cost'!$B$4:$R$116,17,0) -> 0.052785 | L51: 0.062 | O51: =SUM(G51:N51) -> 3.5897484 | P51: 3.323 | Q51: =C51-P51 -> -0.122 | R51: =Q51/P51 -> -0.036713813
A52: =A51+1 -> 41 | B52: Khargone | C52: =C51 -> 3.201 | D52: =D51 -> -0.023 | E52: =C52+D52 -> 3.178 | F52: =F51 -> 0.0442 | G52: =E52/((100%-F52)) -> 3.3249634 | H52: =H51 -> 0.15 | I52: =VLOOKUP(B52,'fixed cost'!$B$4:$R$116,17,0) -> 0.052785 | L52: =L51 -> 0.062 | M52: =VLOOKUP(B52,'fixed cost'!$B$4:$H$116,7,0) -> 2.0731461 | O52: =SUM(G52:N52) -> 5.6628945 | P52: 3.323 | Q52: =C52-P52 -> -0.122 | R52: =Q52/P52 -> -0.036713813
A53: =A52+1 -> 42 | B53: KSTPS | C53: 1.317 | D53: 0.001 | E53: =C53+D53 -> 1.318 | F53: =F52 -> 0.0442 | G53: =E53/((100%-F53)) -> 1.3789496 | I53: =VLOOKUP(B53,'fixed cost'!$B$4:$R$116,17,0) -> 0.13208364 | O53: =SUM(G53:N53) -> 1.5110332 | P53: 1.273 | Q53: =C53-P53 -> 0.044 | R53: =Q53/P53 -> 0.034564022
A54: =A53+1 -> 43 | B54: KSTPS | C54: =C53 -> 1.317 | D54: =D53 -> 0.001 | E54: =C54+D54 -> 1.318 | F54: =F53 -> 0.0442 | G54: =E54/((100%-F54)) -> 1.3789496 | I54: =VLOOKUP(B54,'fixed cost'!$B$4:$R$116,17,0) -> 0.13208364 | M54: =VLOOKUP(B54,'fixed cost'!$B$4:$H$116,7,0) -> 0.75506732 | O54: =SUM(G54:N54) -> 2.2661005 | P54: 1.273 | Q54: =C54-P54 -> 0.044 | R54: =Q54/P54 -> 0.034564022
A55: =A54+1 -> 44 | B55: =B54 -> KSTPS | C55: =C54 -> 1.317 | D55: =D54 -> 0.001 | E55: =C55+D55 -> 1.318 | F55: =F54 -> 0.0442 | G55: =E55/((100%-F55)) -> 1.3789496 | I55: =VLOOKUP(B55,'fixed cost'!$B$4:$R$116,17,0) -> 0.13208364 | N55: 0.55 | O55: =SUM(G55:N55) -> 2.0610332 | P55: 1.273 | Q55: =C55-P55 -> 0.044 | R55: =Q55/P55 -> 0.034564022
A56: =A55+1 -> 45 | B56: =B55 -> KSTPS | C56: =C55 -> 1.317 | D56: =D55 -> 0.001 | E56: =C56+D56 -> 1.318 | F56: =F55 -> 0.0442 | G56: =E56/((100%-F56)) -> 1.3789496 | I56: =VLOOKUP(B56,'fixed cost'!$B$4:$R$116,17,0) -> 0.13208364 | N56: 0.75 | O56: =SUM(G56:N56) -> 2.2610332 | P56: 1.273 | Q56: =C56-P56 -> 0.044 | R56: =Q56/P56 -> 0.034564022
A57: =A55+1 -> 45 | B57: KSTPS-III | C57: 1.292 | D57: 0.00099 | E57: =C57+D57 -> 1.29299 | F57: =F56 -> 0.0442 | G57: =E57/((100%-F57)) -> 1.352783 | I57: =VLOOKUP(B57,'fixed cost'!$B$4:$R$116,17,0) -> 0.11369475 | O57: =SUM(G57:N57) -> 1.4664778 | P57: 1.248 | Q57: =C57-P57 -> 0.044 | R57: =Q57/P57 -> 0.03525641
A58: =A57+1 -> 46 | B58: KSTPS-III | C58: =C57 -> 1.292 | D58: =D57 -> 0.00099 | E58: =C58+D58 -> 1.29299 | F58: =F57 -> 0.0442 | G58: =E58/((100%-F58)) -> 1.352783 | I58: =VLOOKUP(B58,'fixed cost'!$B$4:$R$116,17,0) -> 0.11369475 | M58: =VLOOKUP(B58,'fixed cost'!$B$4:$H$116,7,0) -> 1.1259324 | O58: =SUM(G58:N58) -> 2.5924101 | P58: 1.248 | Q58: =C58-P58 -> 0.044 | R58: =Q58/P58 -> 0.03525641
A59: =A58+1 -> 47 | B59: =B58 -> KSTPS-III | C59: =C58 -> 1.292 | D59: =D58 -> 0.00099 | E59: =C59+D59 -> 1.29299 | F59: =F58 -> 0.0442 | G59: =E59/((100%-F59)) -> 1.352783 | I59: =VLOOKUP(B59,'fixed cost'!$B$4:$R$116,17,0) -> 0.11369475 | N59: 0.55 | O59: =SUM(G59:N59) -> 2.0164778 | P59: 1.248 | Q59: =C59-P59 -> 0.044 | R59: =Q59/P59 -> 0.03525641
A60: =A59+1 -> 48 | B60: =B59 -> KSTPS-III | C60: =C59 -> 1.292 | D60: =D59 -> 0.00099 | E60: =C60+D60 -> 1.29299 | F60: =F59 -> 0.0442 | G60: =E60/((100%-F60)) -> 1.352783 | I60: =VLOOKUP(B60,'fixed cost'!$B$4:$R$116,17,0) -> 0.11369475 | N60: 0.75 | O60: =SUM(G60:N60) -> 2.2164778 | P60: 1.248 | Q60: =C60-P60 -> 0.044 | R60: =Q60/P60 -> 0.03525641
A61: =A59+1 -> 48 | B61: Korba Power Ltd. (FSA) | C61: 1.728 | D61: 0.004 | E61: =C61+D61 -> 1.732 | F61: =F60 -> 0.0442 | G61: =E61/((100%-F61)) -> 1.8120946 | I61: =VLOOKUP(B61,'fixed cost'!$B$4:$R$116,17,0) -> 0.05337 | J61: 0.1 | O61: =SUM(G61:N61) -> 1.9654646 | P61: 1.789 | Q61: =C61-P61 -> -0.061 | R61: =Q61/P61 -> -0.034097261
A62: =A60+1 -> 49 | B62: Korba Power Ltd. (Non - FSA) | C62: 11.531 | E62: =C62+D62 -> 11.531 | F62: =F61 -> 0.0442 | G62: =E62/((100%-F62)) -> 12.064239 | I62: =VLOOKUP(B62,'fixed cost'!$B$4:$R$116,17,0) -> 0.05337 | J62: 0.1 | O62: =SUM(G62:N62) -> 12.217609 | P62: 11.531 | Q62: =C62-P62 -> 0 | R62: =Q62/P62 -> 0
A63: =A61+1 -> 49 | B63: Korba Power Ltd. (Imported Coal) | C63: 15.63 | E63: =C63+D63 -> 15.63 | F63: =F62 -> 0.0442 | G63: =E63/((100%-F63)) -> 16.352793 | I63: =I62 -> 0.05337 | J63: 0.1 | O63: =SUM(G63:N63) -> 16.506163 | P63: 15.63 | Q63: =C63-P63 -> 0 | R63: =Q63/P63 -> 0
A64: =A61+1 -> 49 | B64: Lara | C64: 1.224 | D64: 0.002 | E64: =C64+D64 -> 1.226 | F64: =F61 -> 0.0442 | G64: =E64/((100%-F64)) -> 1.2826951 | I64: =VLOOKUP(B64,'fixed cost'!$B$4:$R$116,17,0) -> 0.11369475 | L64: 0.039 | O64: =SUM(G64:N64) -> 1.4353899 | P64: 1.214 | Q64: =C64-P64 -> 0.01 | R64: =Q64/P64 -> 0.0082372323
A65: =A64+1 -> 50 | B65: Lara | C65: =C64 -> 1.224 | D65: =D64 -> 0.002 | E65: =C65+D65 -> 1.226 | F65: =F64 -> 0.0442 | G65: =E65/((100%-F65)) -> 1.2826951 | I65: =VLOOKUP(B65,'fixed cost'!$B$4:$R$116,17,0) -> 0.11369475 | L65: =L64 -> 0.039 | M65: =VLOOKUP(B65,'fixed cost'!$B$4:$H$116,7,0) -> 2.2835364 | O65: =SUM(G65:N65) -> 3.7189263 | P65: 1.214 | Q65: =C65-P65 -> 0.01 | R65: =Q65/P65 -> 0.0082372323
A66: =A65+1 -> 51 | B66: Lara | C66: =C65 -> 1.224 | D66: =D65 -> 0.002 | E66: =C66+D66 -> 1.226 | F66: =F65 -> 0.0442 | G66: =E66/((100%-F66)) -> 1.2826951 | I66: =VLOOKUP(B66,'fixed cost'!$B$4:$R$116,17,0) -> 0.11369475 | L66: =L65 -> 0.039 | N66: 0.55 | O66: =SUM(G66:N66) -> 1.9853899 | P66: 1.214 | Q66: =C66-P66 -> 0.01 | R66: =Q66/P66 -> 0.0082372323
A67: =A66+1 -> 52 | B67: Lara | C67: =C66 -> 1.224 | D67: =D66 -> 0.002 | E67: =C67+D67 -> 1.226 | F67: =F66 -> 0.0442 | G67: =E67/((100%-F67)) -> 1.2826951 | I67: =VLOOKUP(B67,'fixed cost'!$B$4:$R$116,17,0) -> 0.11369475 | L67: =L66 -> 0.039 | N67: 0.75 | O67: =SUM(G67:N67) -> 2.1853899 | P67: 1.214 | Q67: =C67-P67 -> 0.01 | R67: =Q67/P67 -> 0.0082372323
A68: =A65+1 -> 51 | B68: Madikhera HPS | C68: 1.425 | E68: =C68+D68 -> 1.425 | G68: =E68/((100%-F68)) -> 1.425 | I68: =VLOOKUP(B68,'fixed cost'!$B$4:$R$116,17,0) -> 0 | O68: =SUM(G68:N68) -> 1.425 | P68: 1.425 | Q68: =C68-P68 -> 0 | R68: =Q68/P68 -> 0
A69: =A68+1 -> 52 | B69: Mauda-I | C69: 3.226 | D69: -0.036 | E69: =C69+D69 -> 3.19 | F69: =F65 -> 0.0442 | G69: =E69/((100%-F69)) -> 3.3375183 | I69: =VLOOKUP(B69,'fixed cost'!$B$4:$R$116,17,0) -> 0 | O69: =SUM(G69:N69) -> 3.3375183 | P69: 3.166 | Q69: =C69-P69 -> 0.06 | R69: =Q69/P69 -> 0.018951358
A70: =A69+1 -> 53 | B70: Mauda-I | C70: =C69 -> 3.226 | D70: =D69 -> -0.036 | E70: =C70+D70 -> 3.19 | F70: =F69 -> 0.0442 | G70: =E70/((100%-F70)) -> 3.3375183 | I70: =VLOOKUP(B70,'fixed cost'!$B$4:$R$116,17,0) -> 0 | M70: =VLOOKUP(B70,'fixed cost'!$B$4:$H$116,7,0) -> 1.6931572 | O70: =SUM(G70:N70) -> 5.0306755 | P70: 3.166 | Q70: =C70-P70 -> 0.06 | R70: =Q70/P70 -> 0.018951358
A71: =A70+1 -> 54 | B71: Mauda-II | C71: 3.152 | D71: -0.0349 | E71: =C71+D71 -> 3.1171 | F71: =F70 -> 0.0442 | G71: =E71/((100%-F71)) -> 3.2612471 | I71: =VLOOKUP(B71,'fixed cost'!$B$4:$R$116,17,0) -> 0 | L71: 0.071 | O71: =SUM(G71:N71) -> 3.3322471 | P71: 3.147 | Q71: =C71-P71 -> 0.005 | R71: =Q71/P71 -> 0.0015888147
A72: =A71+1 -> 55 | B72: Mauda-II | C72: =C71 -> 3.152 | D72: =D71 -> -0.0349 | E72: =C72+D72 -> 3.1171 | F72: =F71 -> 0.0442 | G72: =E72/((100%-F72)) -> 3.2612471 | I72: =VLOOKUP(B72,'fixed cost'!$B$4:$R$116,17,0) -> 0 | L72: =L71 -> 0.071 | M72: =VLOOKUP(B72,'fixed cost'!$B$4:$H$116,7,0) -> 1.5812064 | O72: =SUM(G72:N72) -> 4.9134535 | P72: 3.147 | Q72: =C72-P72 -> 0.005 | R72: =Q72/P72 -> 0.0015888147
A73: =A72+1 -> 56 | B73: MB Power | C73: 2.951 | E73: =C73+D73 -> 2.951 | F73: =F72 -> 0.0442 | G73: =E73/((100%-F73)) -> 3.087466 | H73: 0.15 | I73: =VLOOKUP(B73,'fixed cost'!$B$4:$R$116,17,0) -> 0.047625 | L73: 0.042 | O73: =SUM(G73:N73) -> 3.327091 | P73: 2.868 | Q73: =C73-P73 -> 0.083 | R73: =Q73/P73 -> 0.028940028
A74: =A73+1 -> 57 | B74: Orient Green Power (Biomass) | C74: 4.38 | E74: =C74+D74 -> 4.38 | G74: =E74/((100%-F74)) -> 4.38 | I74: =VLOOKUP(B74,'fixed cost'!$B$4:$R$116,17,0) -> 0 | O74: =SUM(G74:N74) -> 4.38 | P74: 4.38 | Q74: =C74-P74 -> 0 | R74: =Q74/P74 -> 0
A75: =A74+1 -> 58 | B75: Pench HPS | C75: 0.584 | E75: =C75+D75 -> 0.584 | G75: =E75/((100%-F75)) -> 0.584 | I75: =VLOOKUP(B75,'fixed cost'!$B$4:$R$116,17,0) -> 0 | O75: =SUM(G75:N75) -> 0.584 | P75: 0.584 | Q75: =C75-P75 -> 0 | R75: =Q75/P75 -> 0
A76: =A75+1 -> 59 | B76: R P sagar (Inter state project) | C76: 1.51 | E76: =C76+D76 -> 1.51 | G76: =E76/((100%-F76)) -> 1.51 | I76: =VLOOKUP(B76,'fixed cost'!$B$4:$R$116,17,0) -> 0 | O76: =SUM(G76:N76) -> 1.51 | P76: 1.51 | Q76: =C76-P76 -> 0 | R76: =Q76/P76 -> 0
A77: =A76+1 -> 60 | B77: Rajghat HPS | C77: 0.984 | E77: =C77+D77 -> 0.984 | G77: =E77/((100%-F77)) -> 0.984 | I77: =VLOOKUP(B77,'fixed cost'!$B$4:$R$116,17,0) -> 0 | O77: =SUM(G77:N77) -> 0.984 | P77: 0.984 | Q77: =C77-P77 -> 0 | R77: =Q77/P77 -> 0
A78: =A77+1 -> 61 | B78: Sasan | C78: 1.1495327 | E78: =C78+D78 -> 1.1495327 | F78: =F73 -> 0.0442 | G78: =E78/((100%-F78)) -> 1.2026917 | H78: 0.15 | I78: =VLOOKUP(B78,'fixed cost'!$B$4:$R$116,17,0) -> 0.038347439 | L78: 0.165 | O78: =SUM(G78:N78) -> 1.5560391 | P78: 1.1495327 | Q78: =C78-P78 -> 0 | R78: =Q78/P78 -> 0
A79: =A78+1 -> 62 | B79: Sasan | C79: =C78 -> 1.1495327 | D79: =D78 -> 0 | E79: =C79+D79 -> 1.1495327 | F79: =F78 -> 0.0442 | G79: =E79/((100%-F79)) -> 1.2026917 | H79: 0.15 | I79: =VLOOKUP(B79,'fixed cost'!$B$4:$R$116,17,0) -> 0.038347439 | L79: =L78 -> 0.165 | M79: =VLOOKUP(B79,'fixed cost'!$B$4:$H$116,7,0) -> 0.16570016 | O79: =SUM(G79:N79) -> 1.7217393 | P79: 1.1495327 | Q79: =C79-P79 -> 0 | R79: =Q79/P79 -> 0
A80: =A79+1 -> 63 | B80: SGTPS -1x500 | C80: 2.399 | D80: -0.002 | E80: =C80+D80 -> 2.397 | G80: =E80/((100%-F80)) -> 2.397 | I80: =VLOOKUP(B80,'fixed cost'!$B$4:$R$116,17,0) -> 0 | O80: =SUM(G80:N80) -> 2.397 | P80: 2.377 | Q80: =C80-P80 -> 0.022 | R80: =Q80/P80 -> 0.0092553639
A81: =A80+1 -> 64 | B81: SGTPS -1x500 | C81: =C80 -> 2.399 | E81: =C81+D81 -> 2.399 | G81: =E81/((100%-F81)) -> 2.399 | I81: =VLOOKUP(B81,'fixed cost'!$B$4:$R$116,17,0) -> 0 | N81: 0.55 | O81: =SUM(G81:N81) -> 2.949 | P81: 2.377 | Q81: =C81-P81 -> 0.022 | R81: =Q81/P81 -> 0.0092553639
A82: =A81+1 -> 65 | B82: SGTPS -1x500 | C82: =C81 -> 2.399 | E82: =C82+D82 -> 2.399 | G82: =E82/((100%-F82)) -> 2.399 | I82: =VLOOKUP(B82,'fixed cost'!$B$4:$R$116,17,0) -> 0 | N82: 0.75 | O82: =SUM(G82:N82) -> 3.149 | P82: 2.377 | Q82: =C82-P82 -> 0.022 | R82: =Q82/P82 -> 0.0092553639
A83: =A81+1 -> 65 | B83: SGTPS -4x210 | C83: 3.064 | D83: 0.003 | E83: =C83+D83 -> 3.067 | G83: =E83/((100%-F83)) -> 3.067 | I83: =VLOOKUP(B83,'fixed cost'!$B$4:$R$116,17,0) -> 0 | O83: =SUM(G83:N83) -> 3.067 | P83: 3.064 | Q83: =C83-P83 -> 0 | R83: =Q83/P83 -> 0
A84: =A83+1 -> 66 | B84: SIPAT I | C84: 1.212 | D84: -0.00799 | E84: =C84+D84 -> 1.20401 | F84: =F79 -> 0.0442 | G84: =E84/((100%-F84)) -> 1.2596882 | I84: =VLOOKUP(B84,'fixed cost'!$B$4:$R$116,17,0) -> 0.11823725 | L84: 0.034 | O84: =SUM(G84:N84) -> 1.4119255 | P84: 1.212 | Q84: =C84-P84 -> 0 | R84: =Q84/P84 -> 0
A85: =A84+1 -> 67 | B85: SIPAT I | C85: =C84 -> 1.212 | D85: =D84 -> -0.00799 | E85: =C85+D85 -> 1.20401 | F85: =F84 -> 0.0442 | G85: =E85/((100%-F85)) -> 1.2596882 | I85: =VLOOKUP(B85,'fixed cost'!$B$4:$R$116,17,0) -> 0.11823725 | L85: =L84 -> 0.034 | M85: =VLOOKUP(B85,'fixed cost'!$B$4:$H$116,7,0) -> 1.2557147 | O85: =SUM(G85:N85) -> 2.6676402 | P85: 1.212 | Q85: =C85-P85 -> 0 | R85: =Q85/P85 -> 0
A86: =A85+1 -> 68 | B86: =B85 -> SIPAT I | C86: =C85 -> 1.212 | D86: =D85 -> -0.00799 | E86: =C86+D86 -> 1.20401 | F86: =F85 -> 0.0442 | G86: =E86/((100%-F86)) -> 1.2596882 | I86: =VLOOKUP(B86,'fixed cost'!$B$4:$R$116,17,0) -> 0.11823725 | L86: =L85 -> 0.034 | N86: 0.55 | O86: =SUM(G86:N86) -> 1.9619255 | P86: 1.212 | Q86: =C86-P86 -> 0 | R86: =Q86/P86 -> 0
A87: =A86+1 -> 69 | B87: =B86 -> SIPAT I | C87: =C86 -> 1.212 | D87: =D86 -> -0.00799 | E87: =C87+D87 -> 1.20401 | F87: =F86 -> 0.0442 | G87: =E87/((100%-F87)) -> 1.2596882 | I87: =VLOOKUP(B87,'fixed cost'!$B$4:$R$116,17,0) -> 0.11823725 | L87: =L86 -> 0.034 | N87: 0.75 | O87: =SUM(G87:N87) -> 2.1619255 | P87: 1.212 | Q87: =C87-P87 -> 0 | R87: =Q87/P87 -> 0
A88: =A86+1 -> 69 | B88: SIPAT II | C88: 1.249 | D88: -0.00799 | E88: =C88+D88 -> 1.24101 | F88: =F87 -> 0.0442 | G88: =E88/((100%-F88)) -> 1.2983992 | I88: =VLOOKUP(B88,'fixed cost'!$B$4:$R$116,17,0) -> 0.11823725 | O88: =SUM(G88:N88) -> 1.4166365 | P88: 1.249 | Q88: =C88-P88 -> 0 | R88: =Q88/P88 -> 0
A89: =A88+1 -> 70 | B89: SIPAT II | C89: =C88 -> 1.249 | D89: =D88 -> -0.00799 | E89: =C89+D89 -> 1.24101 | F89: =F88 -> 0.0442 | G89: =E89/((100%-F89)) -> 1.2983992 | I89: =VLOOKUP(B89,'fixed cost'!$B$4:$R$116,17,0) -> 0.11823725 | M89: =VLOOKUP(B89,'fixed cost'!$B$4:$H$116,7,0) -> 0.98415242 | O89: =SUM(G89:N89) -> 2.4007889 | P89: 1.249 | Q89: =C89-P89 -> 0 | R89: =Q89/P89 -> 0
A90: =A89+1 -> 71 | B90: =B89 -> SIPAT II | C90: =C89 -> 1.249 | D90: =D89 -> -0.00799 | E90: =C90+D90 -> 1.24101 | F90: =F89 -> 0.0442 | G90: =E90/((100%-F90)) -> 1.2983992 | I90: =VLOOKUP(B90,'fixed cost'!$B$4:$R$116,17,0) -> 0.11823725 | N90: 0.55 | O90: =SUM(G90:N90) -> 1.9666365 | P90: 1.249 | Q90: =C90-P90 -> 0 | R90: =Q90/P90 -> 0
A91: =A90+1 -> 72 | B91: =B90 -> SIPAT II | C91: =C90 -> 1.249 | D91: =D90 -> -0.00799 | E91: =C91+D91 -> 1.24101 | F91: =F90 -> 0.0442 | G91: =E91/((100%-F91)) -> 1.2983992 | I91: =VLOOKUP(B91,'fixed cost'!$B$4:$R$116,17,0) -> 0.11823725 | N91: 0.75 | O91: =SUM(G91:N91) -> 2.1666365 | P91: 1.249 | Q91: =C91-P91 -> 0 | R91: =Q91/P91 -> 0
A92: =A90+1 -> 72 | B92: Solapur I | C92: 3.94 | D92: 0.022 | E92: =C92+D92 -> 3.962 | F92: =F91 -> 0.0442 | G92: =E92/((100%-F92)) -> 4.1452187 | I92: =VLOOKUP(B92,'fixed cost'!$B$4:$R$116,17,0) -> 0 | L92: 0.096 | O92: =SUM(G92:N92) -> 4.2412187 | P92: 3.957 | Q92: =C92-P92 -> -0.017 | R92: =Q92/P92 -> -0.004296184
A93: =A92+1 -> 73 | B93: Solapur I | C93: =C92 -> 3.94 | D93: =D92 -> 0.022 | E93: =C93+D93 -> 3.962 | F93: =F92 -> 0.0442 | G93: =E93/((100%-F93)) -> 4.1452187 | I93: =VLOOKUP(B93,'fixed cost'!$B$4:$R$116,17,0) -> 0 | L93: =L92 -> 0.096 | M93: =VLOOKUP(B93,'fixed cost'!$B$4:$H$116,7,0) -> 1.9962859 | O93: =SUM(G93:N93) -> 6.2375045 | P93: 3.957 | Q93: =C93-P93 -> -0.017 | R93: =Q93/P93 -> -0.004296184
A94: =A93+1 -> 74 | B94: SSP | C94: 0.82 | E94: =C94+D94 -> 0.82 | F94: =F93 -> 0.0442 | G94: =E94/((100%-F94)) -> 0.85792007 | I94: =VLOOKUP(B94,'fixed cost'!$B$4:$R$116,17,0) -> 0 | O94: =SUM(G94:N94) -> 0.85792007 | P94: 0.82 | Q94: =C94-P94 -> 0 | R94: =Q94/P94 -> 0
A95: =A94+1 -> 75 | B95: SSTPS Khandwa (Singaji) | C95: 3.126 | D95: 0.001 | E95: =C95+D95 -> 3.127 | G95: =E95/((100%-F95)) -> 3.127 | I95: =VLOOKUP(B95,'fixed cost'!$B$4:$R$116,17,0) -> 0 | O95: =SUM(G95:N95) -> 3.127 | P95: 3.169 | Q95: =C95-P95 -> -0.043 | R95: =Q95/P95 -> -0.013568949
A96: =A95+1 -> 76 | B96: SSTPS Khandwa (Singaji) # 3 & 4 | C96: 2.927 | D96: -0.001 | E96: =C96+D96 -> 2.926 | G96: =E96/((100%-F96)) -> 2.926 | I96: =VLOOKUP(B96,'fixed cost'!$B$4:$R$116,17,0) -> 0 | O96: =SUM(G96:N96) -> 2.926 | P96: 2.916 | Q96: =C96-P96 -> 0.011 | R96: =Q96/P96 -> 0.0037722908
A97: =A96+1 -> 77 | B97: STPS Sarni | C97: 0 | D97: 0 | E97: =C97+D97 -> 0 | G97: =E97/((100%-F97)) -> 0 | I97: =VLOOKUP(B97,'fixed cost'!$B$4:$R$116,17,0) -> 0 | O97: =SUM(G97:N97) -> 0 | P97: 0 | Q97: =C97-P97 -> 0 | R97: =Q97/P97 -> #DIV/0!
A98: =A97+1 -> 78 | B98: STPS Sarni 10 & 11 | C98: 2.779 | D98: 0.007 | E98: =C98+D98 -> 2.786 | G98: =E98/((100%-F98)) -> 2.786 | I98: =VLOOKUP(B98,'fixed cost'!$B$4:$R$116,17,0) -> 0 | O98: =SUM(G98:N98) -> 2.786 | P98: 2.917 | Q98: =C98-P98 -> -0.138 | R98: =Q98/P98 -> -0.047308879
A99: =A98+1 -> 79 | B99: STPS Sarni 10 & 11 | C99: =C98 -> 2.779 | D99: =D98 -> 0.007 | E99: =C99+D99 -> 2.786 | G99: =E99/((100%-F99)) -> 2.786 | I99: =VLOOKUP(B99,'fixed cost'!$B$4:$R$116,17,0) -> 0 | N99: 0.55 | O99: =SUM(G99:N99) -> 3.336 | P99: 2.917 | Q99: =C99-P99 -> -0.138 | R99: =Q99/P99 -> -0.047308879
A100: =A99+1 -> 80 | B100: STPS Sarni 10 & 11 | C100: =C99 -> 2.779 | D100: =D99 -> 0.007 | E100: =C100+D100 -> 2.786 | G100: =E100/((100%-F100)) -> 2.786 | I100: =VLOOKUP(B100,'fixed cost'!$B$4:$R$116,17,0) -> 0 | N100: 0.75 | O100: =SUM(G100:N100) -> 3.536 | P100: 2.917 | Q100: =C100-P100 -> -0.138 | R100: =Q100/P100 -> -0.047308879
A101: =A99+1 -> 80 | B101: Torrent (Indigenous) | C101: 7.243 | E101: =C101+D101 -> 7.243 | F101: =F94 -> 0.0442 | G101: =E101/((100%-F101)) -> 7.5779452 | I101: =VLOOKUP(B101,'fixed cost'!$B$4:$R$116,17,0) -> 0 | J101: 0.1 | O101: =SUM(G101:N101) -> 7.6779452 | P101: 8.834 | Q101: =C101-P101 -> -1.591 | R101: =Q101/P101 -> -0.18009962
...

Sheet URS 4
A1: Details of URS power purchase cost per unit for MOD for the month of March 2026
A2: Sr. No. | B2: Name of Generating Stations | C2: Energy Charges Rate for MOD Purpose Rs./kwh | D2: FCA/ MOPA in Rs./kwh | E2: Effective Energy Charges in (Rs./kwh) | F2: Transmission Losses beyond MP Periphery | G2: Variable cost incl. losses | H2: Cess on Intrastate sales | I2: ED & Cess on Auxiliary Consumption | J2: FGD / Change in Law | K2: Transmission charges | L2: Normative fixed cost for URS | M2: Variable rate at MP periphery in Rs./kwh
G4: (Rs. per kwh)
A5: A | B5: B | C5: C | D5: D | E5: E=C+D | F5: F | G5: G=E/((100%-F)) | H5: H | I5: I | J5: J | K5: K | L5: L | M5: M=sum(G:L)
A6: 1 | B6: KAWAS (NAPM) | C6: 35.627 | D6: 0 | E6: =C6+D6 -> 35.627 | F6: 0.0442 | G6: =E6/((100%-F6)) -> 37.274534 | I6: 0 | L6: 0.85915096 | M6: =SUM(G6:L6) -> 38.133685 | N6: 5.5743143 | O6: =M6-N6 -> 32.559371
A7: =+A6+1 -> 2 | B7: GANDHAR (NAPM) | C7: 29.718 | D7: 0 | E7: =C7+D7 -> 29.718 | F7: 0.0442 | G7: =E7/((100%-F7)) -> 31.092279 | I7: 0 | L7: 1.0465902 | M7: =SUM(G7:L7) -> 32.138869 | N7: 3.2347421 | O7: =M7-N7 -> 28.904127
A8: =+A7+1 -> 3 | B8: KAWAS (Liquid) | C8: 24.043 | D8: 0 | E8: =C8+D8 -> 24.043 | F8: 0.0442 | G8: =E8/((100%-F8)) -> 25.154844 | I8: 0 | L8: 0.85915096 | M8: =SUM(G8:L8) -> 26.013995 | N8: 10.344671 | O8: =M8-N8 -> 15.669324
A9: =+A8+1 -> 4 | B9: Dadri Liquid (NR) | C9: 23.874 | D9: 0 | E9: =C9+D9 -> 23.874 | F9: 0.0442 | G9: =E9/((100%-F9)) -> 24.978029 | I9: 0 | L9: 0.52960707 | M9: =SUM(G9:L9) -> 25.507636 | N9: 14.612506 | O9: =M9-N9 -> 10.89513
A10: =+A9+1 -> 5 | B10: Auraiya Liquid (NR) | C10: 18.689 | E10: =C10+D10 -> 18.689 | F10: 0.0442 | G10: =E10/((100%-F10)) -> 19.553254 | I10: 0 | L10: 0.635 | M10: =SUM(G10:L10) -> 20.188254 | N10: 32.041584 | O10: =M10-N10 -> -11.85333
A11: =+A10+1 -> 6 | B11: Anta Liquid (NR) | C11: 17.498 | E11: =C11+D11 -> 17.498 | F11: 0.0442 | G11: =E11/((100%-F11)) -> 18.307177 | I11: 0 | L11: 0.709 | M11: =SUM(G11:L11) -> 19.016177 | N11: 3.798754 | O11: =M11-N11 -> 15.217423
A12: =+A11+1 -> 7 | B12: GANDHAR (LNG) | C12: 9.693 | D12: 3.353 | E12: =C12+D12 -> 13.046 | F12: 0.0442 | G12: =E12/((100%-F12)) -> 13.649299 | I12: 0 | L12: 1.0465902 | M12: =SUM(G12:L12) -> 14.695889 | N12: 2.5247747 | O12: =M12-N12 -> 12.171115
A13: =+A12+1 -> 8 | B13: Auraiya CLNG (NR) | C13: 12.268 | E13: =C13+D13 -> 12.268 | F13: 0.0442 | G13: =E13/((100%-F13)) -> 12.835321 | I13: 0 | L13: 0.635 | M13: =SUM(G13:L13) -> 13.470321 | N13: 10.197908 | O13: =M13-N13 -> 3.2724135
A14: =+A13+1 -> 9 | B14: Dadri Comm LNG (NR) | C14: 11.683 | D14: 0 | E14: =C14+D14 -> 11.683 | F14: 0.0442 | G14: =E14/((100%-F14)) -> 12.223268 | I14: 0 | L14: 0.52960707 | M14: =SUM(G14:L14) -> 12.752876 | N14: 10.848721 | O14: =M14-N14 -> 1.9041543
A15: =+A14+1 -> 10 | B15: Auraiya LNG (NR) | C15: 11.402 | E15: =C15+D15 -> 11.402 | F15: 0.0442 | G15: =E15/((100%-F15)) -> 11.929274 | I15: 0 | L15: 0.635 | M15: =SUM(G15:L15) -> 12.564274 | N15: 25.935288 | O15: =M15-N15 -> -13.371014
A16: =+A15+1 -> 11 | B16: Anta LNG (NR) | C16: 11.266 | E16: =C16+D16 -> 11.266 | F16: 0.0442 | G16: =E16/((100%-F16)) -> 11.786985 | I16: 0 | L16: 0.709 | M16: =SUM(G16:L16) -> 12.495985 | N16: 38.017057 | O16: =M16-N16 -> -25.521072
A17: =+A16+1 -> 12 | B17: Dadri LNG (NR) | C17: 10.859 | D17: 0 | E17: =C17+D17 -> 10.859 | F17: 0.0442 | G17: =E17/((100%-F17)) -> 11.361163 | I17: 0 | L17: 0.52960707 | M17: =SUM(G17:L17) -> 11.89077 | N17: 5.7807333 | O17: =M17-N17 -> 6.1100372
A18: =+A17+1 -> 13 | B18: KAWAS (LNG) | C18: 9.578 | D18: 0 | E18: =C18+D18 -> 9.578 | F18: 0.0442 | G18: =E18/((100%-F18)) -> 10.020925 | I18: 0 | L18: 0.85915096 | M18: =SUM(G18:L18) -> 10.880076 | N18: 2.2158952 | O18: =M18-N18 -> 8.6641806
A19: =+A18+1 -> 14 | B19: GANDHAR (CLNG) | C19: 8.915 | D19: 0 | E19: =C19+D19 -> 8.915 | F19: 0.0442 | G19: =E19/((100%-F19)) -> 9.3272651 | I19: 0 | L19: 1.0465902 | M19: =SUM(G19:L19) -> 10.373855 | N19: 2.5422867 | O19: =M19-N19 -> 7.8315687
A20: =+A19+1 -> 15 | B20: Anta CLNG (NR) | C20: 9.189 | E20: =C20+D20 -> 9.189 | F20: 0.0442 | G20: =E20/((100%-F20)) -> 9.613936 | I20: 0 | L20: 0.709 | M20: =SUM(G20:L20) -> 10.322936 | N20: 3.7064832 | O20: =M20-N20 -> 6.6164528
A21: =+A20+1 -> 16 | B21: KAWAS (CLNG) | C21: 8.954 | E21: =C21+D21 -> 8.954 | F21: 0.0442 | G21: =E21/((100%-F21)) -> 9.3680686 | I21: 0 | L21: 0.85915096 | M21: =SUM(G21:L21) -> 10.22722 | N21: 4.9576545 | O21: =M21-N21 -> 5.2695651
A22: =+A21+1 -> 17 | B22: Ghatampur Thermal Power Station (NUPPL) | C22: 3.412 | D22: 0 | E22: =C22+D22 -> 3.412 | F22: 0.0442 | G22: =E22/((100%-F22)) -> 3.5697845 | J22: 0 | L22: 3.3963081 | M22: =SUM(G22:L22) -> 6.9660926 | N22: 4.8270345 | O22: =M22-N22 -> 2.1390581
A23: =+A22+1 -> 18 | B23: Solapur I | C23: 3.94 | D23: 0.022 | E23: =C23+D23 -> 3.962 | F23: 0.0442 | G23: =E23/((100%-F23)) -> 4.1452187 | I23: 0 | J23: 0.096 | L23: 1.9962859 | M23: =SUM(G23:L23) -> 6.2375045 | N23: 1.7179762 | O23: =M23-N23 -> 4.5195283
A24: =+A23+1 -> 19 | B24: Gadarwara | C24: 3.119 | D24: 0.032 | E24: =C24+D24 -> 3.151 | F24: 0.0442 | G24: =E24/((100%-F24)) -> 3.2967148 | H24: 0.15 | I24: 0.058995 | J24: 0.65 | L24: 2.0601461 | M24: =SUM(G24:L24) -> 6.2158559 | N24: 2.6636987 | O24: =M24-N24 -> 3.5521572
A25: =+A24+1 -> 20 | B25: Indira Gandhi STPS (Jhajjar) (NR) | C25: 4.158 | D25: 0.031 | E25: =C25+D25 -> 4.189 | F25: 0.0442 | G25: =E25/((100%-F25)) -> 4.382716 | I25: 0 | L25: 1.56 | M25: =SUM(G25:L25) -> 5.942716 | N25: 2.3967263 | O25: =M25-N25 -> 3.5459897
A26: =+A25+1 -> 21 | B26: Khargone | C26: 3.201 | D26: -0.023 | E26: =C26+D26 -> 3.178 | F26: 0.0442 | G26: =E26/((100%-F26)) -> 3.3249634 | H26: 0.15 | I26: 0.052785 | J26: 0.062 | L26: 2.0731461 | M26: =SUM(G26:L26) -> 5.6628945 | N26: 6.245265 | O26: =M26-N26 -> -0.58237053
A27: =+A26+1 -> 22 | B27: Unchahar II (NR) | C27: 3.386 | D27: 0.19299 | E27: =C27+D27 -> 3.57899 | F27: 0.0442 | G27: =E27/((100%-F27)) -> 3.7444968 | I27: 0 | J27: 0.7 | L27: 1.1206832 | M27: =SUM(G27:L27) -> 5.56518 | N27: 3.4828769 | O27: =M27-N27 -> 2.0823031
A28: =+A27+1 -> 23 | B28: Meja (NR) | C28: 2.966 | D28: 0 | E28: =C28+D28 -> 2.966 | F28: 0.0442 | G28: =E28/((100%-F28)) -> 3.1031597 | I28: 0 | L28: 2.2494753 | M28: =SUM(G28:L28) -> 5.3526349 | N28: 3.5840453 | O28: =M28-N28 -> 1.7685896
A29: =+A28+1 -> 24 | B29: Unchahar IV (NR) | C29: 3.173 | D29: 0.158 | E29: =C29+D29 -> 3.331 | F29: 0.0442 | G29: =E29/((100%-F29)) -> 3.4850387 | I29: 0 | J29: 0.066 | L29: 1.6577601 | M29: =SUM(G29:L29) -> 5.2087988 | N29: 3.3512485 | O29: =M29-N29 -> 1.8575503
A30: =+A29+1 -> 25 | B30: Tanda II | C30: 2.851 | D30: 0.063 | E30: =C30+D30 -> 2.914 | F30: 0.0442 | G30: =E30/((100%-F30)) -> 3.048755 | I30: 0 | K30: 0.23259 | L30: 1.7669774 | M30: =SUM(G30:L30) -> 5.0483224 | N30: 4.0635438 | O30: =M30-N30 -> 0.98477853
A31: =+A30+1 -> 26 | B31: Mauda-I | C31: 3.226 | D31: -0.036 | E31: =C31+D31 -> 3.19 | F31: 0.0442 | G31: =E31/((100%-F31)) -> 3.3375183 | I31: 0 | L31: 1.6931572 | M31: =SUM(G31:L31) -> 5.0306755 | N31: 3.88687 | O31: =M31-N31 -> 1.1438055
A32: =+A31+1 -> 27 | B32: Mauda-II | C32: 3.152 | D32: -0.0349 | E32: =C32+D32 -> 3.1171 | F32: 0.0442 | G32: =E32/((100%-F32)) -> 3.2612471 | I32: 0 | J32: 0.071 | L32: 1.5812064 | M32: =SUM(G32:L32) -> 4.9134535 | N32: 2.8001556 | O32: =M32-N32 -> 2.1132979
A33: =+A32+1 -> 28 | B33: Unchahar III (NR) | C33: 3.339 | D33: 0.119 | E33: =C33+D33 -> 3.458 | F33: 0.0442 | G33: =E33/((100%-F33)) -> 3.6179117 | I33: 0 | J33: 0.071 | L33: 1.2090519 | M33: =SUM(G33:L33) -> 4.8979636 | N33: 10.381507 | O33: =M33-N33 -> -5.4835437
A34: =+A33+1 -> 29 | B34: National Capital Thermal Power Station Dadri II (NR) | C34: 3.72 | D34: 0.165 | E34: =C34+D34 -> 3.885 | F34: 0.0442 | G34: =E34/((100%-F34)) -> 4.0646579 | I34: 0 | J34: 0.06 | L34: 0.65153793 | M34: =SUM(G34:L34) -> 4.7761958 | N34: 12.270327 | O34: =M34-N34 -> -7.4941308
A35: =+A34+1 -> 30 | B35: Unchahar I (NR) | C35: 3.35 | D35: 0.115 | E35: =C35+D35 -> 3.465 | F35: 0.0442 | G35: =E35/((100%-F35)) -> 3.6252354 | I35: 0 | J35: 0.074 | L35: 1.0459098 | M35: =SUM(G35:L35) -> 4.7451452 | N35: 18.958896 | O35: =M35-N35 -> -14.213751
A36: =+A35+1 -> 31 | B36: VSTPS-IV | C36: 1.984 | D36: -0.001 | E36: =C36+D36 -> 1.983 | F36: 0.0442 | G36: =E36/((100%-F36)) -> 2.0747018 | H36: 0.15 | I36: 0.058719 | J36: 0.036 | L36: 1.6494464 | M36: =SUM(G36:L36) -> 3.9688673 | N36: 2.8095932 | O36: =M36-N36 -> 1.159274
A37: =+A36+1 -> 32 | B37: VSTPS-V | C37: 1.862 | D37: -0.001 | E37: =C37+D37 -> 1.861 | F37: 0.0442 | G37: =E37/((100%-F37)) -> 1.9470601 | H37: 0.15 | I37: 0.0709734 | L37: 1.7249287 | M37: =SUM(G37:L37) -> 3.8929622 | N37: 19.993573 | O37: =M37-N37 -> -16.100611
A38: =+A37+1 -> 33 | B38: KAHALGAON-II | C38: 2.702 | D38: 0.05799 | E38: =C38+D38 -> 2.75999 | F38: 0.0442 | G38: =E38/((100%-F38)) -> 2.8876229 | I38: 0 | L38: 0.92016616 | M38: =SUM(G38:L38) -> 3.8077891 | N38: 12.332956 | O38: =M38-N38 -> -8.5251667
A39: =+A38+1 -> 34 | B39: Lara | C39: 1.224 | D39: 0.002 | E39: =C39+D39 -> 1.226 | F39: 0.0442 | G39: =E39/((100%-F39)) -> 1.2826951 | I39: 0.11369475 | J39: 0.039 | L39: 2.2835364 | M39: =SUM(G39:L39) -> 3.7189263 | N39: 10.565121 | O39: =M39-N39 -> -6.8461947
A40: =+A39+1 -> 35 | B40: Khurja STPP | C40: 2.023 | D40: 0 | E40: =C40+D40 -> 2.023 | F40: 0.0442 | G40: =E40/((100%-F40)) -> 2.1165516 | I40: 0 | J40: 0 | L40: 1.3848414 | M40: =SUM(G40:L40) -> 3.501393 | N40: 2.6676964 | O40: =M40-N40 -> 0.83369665
A41: =+A40+1 -> 36 | B41: VSTPS-I | C41: 2.113 | D41: 0.0109 | E41: =C41+D41 -> 2.1239 | F41: 0.0442 | G41: =E41/((100%-F41)) -> 2.2221176 | H41: 0.15 | I41: 0.091908 | L41: 0.9173352 | M41: =SUM(G41:L41) -> 3.3813608 | N41: 25.429482 | O41: =M41-N41 -> -22.048121
A42: =+A41+1 -> 37 | B42: VSTPS-III | C42: 2.007 | D42: -0.001 | E42: =C42+D42 -> 2.006 | F42: 0.0442 | G42: =E42/((100%-F42)) -> 2.0987654 | H42: 0.15 | I42: 0.058719 | J42: 0.035 | L42: 0.91111985 | M42: =SUM(G42:L42) -> 3.2536043 | N42: 11.657058 | O42: =M42-N42 -> -8.4034538
A43: =+A42+1 -> 38 | B43: GANDHAR (APM) | C43: 2.098 | D43: 0 | E43: =C43+D43 -> 2.098 | F43: 0.0442 | G43: =E43/((100%-F43)) -> 2.1950199 | I43: 0 | L43: 1.0465902 | M43: =SUM(G43:L43) -> 3.2416101 | N43: 10.015423 | O43: =M43-N43 -> -6.7738126
A44: =+A43+1 -> 39 | B44: VSTPS-II | C44: 2.024 | D44: -0.0009 | E44: =C44+D44 -> 2.0231 | F44: 0.0442 | G44: =E44/((100%-F44)) -> 2.1166562 | H44: 0.15 | I44: 0.0668886 | J44: 0.037 | L44: 0.78386922 | M44: =SUM(G44:L44) -> 3.154414 | N44: 5.8684063 | O44: =M44-N44 -> -2.7139923
A45: =+A44+1 -> 40 | B45: Rihand III (NR) | C45: 1.603 | D45: -0.042 | E45: =C45+D45 -> 1.561 | F45: 0.0442 | G45: =E45/((100%-F45)) -> 1.6331869 | I45: 0 | L45: 1.4694115 | M45: =SUM(G45:L45) -> 3.1025984 | N45: 5.4128044 | O45: =M45-N45 -> -2.310206
A46: =+A45+1 -> 41 | B46: Auraiya APM (NR) | C46: 2.085 | E46: =C46+D46 -> 2.085 | F46: 0.0442 | G46: =E46/((100%-F46)) -> 2.1814187 | I46: 0 | L46: 0.635 | M46: =SUM(G46:L46) -> 2.8164187 | N46: 4.5610986 | O46: =M46-N46 -> -1.7446799
A47: =+A46+1 -> 42 | B47: Singrauli (NR) | C47: 1.974 | D47: -0.0129 | E47: =C47+D47 -> 1.9611 | F47: 0.0442 | G47: =E47/((100%-F47)) -> 2.0517891 | I47: 0 | L47: 0.76384627 | M47: =SUM(G47:L47) -> 2.8156353 | N47: 2.5691176 | O47: =M47-N47 -> 0.24651778
A48: =+A47+1 -> 43 | B48: Anta APM (NR) | C48: 2.005 | E48: =C48+D48 -> 2.005 | F48: 0.0442 | G48: =E48/((100%-F48)) -> 2.0977192 | I48: 0 | L48: 0.709 | M48: =SUM(G48:L48) -> 2.8067192 | N48: 2.5054645 | O48: =M48-N48 -> 0.30125468
A49: =+A48+1 -> 44 | B49: Dadri APM (NR) | C49: 2.05 | D49: 0 | E49: =C49+D49 -> 2.05 | F49: 0.0442 | G49: =E49/((100%-F49)) -> 2.1448002 | I49: 0 | L49: 0.52960707 | M49: =SUM(G49:L49) -> 2.6744072 | N49: 3.1725822 | O49: =M49-N49 -> -0.49817491
A50: =+A49+1 -> 45 | B50: SIPAT I | C50: 1.212 | D50: -0.00799 | E50: =C50+D50 -> 1.20401 | F50: 0.0442 | G50: =E50/((100%-F50)) -> 1.2596882 | I50: 0.11823725 | J50: 0.034 | L50: 1.2557147 | M50: =SUM(G50:L50) -> 2.6676402 | N50: 2.7007466 | O50: =M50-N50 -> -0.033106386
A51: =+A50+1 -> 46 | B51: KSTPS-III | C51: 1.292 | D51: 0.00099 | E51: =C51+D51 -> 1.29299 | F51: 0.0442 | G51: =E51/((100%-F51)) -> 1.352783 | I51: 0.11369475 | L51: 1.1259324 | M51: =SUM(G51:L51) -> 2.5924101 | N51: 4.9344965 | O51: =M51-N51 -> -2.3420864
A52: =+A51+1 -> 47 | B52: KAWAS (APM) | C52: 1.597 | D52: 0 | E52: =C52+D52 -> 1.597 | F52: 0.0442 | G52: =E52/((100%-F52)) -> 1.6708516 | I52: 0 | L52: 0.85915096 | M52: =SUM(G52:L52) -> 2.5300026 | N52: 4.8683023 | O52: =M52-N52 -> -2.3382997
A53: =+A52+1 -> 48 | B53: Rihand I (NR) | C53: 1.634 | D53: -0.0399 | E53: =C53+D53 -> 1.5941 | F53: 0.0442 | G53: =E53/((100%-F53)) -> 1.6678175 | I53: 0 | L53: 0.83038165 | M53: =SUM(G53:L53) -> 2.4981992 | N53: 4.9702765 | O53: =M53-N53 -> -2.4720773
A54: =+A53+1 -> 49 | B54: Rihand II (NR) | C54: 1.621 | D54: -0.039 | E54: =C54+D54 -> 1.582 | F54: 0.0442 | G54: =E54/((100%-F54)) -> 1.655158 | I54: 0 | L54: 0.77934853 | M54: =SUM(G54:L54) -> 2.4345065 | N54: 5.0231437 | O54: =M54-N54 -> -2.5886372
A55: =+A54+1 -> 50 | B55: SIPAT II | C55: 1.249 | D55: -0.00799 | E55: =C55+D55 -> 1.24101 | F55: 0.0442 | G55: =E55/((100%-F55)) -> 1.2983992 | I55: 0.11823725 | L55: 0.98415242 | M55: =SUM(G55:L55) -> 2.4007889 | N55: 5.2477422 | O55: =M55-N55 -> -2.8469532
A56: =+A55+1 -> 51 | B56: KSTPS | C56: 1.317 | D56: 0.001 | E56: =C56+D56 -> 1.318 | F56: 0.0442 | G56: =E56/((100%-F56)) -> 1.3789496 | I56: 0.13208364 | L56: 0.75506732 | M56: =SUM(G56:L56) -> 2.2661005 | N56: 6.9257199 | O56: =M56-N56 -> -4.6596194
A57: =+A56+1 -> 52 | B57: Sasan | C57: 1.1495327 | D57: 0 | E57: =C57+D57 -> 1.1495327 | F57: 0.0442 | G57: =E57/((100%-F57)) -> 1.2026917 | H57: 0.15 | I57: 0.038347439 | J57: 0.165 | L57: 0.16570016 | M57: =SUM(G57:L57) -> 1.7217393 | N57: 3.4947705 | O57: =M57-N57 -> -1.7730312

Sheet Excl URS 3 
A1: Details of power purchase cost per unit of Thermal and Gas Power stations for MOD for the month of March 2026
A2: Sr. No. | B2: Name of Generating Stations | C2: Energy Charges Rate for MOD Purpose Rs./kwh | D2: FCA Rs./kwh | E2: Effective Energy Charges (Rs./kwh) | F2: Transmission Losses beyond MP Periphery | G2: Variable cost incl. losses | H2: Cess on Intrastate sales | I2: ED & Cess on Auxiliary Consumption | J2: Trading Margin | K2: Transmission charges | L2: FGD / Change in Law | M2: Incentive p.u. | N2: Effective rate in Rs./kwh
G4: (Rs. per kwh)
A5: A | B5: B | C5: C | D5: D | E5: E=C+D | F5: F | G5: G=E/(100%-F) | H5: H | I5: I | J5: J | K5: K | L5: L | M5: M | N5: N=sum(H:L)
A6: 1 | B6: Indira Gandhi STPS (Jhajjar) (NR) | C6: 4.158 | D6: 0.031 | E6: =C6+D6 -> 4.189 | F6: 0.0442 | G6: =E6/((100%-F6)) -> 4.382716 | I6: 0 | L6: 0.065 | N6: =SUM(G6:M6) -> 4.447716 | O6: 3.849 | P6: =N6-O6 -> 0.59871605 | Q6: =N6-N7 -> 0.0032192927 | R6: =N6-N7 -> 0.0032192927 | S6: =N6-N7 -> 0.0032192927 | T6: 3.914 | U6: =N6-T6 -> 0.53371605 | V6: 1.657 | W6: =N6-V6 -> 2.790716 | X6: 1.929 | Y6: =N6-X6 -> 2.518716 | Z6: 1.866 | AA6: =N6-Z6 -> 2.581716 | AB6: 1.913 | AC6: =N6-AB6 -> 2.534716
A7: =+A6+1 -> 2 | B7: Unchahar II (NR) | C7: 3.386 | D7: 0.19299 | E7: =C7+D7 -> 3.57899 | F7: 0.0442 | G7: =E7/((100%-F7)) -> 3.7444968 | I7: 0 | L7: 0.7 | N7: =SUM(G7:M7) -> 4.4444968 | O7: 3.415474 | P7: =N7-O7 -> 1.0290227 | Q7: =N7-#REF! -> #REF! | R7: =N7-#REF! -> #REF! | S7: =N7-#REF! -> #REF! | T7: 3.849 | U7: =N7-T7 -> 0.59549676 | V7: 4.21901 | W7: =N7-V7 -> 0.22548676 | X7: 4.39601 | Y7: =N7-X7 -> 0.048486757 | Z7: 4.12601 | AA7: =N7-Z7 -> 0.31848676 | AB7: 3.99101 | AC7: =N7-AB7 -> 0.45348676
A8: =+A7+1 -> 3 | B8: Solapur I | C8: 3.94 | D8: 0.022 | E8: =C8+D8 -> 3.962 | F8: 0.0442 | G8: =E8/((100%-F8)) -> 4.1452187 | I8: 0 | L8: 0.096 | N8: =SUM(G8:M8) -> 4.2412187 | O8: 2.9165641 | P8: =N8-O8 -> 1.3246546 | Q8: =N8-N9 -> 0.085508871 | R8: =N8-N9 -> 0.085508871 | S8: =N8-N9 -> 0.085508871 | T8: 2.8281883 | U8: =N8-T8 -> 1.4130303 | V8: 4.09701 | W8: =N8-V8 -> 0.14420866 | X8: 3.6690126 | Y8: =N8-X8 -> 0.57220604 | Z8: 3.9690348 | AA8: =N8-Z8 -> 0.27218389 | AB8: 3.002403 | AC8: =N8-AB8 -> 1.2388157
A9: =+A8+1 -> 4 | B9: Gadarwara | C9: 3.119 | D9: 0.032 | E9: =C9+D9 -> 3.151 | F9: 0.0442 | G9: =E9/((100%-F9)) -> 3.2967148 | H9: 0.15 | I9: 0.058995 | L9: 0.65 | N9: =SUM(G9:M9) -> 4.1557098 | O9: 2.872606 | P9: =N9-O9 -> 1.2831038 | Q9: =N9-N10 -> 0.031051916 | R9: =N9-N10 -> 0.031051916 | S9: =N9-N10 -> 0.031051916 | T9: 1.9803711 | U9: =N9-T9 -> 2.1753387 | V9: 4.4699081 | W9: =N9-V9 -> -0.31419833 | X9: 2.739526 | Y9: =N9-X9 -> 1.4161838 | Z9: 2.7337724 | AA9: =N9-Z9 -> 1.4219374 | AB9: 2.7136212 | AC9: =N9-AB9 -> 1.4420886
A10: =+A9+1 -> 5 | B10: National Capital Thermal Power Station Dadri II (NR) | C10: 3.72 | D10: 0.165 | E10: =C10+D10 -> 3.885 | F10: 0.0442 | G10: =E10/((100%-F10)) -> 4.0646579 | I10: 0 | L10: 0.06 | N10: =SUM(G10:M10) -> 4.1246579 | O10: 2.7761089 | P10: =N10-O10 -> 1.348549 | Q10: =N10-N11 -> 0.14264788 | R10: =N10-N11 -> 0.14264788 | S10: =N10-N11 -> 0.14264788 | T10: 2.6892371 | U10: =N10-T10 -> 1.4354208 | V10: 2.6781305 | W10: =N10-V10 -> 1.4465274 | X10: 3.7395601 | Y10: =N10-X10 -> 0.38509782 | Z10: 3.4913975 | AA10: =N10-Z10 -> 0.63326035 | AB10: 3.5141681 | AC10: =N10-AB10 -> 0.61048975
A11: =+A10+1 -> 6 | B11: BLA | C11: 3.752 | E11: =C11+D11 -> 3.752 | G11: =E11/((100%-F11)) -> 3.752 | H11: 0.15 | I11: 0.08001 | N11: =SUM(G11:M11) -> 3.98201 | O11: 3.31 | P11: =N11-O11 -> 0.67201 | Q11: =N11-N12 -> 0.2827746 | R11: =N11-N12 -> 0.2827746 | S11: =N11-N12 -> 0.2827746 | T11: 1.6656273 | U11: =N11-T11 -> 2.3163827 | V11: 5.000485 | W11: =N11-V11 -> -1.018475 | X11: 1.6507969 | Y11: =N11-X11 -> 2.3312131 | Z11: 2.2107482 | AA11: =N11-Z11 -> 1.7712618 | AB11: 2.1881519 | AC11: =N11-AB11 -> 1.7938581
A12: =+A11+1 -> 7 | B12: Unchahar I (NR) | C12: 3.35 | D12: 0.115 | E12: =C12+D12 -> 3.465 | F12: 0.0442 | G12: =E12/((100%-F12)) -> 3.6252354 | I12: 0 | L12: 0.074 | N12: =SUM(G12:M12) -> 3.6992354 | O12: 0.65704658 | P12: =N12-O12 -> 3.0421888 | Q12: =N12-N13 -> 0.010323708 | R12: =N12-N13 -> 0.010323708 | S12: =N12-N13 -> 0.010323708 | T12: 2.5527492 | U12: =N12-T12 -> 1.1464862 | V12: 2.9233935 | W12: =N12-V12 -> 0.77584194 | X12: 3.2052681 | Y12: =N12-X12 -> 0.49396734 | Z12: 3.0952055 | AA12: =N12-Z12 -> 0.60402993 | AB12: 2.8503546 | AC12: =N12-AB12 -> 0.84888079
A13: =+A12+1 -> 8 | B13: Unchahar III (NR) | C13: 3.339 | D13: 0.119 | E13: =C13+D13 -> 3.458 | F13: 0.0442 | G13: =E13/((100%-F13)) -> 3.6179117 | I13: 0 | L13: 0.071 | N13: =SUM(G13:M13) -> 3.6889117 | O13: 2.1547486 | P13: =N13-O13 -> 1.5341631 | Q13: =N13-N14 -> 0.098141697 | R13: =N13-N14 -> 0.098141697 | S13: =N13-N14 -> 0.098141697 | T13: 1.6698888 | U13: =N13-T13 -> 2.0190229 | V13: 3.85077 | W13: =N13-V13 -> -0.1618583 | X13: 3.11177 | Y13: =N13-X13 -> 0.5771417 | Z13: 3.22177 | AA13: =N13-Z13 -> 0.4671417 | AB13: 3.59077 | AC13: =N13-AB13 -> 0.098141697
A14: =+A13+1 -> 9 | B14: JP Bina | C14: 3.376 | E14: =C14+D14 -> 3.376 | G14: =E14/((100%-F14)) -> 3.376 | H14: 0.15 | I14: 0.06477 | N14: =SUM(G14:M14) -> 3.59077 | O14: 2.872606 | P14: =N14-O14 -> 0.71816396 | Q14: =N14-N16 -> 0.020985526 | R14: =N14-N16 -> 0.020985526 | S14: =N14-N16 -> 0.020985526 | T14: 2.6954734 | U14: =N14-T14 -> 0.89529656 | V14: 0.80423025 | W14: =N14-V14 -> 2.7865397 | X14: 0.82030928 | Y14: =N14-X14 -> 2.7704607 | Z14: 0.92340858 | AA14: =N14-Z14 -> 2.6673614 | AB14: 0.89922486 | AC14: =N14-AB14 -> 2.6915451
A15: =+A14+1 -> 10 | B15: Khargone | C15: 3.201 | D15: -0.023 | E15: =C15+D15 -> 3.178 | F15: 0.0442 | G15: =E15/((100%-F15)) -> 3.3249634 | H15: 0.15 | I15: 0.052785 | L15: 0.062 | N15: =SUM(G15:M15) -> 3.5897484 | Z15: 2.9314963 | AA15: =N15-Z15 -> 0.65825207 | AB15: 2.8785878 | AC15: =N15-AB15 -> 0.71116056
A16: =+A15+1 -> 11 | B16: Ghatampur Thermal Power Station (NUPPL) | C16: 3.412 | E16: =C16+D16 -> 3.412 | F16: 0.0442 | G16: =E16/((100%-F16)) -> 3.5697845 | N16: =SUM(G16:M16) -> 3.5697845 | O16: 2.9216755 | P16: =N16-O16 -> 0.64810901 | Q16: =N16-N17 -> 0.018745763 | R16: =N16-N17 -> 0.018745763 | S16: =N16-N17 -> 0.018745763 | T16: 3.372 | U16: =N16-T16 -> 0.19778447 | V16: 4.0528543 | W16: =N16-V16 -> -0.48306987 | X16: 3.1649762 | Y16: =N16-X16 -> 0.40480828 | Z16: 1.682824 | AA16: =N16-Z16 -> 1.8869604 | AB16: 1.6656237 | AC16: =N16-AB16 -> 1.9041608
A17: =+A16+1 -> 12 | B17: Unchahar IV (NR) | C17: 3.173 | D17: 0.158 | E17: =C17+D17 -> 3.331 | F17: 0.0442 | G17: =E17/((100%-F17)) -> 3.4850387 | I17: 0 | L17: 0.066 | N17: =SUM(G17:M17) -> 3.5510387 | O17: 1.5871379 | P17: =N17-O17 -> 1.9639008 | Q17: =N17-N18 -> 0.080745763 | R17: =N17-N18 -> 0.080745763 | S17: =N17-N18 -> 0.080745763 | T17: 0.70503586 | U17: =N17-T17 -> 2.8460029 | V17: 1.650989 | W17: =N17-V17 -> 1.9000497 | X17: 1.6528669 | Y17: =N17-X17 -> 1.8981718 | Z17: 3.8486111 | AA17: =N17-Z17 -> -0.29757242 | AB17: 3.7075873 | AC17: =N17-AB17 -> -0.15654854
A18: =+A17+1 -> 13 | B18: DVC (DTPS) (STOA LOI) | C18: 3.085 | D18: 0.165 | E18: =C18+D18 -> 3.25 | F18: 0.0442 | G18: =E18/((100%-F18)) -> 3.4002929 | I18: 0 | K18: 0 | L18: 0.07 | N18: =SUM(G18:M18) -> 3.4702929 | O18: 1.5590809 | P18: =N18-O18 -> 1.9112121 | Q18: =N18-N15 -> -0.11945543 | R18: =N18-N15 -> -0.11945543 | S18: =N18-N15 -> -0.11945543 | T18: 2.1505041 | U18: =N18-T18 -> 1.3197888 | V18: 1.6072498 | W18: =N18-V18 -> 1.8630432 | X18: 3.9069721 | Y18: =N18-X18 -> -0.43667913 | Z18: 1.4397759 | AA18: =N18-Z18 -> 2.030517 | AB18: 1.4608279 | AC18: =N18-AB18 -> 2.009465
A19: =+A18+1 -> 14 | B19: Tanda II | C19: 2.851 | D19: 0.063 | E19: =C19+D19 -> 2.914 | F19: 0.0442 | G19: =E19/((100%-F19)) -> 3.048755 | I19: 0 | K19: 0.23259 | L19: 0.064 | N19: =SUM(G19:M19) -> 3.345345 | O19: 2.4071804 | P19: =N19-O19 -> 0.93816455 | Q19: =N19-N20 -> 0.0078266604 | R19: =N19-N20 -> 0.0078266604 | S19: =N19-N20 -> 0.0078266604 | T19: 2.6057582 | U19: =N19-T19 -> 0.73958673 | V19: 3.9901661 | W19: =N19-V19 -> -0.64482116 | X19: 1.4282624 | Y19: =N19-X19 -> 1.9170826 | Z19: 1.3981942 | AA19: =N19-Z19 -> 1.9471507 | AB19: 1.4163543 | AC19: =N19-AB19 -> 1.9289906
A20: =+A19+1 -> 15 | B20: Mauda-I | C20: 3.226 | D20: -0.036 | E20: =C20+D20 -> 3.19 | F20: 0.0442 | G20: =E20/((100%-F20)) -> 3.3375183 | I20: 0 | N20: =SUM(G20:M20) -> 3.3375183 | O20: 3.4208333 | P20: =N20-O20 -> -0.083314982 | Q20: =N20-N21 -> 0.0052711864 | R20: =N20-N21 -> 0.0052711864 | S20: =N20-N21 -> 0.0052711864 | T20: 1.6800748 | U20: =N20-T20 -> 1.6574435 | V20: 3.3451423 | W20: =N20-V20 -> -0.0076239819 | X20: 2.1743698 | Y20: =N20-X20 -> 1.1631485 | Z20: 2.3230223 | AA20: =N20-Z20 -> 1.014496 | AB20: 2.0234159 | AC20: =N20-AB20 -> 1.3141024
A21: =+A20+1 -> 16 | B21: Mauda-II | C21: 3.152 | D21: -0.0349 | E21: =C21+D21 -> 3.1171 | F21: 0.0442 | G21: =E21/((100%-F21)) -> 3.2612471 | I21: 0 | L21: 0.071 | N21: =SUM(G21:M21) -> 3.3322471 | O21: 3.4980879 | P21: =N21-O21 -> -0.16584076 | Q21: =N21-N22 -> 0.0051561258 | R21: =N21-N22 -> 0.0051561258 | S21: =N21-N22 -> 0.0051561258 | T21: 2.8181218 | U21: =N21-T21 -> 0.51412531 | V21: 1.5394732 | W21: =N21-V21 -> 1.7927739 | X21: 1.5617854 | Y21: =N21-X21 -> 1.7704617 | Z21: 1.3907327 | AA21: =N21-Z21 -> 1.9415144 | AB21: 1.4229467 | AC21: =N21-AB21 -> 1.9093004
A22: =+A21+1 -> 17 | B22: MB Power | C22: 2.951 | E22: =C22+D22 -> 2.951 | F22: 0.0442 | G22: =E22/((100%-F22)) -> 3.087466 | H22: 0.15 | I22: 0.047625 | L22: 0.042 | N22: =SUM(G22:M22) -> 3.327091 | O22: 2.5944007 | P22: =N22-O22 -> 0.73269032 | Q22: =N22-N23 -> 0.200091 | R22: =N22-N23 -> 0.200091 | S22: =N22-N23 -> 0.200091 | T22: 1.5424592 | U22: =N22-T22 -> 1.7846318 | V22: 2.052 | W22: =N22-V22 -> 1.275091 | X22: 3.2819292 | Y22: =N22-X22 -> 0.04516179 | Z22: 3.0273973 | AA22: =N22-Z22 -> 0.29969374 | AB22: 3.2644973 | AC22: =N22-AB22 -> 0.062593709
A23: =+A22+1 -> 18 | B23: SSTPS Khandwa (Singaji) | C23: 3.126 | D23: 0.001 | E23: =C23+D23 -> 3.127 | G23: =E23/((100%-F23)) -> 3.127 | I23: 0 | N23: =SUM(G23:M23) -> 3.127 | O23: 2.5933627 | P23: =N23-O23 -> 0.53363728 | Q23: =N23-N24 -> 0.033256539 | R23: =N23-N24 -> 0.033256539 | S23: =N23-N24 -> 0.033256539 | T23: 1.5112774 | U23: =N23-T23 -> 1.6157226 | V23: 2.601 | W23: =N23-V23 -> 0.526 | X23: 3.353343 | Y23: =N23-X23 -> -0.22634299 | Z23: 3.0010537 | AA23: =N23-Z23 -> 0.12594626 | AB23: 3.2458281 | AC23: =N23-AB23 -> -0.11882812
A24: =+A23+1 -> 19 | B24: Meja (NR) | C24: 2.966 | D24: -0.009 | E24: =C24+D24 -> 2.957 | F24: 0.0442 | G24: =E24/((100%-F24)) -> 3.0937435 | I24: 0 | N24: =SUM(G24:M24) -> 3.0937435 | O24: 1.5003771 | P24: =N24-O24 -> 1.5933663 | Q24: =N24-N26 -> 0.043942247 | R24: =N24-N26 -> 0.043942247 | S24: =N24-N26 -> 0.043942247 | T24: 1.8335984 | U24: =N24-T24 -> 1.2601451 | V24: 3.2283224 | W24: =N24-V24 -> -0.1345789 | X24: 3.1048906 | Y24: =N24-X24 -> -0.011147116 | Z24: 3.0963163 | AA24: =N24-Z24 -> -0.002572793 | AB24: 3.230864 | AC24: =N24-AB24 -> -0.13712059
A25: =+A24+1 -> 20 | B25: SGTPS -4x210 | C25: 3.064 | D25: 0.003 | E25: =C25+D25 -> 3.067 | G25: =E25/((100%-F25)) -> 3.067 | I25: 0 | N25: =SUM(G25:M25) -> 3.067 | Z25: 1.564657 | AA25: =N25-Z25 -> 1.502343 | AB25: 1.552276 | AC25: =N25-AB25 -> 1.514724
A26: =+A25+1 -> 21 | B26: TRN Energy Pvt. Ltd. (Medium Term) | C26: 3.101 | D26: -0.186 | E26: =C26+D26 -> 2.915 | F26: 0.0442 | G26: =E26/((100%-F26)) -> 3.0498012 | N26: =SUM(G26:M26) -> 3.0498012 | O26: 1.907 | P26: =N26-O26 -> 1.1428012 | Q26: =N26-#REF! -> #REF! | R26: =N26-#REF! -> #REF! | S26: =N26-#REF! -> #REF! | T26: 2.1025881 | U26: =N26-T26 -> 0.94721313 | V26: 3.4801031 | W26: =N26-V26 -> -0.43030189 | X26: 1.5429562 | Y26: =N26-X26 -> 1.506845 | Z26: 2.339 | AA26: =N26-Z26 -> 0.71080121 | AB26: 2.374 | AC26: =N26-AB26 -> 0.67580121
A27: =+A26+1 -> 22 | B27: SSTPS Khandwa (Singaji) # 3 & 4 | C27: 2.927 | D27: -0.001 | E27: =C27+D27 -> 2.926 | G27: =E27/((100%-F27)) -> 2.926 | I27: 0 | N27: =SUM(G27:M27) -> 2.926 | Z27: 2.98 | AA27: =N27-Z27 -> -0.054 | AB27: 3.061 | AC27: =N27-AB27 -> -0.135
A28: =+A27+1 -> 23 | B28: KAHALGAON-II | C28: 2.702 | D28: 0.05799 | E28: =C28+D28 -> 2.75999 | F28: 0.0442 | G28: =E28/((100%-F28)) -> 2.8876229 | I28: 0 | N28: =SUM(G28:M28) -> 2.8876229 | O28: 1.6171688 | P28: =N25-O28 -> 1.4498312 | Q28: =N25-N29 -> 0.18355158 | R28: =N25-N29 -> 0.18355158 | S28: =N25-N29 -> 0.18355158 | T28: 3.0703669 | U28: =N25-T28 -> -0.0033669057 | V28: 3.465 | W28: =N25-V28 -> -0.398 | X28: 2.841 | Y28: =N25-X28 -> 0.226 | Z28: 1.5269496 | AA28: =N28-Z28 -> 1.3606734 | AB28: 1.407984 | AC28: =N28-AB28 -> 1.4796389
A29: =+A28+1 -> 24 | B29: SKS Power Generation (Medium Term) | C29: 2.756 | E29: =C29+D29 -> 2.756 | F29: 0.0442 | G29: =E29/((100%-F29)) -> 2.8834484 | N29: =SUM(G29:M29) -> 2.8834484 | O29: 1.6656119 | P29: =N29-O29 -> 1.2178365 | Q29: =N29-N27 -> -0.04255158 | R29: =N29-N27 -> -0.04255158 | S29: =N29-N27 -> -0.04255158 | T29: 2.6528583 | U29: =N29-T29 -> 0.23059009 | V29: 3.115 | W29: =N29-V29 -> -0.23155158 | X29: 3.088 | Y29: =N29-X29 -> -0.20455158 | Z29: 1.5270992 | AA29: =N29-Z29 -> 1.3563492 | AB29: 1.4125739 | AC29: =N29-AB29 -> 1.4708745
A30: =+A29+1 -> 25 | B30: Jhabua Power | C30: 2.606 | D30: -0.0099 | E30: =C30+D30 -> 2.5961 | F30: 0.0442 | G30: =E30/((100%-F30)) -> 2.716154 | H30: 0.15 | N30: =SUM(G30:M30) -> 2.866154 | O30: 2.681 | P30: =N30-O30 -> 0.18515401 | Q30: =N30-N31 -> 0.080154007 | R30: =N30-N31 -> 0.080154007 | S30: =N30-N31 -> 0.080154007 | T30: 1.5141564 | U30: =N30-T30 -> 1.3519976 | V30: 1.8737889 | W30: =N30-V30 -> 0.99236515 | X30: 4.9058063 | Y30: =N30-X30 -> -2.0396522 | Z30: 4.8413804 | AA30: =N30-Z30 -> -1.9752264 | AB30: 4.2489791 | AC30: =N30-AB30 -> -1.3828251
A31: =+A30+1 -> 26 | B31: STPS Sarni 10 & 11 | C31: 2.779 | D31: 0.007 | E31: =C31+D31 -> 2.786 | G31: =E31/((100%-F31)) -> 2.786 | I31: 0 | N31: =SUM(G31:M31) -> 2.786 | O31: 2.781 | P31: =N31-O31 -> 0.005 | Q31: =N31-N32 -> 0.0009738439 | R31: =N31-N32 -> 0.0009738439 | S31: =N31-N32 -> 0.0009738439 | T31: 1.998 | U31: =N31-T31 -> 0.788 | V31: 1.7904668 | W31: =N31-V31 -> 0.99553321 | X31: 3.306 | Y31: =N31-X31 -> -0.52 | Z31: 3.102 | AA31: =N31-Z31 -> -0.316 | AB31: 3.177 | AC31: =N31-AB31 -> -0.391
A32: =+A31+1 -> 27 | B32: Jindal Power Limited (Medium Term) | C32: 2.67 | D32: -0.161 | E32: =C32+D32 -> 2.509 | F32: 0.0442 | G32: =E32/((100%-F32)) -> 2.6250262 | L32: 0.16 | N32: =SUM(G32:M32) -> 2.7850262 | O32: 2.332 | P32: =N32-O32 -> 0.45302616 | Q32: =N32-N33 -> 0.063358443 | R32: =N32-N33 -> 0.063358443 | S32: =N32-N33 -> 0.063358443 | T32: 2.368 | U32: =N32-T32 -> 0.41702616 | V32: 1.7731048 | W32: =N32-V32 -> 1.0119214 | X32: 3.011 | Y32: =N32-X32 -> -0.22597384 | Z32: 3.039 | AA32: =N32-Z32 -> -0.25397384 | AB32: 2.89 | AC32: =N32-AB32 -> -0.10497384
A33: =+A32+1 -> 28 | B33: Mahan Energen Ltd. (5%) | C33: 2.488 | D33: -0.03 | E33: =C33+D33 -> 2.458 | F33: 0.0442 | G33: =E33/((100%-F33)) -> 2.5716677 | H33: 0.15 | I33: 0 | N33: =SUM(G33:M33) -> 2.7216677 | O33: 2.0943216 | P33: =N33-O33 -> 0.62734611 | Q33: =N33-N34 -> 0.033343796 | R33: =N33-N34 -> 0.033343796 | S33: =N33-N34 -> 0.033343796 | T33: 1.5486956 | U33: =N33-T33 -> 1.1729722 | V33: 1.7534908 | W33: =N33-V33 -> 0.96817687 | X33: 3.614 | Y33: =N33-X33 -> -0.89233229 | Z33: 2.936 | AA33: =N33-Z33 -> -0.21433229 | AB33: 2.921 | AC33: =N33-AB33 -> -0.19933229
A34: =+A33+1 -> 29 | B34: RKM Powergen (Talcher Field) (Medium Term) | C34: 2.5695 | E34: =C34+D34 -> 2.5695 | F34: 0.0442 | G34: =E34/((100%-F34)) -> 2.6883239 | N34: =SUM(G34:M34) -> 2.6883239 | O34: 2.0259908 | P34: =N34-O34 -> 0.6623331 | Q34: =N34-N35 -> 0.047080979 | R34: =N34-N35 -> 0.047080979 | S34: =N34-N35 -> 0.047080979 | T34: 1.5964972 | U34: =N34-T34 -> 1.0918267 | V34: 1.8088725 | W34: =N34-V34 -> 0.87945138 | X34: 2.872 | Y34: =N34-X34 -> -0.18367608 | Z34: 2.6042895 | AA34: =N34-Z34 -> 0.084034463 | AB34: 2.5655417 | AC34: =N34-AB34 -> 0.12278221
A35: =+A34+1 -> 30 | B35: RKM Powergen (IB Field) (Medium Term) | C35: 2.5245 | E35: =C35+D35 -> 2.5245 | F35: 0.0442 | G35: =E35/((100%-F35)) -> 2.6412429 | N35: =SUM(G35:M35) -> 2.6412429 | O35: 2.0094258 | P35: =N35-O35 -> 0.63181716 | Q35: =N35-N36 -> 0.093638837 | R35: =N35-N36 -> 0.093638837 | S35: =N35-N36 -> 0.093638837 | T35: 3.0620518 | U35: =N35-T35 -> -0.42080882 | V35: 2.0703685 | W35: =N35-V35 -> 0.5708744 | X35: 1.8834486 | Y35: =N35-X35 -> 0.75779436 | Z35: 2.4677843 | AA35: =N35-Z35 -> 0.17345866 | AB35: 2.800176 | AC35: =N35-AB35 -> -0.1589331
A36: =+A35+1 -> 31 | B36: Jindal India Thermal Power (Medium Term) | C36: 2.435 | E36: =C36+D36 -> 2.435 | F36: 0.0442 | G36: =E36/((100%-F36)) -> 2.5476041 | N36: =SUM(G36:M36) -> 2.5476041 | O36: 1.9866488 | P36: =N36-O36 -> 0.56095526 | Q36: =N36-N38 -> 0.1506041 | R36: =N36-N38 -> 0.1506041 | S36: =N36-N38 -> 0.1506041 | T36: 2.855 | U36: =N36-T36 -> -0.3073959 | V36: 2.1523692 | W36: =N36-V36 -> 0.39523495 | X36: 1.8027052 | Y36: =N36-X36 -> 0.74489889 | Z36: 2.475542 | AA36: =N36-Z36 -> 0.07206213 | AB36: 2.4401287 | AC36: =N36-AB36 -> 0.10747542
A37: =+A36+1 -> 32 | B37: VSTPS-I | C37: 2.113 | D37: 0.0109 | E37: =C37+D37 -> 2.1239 | F37: 0.0442 | G37: =E37/((100%-F37)) -> 2.2221176 | H37: 0.15 | I37: 0.091908 | N37: =SUM(G37:M37) -> 2.4640256 | Z37: 2.4502522 | AA37: =N37-Z37 -> 0.013773405 | AB37: 2.4140974 | AC37: =N37-AB37 -> 0.049928208
A38: =+A37+1 -> 33 | B38: SGTPS -1x500 | C38: 2.399 | D38: -0.002 | E38: =C38+D38 -> 2.397 | G38: =E38/((100%-F38)) -> 2.397 | I38: 0 | N38: =SUM(G38:M38) -> 2.397 | O38: 2.0425559 | P38: =N38-O38 -> 0.35444414 | Q38: =N38-N37 -> -0.067025598 | R38: =N38-N37 -> -0.067025598 | S38: =N38-N37 -> -0.067025598 | T38: 2.71 | U38: =N38-T38 -> -0.313 | V38: 2.1492722 | W38: =N38-V38 -> 0.24772778 | X38: 1.7800384 | Y38: =N38-X38 -> 0.61696164 | Z38: 2.4917848 | AA38: =N38-Z38 -> -0.09478478 | AB38: 2.4571019 | AC38: =N38-AB38 -> -0.060101894
A39: =+A38+1 -> 34 | B39: VSTPS-II | C39: 2.024 | D39: -0.0009 | E39: =C39+D39 -> 2.0231 | F39: 0.0442 | G39: =E39/((100%-F39)) -> 2.1166562 | H39: 0.15 | I39: 0.0668886 | L39: 0.037 | N39: =SUM(G39:M39) -> 2.3705448 | O39: 3.7038663 | P39: =N39-O39 -> -1.3333215 | Q39: =N39-N40 -> 0.0079099688 | R39: =N39-N40 -> 0.0079099688 | S39: =N39-N40 -> 0.0079099688 | T39: 2.588 | U39: =N39-T39 -> -0.2174552 | V39: 1.6238257 | W39: =N39-V39 -> 0.74671906 | X39: 1.8274932 | Y39: =N39-X39 -> 0.54305158 | Z39: 2.1127503 | AA39: =N39-Z39 -> 0.25779454 | AB39: 2.0911556 | AC39: =N39-AB39 -> 0.27938919
A40: =+A39+1 -> 35 | B40: VSTPS-V | C40: 2.048 | D40: -0.001 | E40: =C40+D40 -> 2.047 | F40: 0.0442 | G40: =E40/((100%-F40)) -> 2.1416614 | H40: 0.15 | I40: 0.0709734 | N40: =SUM(G40:M40) -> 2.3626348 | O40: 3.5840426 | P40: =N40-O40 -> -1.2214077 | Q40: =N40-N41 -> 0.020150403 | R40: =N40-N41 -> 0.020150403 | S40: =N40-N41 -> 0.020150403 | T40: 2.1061376 | U40: =N40-T40 -> 0.25649722 | V40: 1.6062765 | W40: =N40-V40 -> 0.75635838 | X40: 2.0751397 | Y40: =N40-X40 -> 0.28749511 | Z40: 2.1970495 | AA40: =N40-Z40 -> 0.16558531 | AB40: 2.1745932 | AC40: =N40-AB40 -> 0.18804159
A41: =+A40+1 -> 36 | B41: VSTPS-III | C41: 2.007 | D41: -0.001 | E41: =C41+D41 -> 2.006 | F41: 0.0442 | G41: =E41/((100%-F41)) -> 2.0987654 | H41: 0.15 | I41: 0.058719 | L41: 0.035 | N41: =SUM(G41:M41) -> 2.3424844 | O41: 3.7238268 | P41: =N41-O41 -> -1.3813423 | Q41: =N41-N42 -> 0.023063612 | R41: =N41-N42 -> 0.023063612 | S41: =N41-N42 -> 0.023063612 | T41: 2.0333697 | U41: =N41-T41 -> 0.30911472 | V41: 1.5856302 | W41: =N41-V41 -> 0.75685421 | X41: 2.1579383 | Y41: =N41-X41 -> 0.18454612 | Z41: 2.1601686 | AA41: =N41-Z41 -> 0.18231583 | AB41: 2.1380893 | AC41: =N41-AB41 -> 0.20439515
A42: =+A41+1 -> 37 | B42: VSTPS-IV | C42: 1.984 | D42: -0.001 | E42: =C42+D42 -> 1.983 | F42: 0.0442 | G42: =E42/((100%-F42)) -> 2.0747018 | H42: 0.15 | I42: 0.058719 | L42: 0.036 | N42: =SUM(G42:M42) -> 2.3194208 | O42: 0 | P42: =N42-O42 -> 2.3194208 | Q42: =N42-N44 -> 0.13800211 | R42: =N42-N43 -> 0.12440094 | S42: =N42-N43 -> 0.12440094 | T42: 2.0228822 | U42: =N42-T42 -> 0.29653858 | V42: 1.5206978 | W42: =N42-V42 -> 0.79872298 | X42: 2.1217139 | Y42: =N42-X42 -> 0.19770689 | Z42: 4.3546733 | AA42: =N42-Z42 -> -2.0352525 | AB42: 4.3734063 | AC42: =N42-AB42 -> -2.0539855
A43: =+A42+1 -> 38 | B43: GANDHAR (APM) | C43: 2.098 | E43: =C43+D43 -> 2.098 | F43: 0.0442 | G43: =E43/((100%-F43)) -> 2.1950199 | I43: 0 | N43: =SUM(G43:M43) -> 2.1950199 | R43: =N43-N44 -> 0.013601172 | S43: =N43-N44 -> 0.013601172 | T43: 1.9928334 | U43: =N43-T43 -> 0.20218649 | V43: 4.7698176 | W43: =N43-V43 -> -2.5747977 | X43: 4.3966053 | Y43: =N43-X43 -> -2.2015854 | Z43: 2.7976818 | AA43: =N43-Z43 -> -0.60266189 | AB43: 3.2216312 | AC43: =N43-AB43 -> -1.0266113
A44: =+A43+1 -> 39 | B44: Auraiya APM (NR) | C44: 2.085 | E44: =C44+D44 -> 2.085 | F44: 0.0442 | G44: =E44/((100%-F44)) -> 2.1814187 | I44: 0 | N44: =SUM(G44:M44) -> 2.1814187 | O44: 4.1641135 | P44: =N44-O44 -> -1.9826948 | Q44: =N44-N43 -> -0.013601172 | R44: =N44-N45 -> 0.036618539 | S44: =N44-N45 -> 0.036618539 | T44: 2.014671 | U44: =N44-T44 -> 0.16674767 | V44: 5.3731806 | W44: =N44-V44 -> -3.1917618 | X44: 3.0221486 | Y44: =N44-X44 -> -0.84072992 | Z44: 4.785705 | AA44: =N44-Z44 -> -2.6042862 | AB44: 3.9095607 | AC44: =N44-AB44 -> -1.728142
A45: =+A44+1 -> 40 | B45: Dadri APM (NR) | C45: 2.05 | E45: =C45+D45 -> 2.05 | F45: 0.0442 | G45: =E45/((100%-F45)) -> 2.1448002 | I45: 0 | N45: =SUM(G45:M45) -> 2.1448002 | O45: 1.3621614 | P45: =N45-O45 -> 0.7826388 | Q45: =N45-N46 -> 0.028248588 | R45: =N45-N46 -> 0.028248588 | S45: =N45-N46 -> 0.028248588 | T45: 2.0902193 | U45: =N45-T45 -> 0.054580855 | V45: 5.4196346 | W45: =N45-V45 -> -3.2748344 | X45: 4.233078 | Y45: =N45-X45 -> -2.0882779 | Z45: 1.896628 | AA45: =N45-Z45 -> 0.24817214 | AB45: 1.7387359 | AC45: =N45-AB45 -> 0.40606425
A46: =+A45+1 -> 41 | B46: Khurja STPP | C46: 2.023 | E46: =C46+D46 -> 2.023 | F46: 0.0442 | G46: =E46/((100%-F46)) -> 2.1165516 | N46: =SUM(G46:M46) -> 2.1165516 | O46: 1.345537 | P46: =N46-O46 -> 0.77101461 | Q46: =N46-N51 -> 0.44569994 | R46: =N46-N51 -> 0.44569994 | S46: =N46-N51 -> 0.44569994 | T46: 2.1619374 | U46: =N46-T46 -> -0.045385849 | V46: 5.3731806 | W46: =N46-V46 -> -3.256629 | X46: 1.6580418 | Y46: =N46-X46 -> 0.45850977 | Z46: 1.8830348 | AA46: =N46-Z46 -> 0.23351681 | AB46: 1.726116 | AC46: =N46-AB46 -> 0.3904356
A47: =+A46+1 -> 42 | B47: Anta APM (NR) | C47: 2.005 | E47: =C47+D47 -> 2.005 | F47: 0.0442 | G47: =E47/((100%-F47)) -> 2.0977192 | I47: 0 | N47: =SUM(G47:M47) -> 2.0977192 | X47: 1.6539019 | Y47: =N47-X47 -> 0.4438173 | Z47: 1.8609062 | AA47: =N47-Z47 -> 0.23681297 | AB47: 1.7031706 | AC47: =N47-AB47 -> 0.39454856
A48: =+A47+1 -> 43 | B48: Singrauli (NR) | C48: 1.974 | D48: -0.0129 | E48: =C48+D48 -> 1.9611 | F48: 0.0442 | G48: =E48/((100%-F48)) -> 2.0517891 | I48: 0 | N48: =SUM(G48:M48) -> 2.0517891 | X48: 1.6332022 | Y48: =N48-X48 -> 0.41858684 | Z48: 1.9200211 | AA48: =N48-Z48 -> 0.131768 | AB48: 1.9369003 | AC48: =N48-AB48 -> 0.11488879
A49: =+A48+1 -> 44 | B49: Korba Power Ltd. (FSA) | C49: 1.728 | D49: 0.004 | E49: =C49+D49 -> 1.732 | F49: 0.0442 | G49: =E49/((100%-F49)) -> 1.8120946 | I49: 0.05337 | J49: 0.1 | N49: =SUM(G49:M49) -> 1.9654646 | X49: 1.6269923 | Y49: =N49-X49 -> 0.33847224 | Z49: 3.5526595 | AA49: =N49-Z49 -> -1.587195 | AB49: 3.2325191 | AC49: =N49-AB49 -> -1.2670545
A50: =+A49+1 -> 45 | B50: ATPS (210MW) Chachai | C50: 1.829 | D50: 0 | E50: =C50+D50 -> 1.829 | G50: =E50/((100%-F50)) -> 1.829 | I50: 0 | N50: =SUM(G50:M50) -> 1.829 | X50: 3.5015197 | Y50: =N50-X50 -> -1.6725197 | Z50: 3.8877566 | AA50: =N50-Z50 -> -2.0587566 | AB50: 3.8223926 | AC50: =N50-AB50 -> -1.9933926
A51: =+A50+1 -> 46 | B51: KAWAS (APM) | C51: 1.597 | E51: =C51+D51 -> 1.597 | F51: 0.0442 | G51: =E51/((100%-F51)) -> 1.6708516 | I51: 0 | N51: =SUM(G51:M51) -> 1.6708516 | O51: 1.3995663 | P51: =N51-O51 -> 0.27128539 | Q51: =N51-#REF! -> #REF! | R51: =N51-#REF! -> #REF! | S51: =N51-#REF! -> #REF! | T51: 3.4985968 | U51: =N51-T51 -> -1.8277452 | V51: 5.0645195 | W51: =N51-V51 -> -3.3936678 | X51: 4.6170565 | Y51: =N51-X51 -> -2.9462049 | Z51: 4.0056038 | AA51: =N51-Z51 -> -2.3347522 | AB51: 3.8495932 | AC51: =N51-AB51 -> -2.1787416
A52: =+A51+1 -> 47 | B52: Rihand I (NR) | C52: 1.634 | D52: -0.0399 | E52: =C52+D52 -> 1.5941 | F52: 0.0442 | G52: =E52/((100%-F52)) -> 1.6678175 | I52: 0 | N52: =SUM(G52:M52) -> 1.6678175 | Z52: 4.488156 | AA52: =N52-Z52 -> -2.8203384 | AB52: 3.8140918 | AC52: =N52-AB52 -> -2.1462742
A53: =+A52+1 -> 48 | B53: Rihand II (NR) | C53: 1.621 | D53: -0.039 | E53: =C53+D53 -> 1.582 | F53: 0.0442 | G53: =E53/((100%-F53)) -> 1.655158 | I53: 0 | N53: =SUM(G53:M53) -> 1.655158 | X53: 4.3624508 | Y53: =N53-X53 -> -2.7072929 | Z53: 3.6339125 | AA53: =N53-Z53 -> -1.9787546 | AB53: 3.5899821 | AC53: =N53-AB53 -> -1.9348241
A54: =+A53+1 -> 49 | B54: Rihand III (NR) | C54: 1.603 | D54: -0.042 | E54: =C54+D54 -> 1.561 | F54: 0.0442 | G54: =E54/((100%-F54)) -> 1.6331869 | I54: 0 | N54: =SUM(G54:M54) -> 1.6331869 | Z54: 3.910432 | AA54: =N54-Z54 -> -2.2772452 | AB54: 3.5294118 | AC54: =N54-AB54 -> -1.8962249
A55: =+A54+1 -> 50 | B55: Sasan | C55: 1.1495327 | E55: =C55+D55 -> 1.1495327 | F55: 0.0442 | G55: =E55/((100%-F55)) -> 1.2026917 | H55: 0.15 | I55: 0.038347439 | L55: 0.165 | N55: =SUM(G55:M55) -> 1.5560391 | Z55: 2.2160169 | AA55: =N55-Z55 -> -0.65997772 | AB55: 2.1099291 | AC55: =N55-AB55 -> -0.55388994
A56: =+A55+1 -> 51 | B56: KSTPS | C56: 1.317 | D56: 0.001 | E56: =C56+D56 -> 1.318 | F56: 0.0442 | G56: =E56/((100%-F56)) -> 1.3789496 | I56: 0.13208364 | N56: =SUM(G56:M56) -> 1.5110332 | Z56: 2.8556375 | AA56: =N56-Z56 -> -1.3446043 | AB56: 2.6329787 | AC56: =N56-AB56 -> -1.1219455
A57: =+A56+1 -> 52 | B57: KSTPS-III | C57: 1.292 | D57: 0.00099 | E57: =C57+D57 -> 1.29299 | F57: 0.0442 | G57: =E57/((100%-F57)) -> 1.352783 | I57: 0.11369475 | N57: =SUM(G57:M57) -> 1.4664778 | Z57: 2.9030558 | AA57: =N57-Z57 -> -1.4365781 | AB57: 2.6799124 | AC57: =N57-AB57 -> -1.2134346
A58: =+A57+1 -> 53 | B58: Lara | C58: 1.224 | D58: 0.002 | E58: =C58+D58 -> 1.226 | F58: 0.0442 | G58: =E58/((100%-F58)) -> 1.2826951 | I58: 0.11369475 | L58: 0.039 | N58: =SUM(G58:M58) -> 1.4353899 | Z58: 2.9041096 | AA58: =N58-Z58 -> -1.4687197 | AB58: 2.8744264 | AC58: =N58-AB58 -> -1.4390365
A59: =+A58+1 -> 54 | B59: SIPAT II | C59: 1.249 | D59: -0.00799 | E59: =C59+D59 -> 1.24101 | F59: 0.0442 | G59: =E59/((100%-F59)) -> 1.2983992 | I59: 0.11823725 | N59: =SUM(G59:M59) -> 1.4166365 | Z59: 2.5763962 | AA59: =N59-Z59 -> -1.1597597 | AB59: 2.5396329 | AC59: =N59-AB59 -> -1.1229964
A60: =+A59+1 -> 55 | B60: SIPAT I | C60: 1.212 | D60: -0.00799 | E60: =C60+D60 -> 1.20401 | F60: 0.0442 | G60: =E60/((100%-F60)) -> 1.2596882 | I60: 0.11823725 | L60: 0.034 | N60: =SUM(G60:M60) -> 1.4119255 | Z60: 2.8134879 | AA60: =N60-Z60 -> -1.4015624 | AB60: 2.9447309 | AC60: =N60-AB60 -> -1.5328054
A61: =+A60+1 -> 56 | B61: JP Nigrie | C61: 0.705 | E61: =C61+D61 -> 0.705 | F61: 0.0442 | G61: =E61/((100%-F61)) -> 0.73760201 | H61: 0.15 | I61: 0.040005 | N61: =SUM(G61:M61) -> 0.92760701 | AB61: 3.2342511 | AC61: =N61-AB61 -> -2.3066441
A63: Details of power purchase cost per unit of Hydel Power Stations for MOD on the basis of rates available from bills of March 2026
A64: Sr. No. | B64: Name of Generating Stations | C64: Energy Charges Rate for MOD Purpose Rs./kwh | D64: FCA Rs./kwh | E64: Effective Energy Charges (Rs./kwh) | F64: Transmission Losses beyond MP Periphery | G64: Variable cost incl. losses | H64: Cess on Intrastate sales | I64: ED & Cess on Auxiliary Consumption | J64: Variable rate at MP periphery in Rs./kwh
G66: (Rs. per kwh)
A67: A | B67: B | C67: C | D67: D | E67: E=C+D | F67: F | G67: G=E/(100%-F) | H67: H | I67: I | J67: J=sum(G:H)
A68: 1 | B68: Koteshwar (NR) | C68: 2.95 | E68: =C68+D68 -> 2.95 | F68: 0.0442 | G68: =E68/((100%-F68)) -> 3.0864198 | I68: 0 | J68: =SUM(G68:I68) -> 3.0864198 | O68: 0.612 | P68: =J68-O68 -> 2.4744198 | Q68: =J68-J69 -> 0.58798912 | R68: =J68-J69 -> 0.58798912 | S68: =J68-J69 -> 0.58798912 | X68: 0.68 | Y68: =J68-X68 -> 2.4064198 | Z68: 0.602 | AA68: =J68-Z68 -> 2.4844198 | AB68: 0.602 | AC68: =J68-AB68 -> 2.4844198
A69: =+A68+1 -> 2 | B69: Kishanganga (NR) | C69: 2.388 | E69: =C69+D69 -> 2.388 | F69: 0.0442 | G69: =E69/((100%-F69)) -> 2.4984306 | I69: 0 | J69: =SUM(G69:I69) -> 2.4984306 | O69: 0.585 | P69: =J69-O69 -> 1.9134306 | Q69: =J69-J70 -> 0.062774639 | R69: =J69-J70 -> 0.062774639 | S69: =J69-J70 -> 0.062774639 | X69: 0.516 | Y69: =J69-X69 -> 1.9824306 | Z69: 0.457 | AA69: =J69-Z69 -> 2.0414306 | AB69: 0.457 | AC69: =J69-AB69 -> 2.0414306
A70: =+A69+1 -> 3 | B70: Dulhasti (NR) | C70: 2.328 | E70: =C70+D70 -> 2.328 | F70: 0.0442 | G70: =E70/((100%-F70)) -> 2.435656 | I70: 0 | J70: =SUM(G70:I70) -> 2.435656 | O70: 1.451 | P70: =J70-O70 -> 0.98465599 | Q70: =J70-J71 -> 0.10776313 | R70: =J70-J71 -> 0.10776313 | S70: =J70-J71 -> 0.10776313 | X70: 0.815 | Y70: =J70-X70 -> 1.620656 | Z70: 0.722 | AA70: =J70-Z70 -> 1.713656 | AB70: 0.722 | AC70: =J70-AB70 -> 1.713656
A71: =+A70+1 -> 4 | B71: Koldam (NR) | C71: 2.225 | E71: =C71+D71 -> 2.225 | F71: 0.0442 | G71: =E71/((100%-F71)) -> 2.3278929 | I71: 0 | J71: =SUM(G71:I71) -> 2.3278929 | O71: 0.184 | P71: =J71-O71 -> 2.1438929 | Q71: =J71-J72 -> 0.018832392 | R71: =J71-J72 -> 0.018832392 | S71: =J71-J72 -> 0.018832392 | X71: 0.183 | Y71: =J71-X71 -> 2.1448929 | Z71: 0.19 | AA71: =J71-Z71 -> 2.1378929 | AB71: 0.19 | AC71: =J71-AB71 -> 2.1378929
A72: =+A71+1 -> 5 | B72: URI II (NR) | C72: 2.207 | E72: =C72+D72 -> 2.207 | F72: 0.0442 | G72: =E72/((100%-F72)) -> 2.3090605 | I72: 0 | J72: =SUM(G72:I72) -> 2.3090605 | O72: 0.705 | P72: =J72-O72 -> 1.6040605 | Q72: =J72-J73 -> 0.001046244 | R72: =J72-J73 -> 0.001046244 | S72: =J72-J73 -> 0.001046244 | X72: 0.606 | Y72: =J72-X72 -> 1.7030605 | Z72: 0.589 | AA72: =J72-Z72 -> 1.7200605 | AB72: 0.589 | AC72: =J72-AB72 -> 1.7200605
A73: =+A72+1 -> 6 | B73: Sewa II (NR) | C73: 2.206 | E73: =C73+D73 -> 2.206 | F73: 0.0442 | G73: =E73/((100%-F73)) -> 2.3080142 | I73: 0 | J73: =SUM(G73:I73) -> 2.3080142 | O73: 0.179 | P73: =J73-O73 -> 2.1290142 | Q73: =J73-J74 -> 0.095208203 | R73: =J73-J74 -> 0.095208203 | S73: =J73-J74 -> 0.095208203 | X73: 0.209 | Y73: =J73-X73 -> 2.0990142 | Z73: 0.238 | AA73: =J73-Z73 -> 2.0700142 | AB73: 0.238 | AC73: =J73-AB73 -> 2.0700142
A74: =+A73+1 -> 7 | B74: Tehri I (NR) | C74: 2.115 | E74: =C74+D74 -> 2.115 | F74: 0.0442 | G74: =E74/((100%-F74)) -> 2.212806 | I74: 0 | J74: =SUM(G74:I74) -> 2.212806 | O74: 2.3498333 | P74: =J74-O74 -> -0.13702731 | Q74: =J74-J75 -> 0.028248588 | R74: =J74-J75 -> 0.028248588 | S74: =J74-J75 -> 0.028248588 | X74: 2.2542644 | Y74: =J74-X74 -> -0.041458418 | Z74: 2.1584311 | AA74: =J74-Z74 -> 0.054374915 | AB74: 2.1584311 | AC74: =J74-AB74 -> 0.054374915
A75: =+A74+1 -> 8 | B75: Chamera III (NR) | C75: 2.088 | E75: =C75+D75 -> 2.088 | F75: 0.0442 | G75: =E75/((100%-F75)) -> 2.1845574 | I75: 0 | J75: =SUM(G75:I75) -> 2.1845574 | O75: 1.51 | P75: =J75-O75 -> 0.67455744 | Q75: =J75-J76 -> 0.0073237079 | R75: =J75-J76 -> 0.0073237079 | S75: =J75-J76 -> 0.0073237079 | X75: 1.51 | Y75: =J75-X75 -> 0.67455744 | Z75: 1.51 | AA75: =J75-Z75 -> 0.67455744 | AB75: 1.51 | AC75: =J75-AB75 -> 0.67455744
A76: =+A75+1 -> 9 | B76: Rampur HEP (NR) | C76: 2.081 | E76: =C76+D76 -> 2.081 | F76: 0.0442 | G76: =E76/((100%-F76)) -> 2.1772337 | I76: 0 | J76: =SUM(G76:I76) -> 2.1772337 | O76: 0.921 | P76: =J76-O76 -> 1.2562337 | Q76: =J76-J77 -> 0.01880262 | R76: =J76-J77 -> 0.01880262 | S76: =J76-J77 -> 0.01880262 | X76: 0.608 | Y76: =J76-X76 -> 1.5692337 | Z76: 0.608 | AA76: =J76-Z76 -> 1.5692337 | AB76: 0.608 | AC76: =J76-AB76 -> 1.5692337
A77: =+A76+1 -> 10 | B77: ISP & OSP (25:11) | C77: 1.9996111 | E77: =C77+D77 -> 1.9996111 | G77: =E77/((100%-F77)) -> 1.9996111 | H77: 0.15 | I77: 0.00882 | J77: =SUM(G77:I77) -> 2.1584311 | O77: 2.015 | P77: =J77-O77 -> 0.14343111 | Q77: =J77-J78 -> 0.64843111 | R77: =J77-J78 -> 0.64843111 | S77: =J77-J78 -> 0.64843111 | X77: 1.293 | Y77: =J77-X77 -> 0.86543111 | Z77: 1.425 | AA77: =J77-Z77 -> 0.73343111 | AB77: 1.425 | AC77: =J77-AB77 -> 0.73343111
A78: =+A77+1 -> 11 | B78: Jawahar Sagar (Inter state project) | C78: 1.51 | E78: =C78+D78 -> 1.51 | G78: =E78/((100%-F78)) -> 1.51 | I78: 0 | J78: =SUM(G78:I78) -> 1.51 | O78: 0.465 | P78: =J78-O78 -> 1.045 | Q78: =J78-J79 -> 0 | R78: =J78-J79 -> 0 | S78: =J78-J79 -> 0 | X78: 0.519 | Y78: =J78-X78 -> 0.991 | Z78: 0.584 | AA78: =J78-Z78 -> 0.926 | AB78: 0.584 | AC78: =J78-AB78 -> 0.926
A79: =+A78+1 -> 12 | B79: R P sagar (Inter state project) | C79: 1.51 | E79: =C79+D79 -> 1.51 | G79: =E79/((100%-F79)) -> 1.51 | I79: 0 | J79: =SUM(G79:I79) -> 1.51 | O79: 1.51 | P79: =J79-O79 -> 0 | Q79: =J79-J80 -> 0.085 | R79: =J79-J80 -> 0.085 | S79: =J79-J80 -> 0.085 | X79: 1.51 | Y79: =J79-X79 -> 0 | Z79: 1.51 | AA79: =J79-Z79 -> 0 | AB79: 1.51 | AC79: =J79-AB79 -> 0
A80: =+A79+1 -> 13 | B80: Madikhera HPS | C80: 1.425 | E80: =C80+D80 -> 1.425 | G80: =E80/((100%-F80)) -> 1.425 | I80: 0 | J80: =SUM(G80:I80) -> 1.425 | O80: 1.726 | P80: =J80-O80 -> -0.301 | Q80: =J80-J81 -> 1.569366e-05 | R80: =J80-J81 -> 1.569366e-05 | S80: =J80-J81 -> 1.569366e-05 | X80: 1.252 | Y80: =J80-X80 -> 0.173 | Z80: 0.984 | AA80: =J80-Z80 -> 0.441 | AB80: 0.984 | AC80: =J80-AB80 -> 0.441
A81: =+A80+1 -> 14 | B81: Parbati III (NR) | C81: 1.362 | E81: =C81+D81 -> 1.362 | F81: 0.0442 | G81: =E81/((100%-F81)) -> 1.4249843 | I81: 0 | J81: =SUM(G81:I81) -> 1.4249843 | O81: 0.8446502 | P81: =J81-O81 -> 0.58033411 | Q81: =J81-J82 -> 0.085792007 | R81: =J81-J82 -> 0.085792007 | S81: =J81-J82 -> 0.085792007 | X81: 0.84868557 | Y81: =J81-X81 -> 0.57629873 | Z81: 0.86406744 | AA81: =J81-Z81 -> 0.56091687 | AB81: 0.85523571 | AC81: =J81-AB81 -> 0.5697486
A82: =+A81+1 -> 15 | B82: Dhauliganga (NR) | C82: 1.28 | E82: =C82+D82 -> 1.28 | F82: 0.0442 | G82: =E82/((100%-F82)) -> 1.3391923 | I82: 0 | J82: =SUM(G82:I82) -> 1.3391923 | O82: 1.0336379 | P82: =J82-O82 -> 0.30555437 | Q82: =J82-J83 -> 0.078468299 | R82: =J82-J83 -> 0.078468299 | S82: =J82-J83 -> 0.078468299 | X82: 1.0401573 | Y82: =J82-X82 -> 0.29903498 | Z82: 1.2697576 | AA82: =J82-Z82 -> 0.06943466 | AB82: 1.2567793 | AC82: =J82-AB82 -> 0.082412992
A83: =+A82+1 -> 16 | B83: Chamera II (NR) | C83: 1.205 | E83: =C83+D83 -> 1.205 | F83: 0.0442 | G83: =E83/((100%-F83)) -> 1.260724 | I83: 0 | J83: =SUM(G83:I83) -> 1.260724 | O83: 2.1834958 | P83: =J83-O83 -> -0.92277185 | Q83: =J83-J84 -> 0.002092488 | R83: =J83-J84 -> 0.002092488 | S83: =J83-J84 -> 0.002092488 | X83: 2.0389153 | Y83: =J83-X83 -> -0.77819134 | Z83: 2.2002107 | AA83: =J83-Z83 -> -0.93948675 | AB83: 2.1777222 | AC83: =J83-AB83 -> -0.91699815
A84: =+A83+1 -> 17 | B84: Nathpa-Jhakri (NR) | C84: 1.203 | E84: =C84+D84 -> 1.203 | F84: 0.0442 | G84: =E84/((100%-F84)) -> 1.2586315 | I84: 0 | J84: =SUM(G84:I84) -> 1.2586315 | O84: 1.2527959 | P84: =J84-O84 -> 0.0058356514 | Q84: =J84-J85 -> 0.27463151 | R84: =J84-J85 -> 0.27463151 | S84: =J84-J85 -> 0.27463151 | X84: 1.2989029 | Y84: =J84-X84 -> -0.040271406 | Z84: 1.3487882 | AA84: =J84-Z84 -> -0.090156685 | AB84: 1.3350021 | AC84: =J84-AB84 -> -0.076370573
A85: =+A84+1 -> 18 | B85: Rajghat HPS | C85: 0.984 | E85: =C85+D85 -> 0.984 | G85: =E85/((100%-F85)) -> 0.984 | I85: 0 | J85: =SUM(G85:I85) -> 0.984 | O85: 2.827334 | P85: =J85-O85 -> -1.843334 | Q85: =J85-J86 -> 0.12607993 | R85: =J85-J86 -> 0.12607993 | S85: =J85-J86 -> 0.12607993 | X85: 2.409439 | Y85: =J85-X85 -> -1.425439 | Z85: 2.4531085 | AA85: =J85-Z85 -> -1.4691085 | AB85: 2.428035 | AC85: =J85-AB85 -> -1.444035
A86: =+A85+1 -> 19 | B86: SSP | C86: 0.82 | E86: =C86+D86 -> 0.82 | F86: 0.0442 | G86: =E86/((100%-F86)) -> 0.85792007 | I86: 0 | J86: =SUM(G86:I86) -> 0.85792007 | O86: 1.7361003 | P86: =J86-O86 -> -0.87818026 | Q86: =J86-J87 -> 0.13592007 | R86: =J86-J87 -> 0.13592007 | S86: =J86-J87 -> 0.13592007 | X86: 2.0378804 | Y86: =J86-X86 -> -1.1799603 | Z86: 2.516333 | AA86: =J86-Z86 -> -1.6584129 | AB86: 2.4906133 | AC86: =J86-AB86 -> -1.6326932
A87: =+A86+1 -> 20 | B87: Bansagar-III HPS | C87: 0.722 | E87: =C87+D87 -> 0.722 | G87: =E87/((100%-F87)) -> 0.722 | I87: 0 | J87: =SUM(G87:I87) -> 0.722 | O87: 2.554482 | P87: =J87-O87 -> -1.832482 | Q87: =J87-J88 -> 0.114 | R87: =J87-J88 -> 0.114 | S87: =J87-J88 -> 0.114 | X87: 2.5377769 | Y87: =J87-X87 -> -1.8157769 | Z87: 2.3445732 | AA87: =J87-Z87 -> -1.6225732 | AB87: 2.3206091 | AC87: =J87-AB87 -> -1.5986091
A88: =+A87+1 -> 21 | B88: Jhinna HPS | C88: 0.608 | E88: =C88+D88 -> 0.608 | G88: =E88/((100%-F88)) -> 0.608 | I88: 0 | J88: =SUM(G88:I88) -> 0.608 | O88: 2.3859832 | P88: =J88-O88 -> -1.7779832 | Q88: =J88-J89 -> 0.006 | R88: =J88-J89 -> 0.006 | S88: =J88-J89 -> 0.006 | X88: 2.8420617 | Y88: =J88-X88 -> -2.2340617 | Z88: 3.1085353 | AA88: =J88-Z88 -> -2.5005353 | AB88: 3.0767626 | AC88: =J88-AB88 -> -2.4687626
A89: =+A88+1 -> 22 | B89: Bansagar-I HPS | C89: 0.602 | E89: =C89+D89 -> 0.602 | G89: =E89/((100%-F89)) -> 0.602 | I89: 0 | J89: =SUM(G89:I89) -> 0.602 | O89: 1.2064542 | P89: =J89-O89 -> -0.60445417 | Q89: =J89-J90 -> 0.013 | R89: =J89-J90 -> 0.013 | S89: =J89-J90 -> 0.013 | X89: 1.2450838 | Y89: =J89-X89 -> -0.64308383 | Z89: 1.2676502 | AA89: =J89-Z89 -> -0.66565016 | AB89: 1.2546934 | AC89: =J89-AB89 -> -0.65269337
A90: =+A89+1 -> 23 | B90: Birsinghpur HPS | C90: 0.589 | E90: =C90+D90 -> 0.589 | G90: =E90/((100%-F90)) -> 0.589 | I90: 0 | J90: =SUM(G90:I90) -> 0.589 | O90: 1.5828545 | P90: =J90-O90 -> -0.9938545 | Q90: =J90-J91 -> 0.005 | R90: =J90-J91 -> 0.005 | S90: =J90-J91 -> 0.005 | X90: 1.5928379 | Y90: =J90-X90 -> -1.0038379 | Z90: 1.4351949 | AA90: =J90-Z90 -> -0.84619494 | AB90: 1.4205257 | AC90: =J90-AB90 -> -0.83152566
A91: =+A90+1 -> 24 | B91: Pench HPS | C91: 0.584 | E91: =C91+D91 -> 0.584 | G91: =E91/((100%-F91)) -> 0.584 | I91: 0 | J91: =SUM(G91:I91) -> 0.584 | O91: 2.2251304 | P91: =J91-O91 -> -1.6411304 | Q91: =J91-J92 -> 0.127 | R91: =J91-J92 -> 0.127 | S91: =J91-J92 -> 0.127 | X91: 2.1537984 | Y91: =J91-X91 -> -1.5697984 | Z91: 2.1928346 | AA91: =J91-Z91 -> -1.6088346 | AB91: 2.1704214 | AC91: =J91-AB91 -> -1.5864214
A92: =+A91+1 -> 25 | B92: Bansagar-II HPS | C92: 0.457 | E92: =C92+D92 -> 0.457 | G92: =E92/((100%-F92)) -> 0.457 | I92: 0 | J92: =SUM(G92:I92) -> 0.457 | O92: 2.2308066 | P92: =J92-O92 -> -1.7738066 | Q92: =J92-J93 -> 0.219 | R92: =J92-J93 -> 0.219 | S92: =J92-J93 -> 0.219 | X92: 2.2831712 | Y92: =J92-X92 -> -1.8261712 | Z92: 2.3245522 | AA92: =J92-Z92 -> -1.8675522 | AB92: 2.3007927 | AC92: =J92-AB92 -> -1.8437927
A93: =+A92+1 -> 26 | B93: Gandhi Sagar HPS | C93: 0.238 | E93: =C93+D93 -> 0.238 | G93: =E93/((100%-F93)) -> 0.238 | I93: 0 | J93: =SUM(G93:I93) -> 0.238 | O93: 2.7386221 | P93: =J93-O93 -> -2.5006221 | Q93: =J93-J94 -> 0.048 | R93: =J93-J94 -> 0.048 | S93: =J93-J94 -> 0.048 | X93: 2.1889878 | Y93: =J93-X93 -> -1.9509878 | Z93: 2.2286617 | AA93: =J93-Z93 -> -1.9906617 | AB93: 2.2058824 | AC93: =J93-AB93 -> -1.9678824
A94: =+A93+1 -> 27 | B94: Bargi HPS | C94: 0.19 | E94: =C94+D94 -> 0.19 | G94: =E94/((100%-F94)) -> 0.19 | I94: 0 | J94: =SUM(G94:I94) -> 0.19 | O94: 2.4344522 | P94: =J94-O94 -> -2.2444522 | Q94: =J94-J95 -> 0.19 | R94: =J94-J95 -> 0.19 | S94: =J94-J95 -> 0.19 | X94: 2.2065825 | Y94: =J94-X94 -> -2.0165825 | Z94: 2.3256059 | AA94: =J94-Z94 -> -2.1356059 | AB94: 2.3018356 | AC94: =J94-AB94 -> -2.1118356
A96: Details of power purchase cost from high cost (ECR > Rs. 5) stations on the basis of rates available from bills of March 2026
A97: Sr. No. | B97: Name of Generating Stations | C97: Energy Charges Rate for MOD Purpose Rs./kwh | D97: FCA Rs./kwh | E97: Effective Energy Charges (Rs./kwh) | F97: Transmission Losses beyond MP Periphery | G97: Variable cost incl. losses | H97: Trading Margin | I97: Cess on Intrastate sales | J97: ED & Cess on Auxiliary Consumption | K97: Effective rate (Rs./kwh)
G99: (Rs. per kwh)
A100: A | B100: B | C100: C | D100: D | E100: E=C+D | F100: F | G100: G=E/(100%-F) | H100: H | I100: I | J100: J | K100: K=sum(G:J)
A101: 1 | B101: KAWAS (NAPM) | C101: 35.627 | E101: =C101+D101 -> 35.627 | F101: 0.0442 | G101: =E101/((100%-F101)) -> 37.274534 | J101: 0 | K101: =SUM(G101:J101) -> 37.274534 | O101: 7.0915545 | P101: =O101-K101 -> -30.18298 | Q101: =K101-K102 -> 6.1822557 | S101: =K101-K102 -> 6.1822557 | X101: 14.086111 | Y101: =K101-X101 -> 23.188424 | Z101: 9.4193888 | AA101: =K101-Z101 -> 27.855146 | AB101: 9.2980809 | AC101: =K101-AB101 -> 27.976453
A102: =+A101+1 -> 2 | B102: GANDHAR (NAPM) | C102: 29.718 | E102: =C102+D102 -> 29.718 | F102: 0.0442 | G102: =E102/((100%-F102)) -> 31.092279 | J102: 0 | K102: =SUM(G102:J102) -> 31.092279 | O102: 7.2336514 | P102: =O102-K102 -> -23.858627 | Q102: =K102-K103 -> 5.9374346 | S102: =K102-K103 -> 5.9374346 | X102: 12.691989 | Y102: =K102-X102 -> 18.400289 | Z102: 9.9452055 | AA102: =K102-Z102 -> 21.147073 | AB102: 13.565916 | AC102: =K102-AB102 -> 17.526363
A103: =+A102+1 -> 3 | B103: KAWAS (Liquid) | C103: 24.043 | E103: =C103+D103 -> 24.043 | F103: 0.0442 | G103: =E103/((100%-F103)) -> 25.154844 | J103: 0 | K103: =SUM(G103:J103) -> 25.154844 | O103: 16.24198 | P103: =O103-K103 -> -8.9128638 | Q103: =K103-K104 -> 0.17681523 | S103: =K103-K104 -> 0.17681523 | X103: 30.757607 | Y103: =K103-X103 -> -5.602763 | Z103: 31.315068 | AA103: =K103-Z103 -> -6.1602244 | AB103: 30.994994 | AC103: =K103-AB103 -> -5.8401496
A104: =+A103+1 -> 4 | B104: Dadri Liquid (NR) | C104: 23.874 | E104: =C104+D104 -> 23.874 | F104: 0.0442 | G104: =E104/((100%-F104)) -> 24.978029 | J104: 0 | K104: =SUM(G104:J104) -> 24.978029 | O104: 5.45 | P104: =O104-K104 -> -19.528029 | Q104: =K104-#REF! -> #REF! | S104: =K104-K105 -> 5.4247751 | X104: 14.077831 | Y104: =K104-X104 -> 10.900198 | Z104: 9.4625922 | AA104: =K104-Z104 -> 15.515437 | AB104: 9.3387568 | AC104: =K104-AB104 -> 15.639272
A105: =+A104+1 -> 5 | B105: Auraiya Liquid (NR) | C105: 18.689 | E105: =C105+D105 -> 18.689 | F105: 0.0442 | G105: =E105/((100%-F105)) -> 19.553254 | J105: 0 | K105: =SUM(G105:J105) -> 19.553254 | O105: 8.2677986 | P105: =O105-K105 -> -11.285455 | Q105: =K105-K106 -> 1.2460766 | S105: =K105-K106 -> 1.2460766 | X105: 13.970193 | Y105: =K105-X105 -> 5.5830613 | Z105: 10.055848 | AA105: =K105-Z105 -> 9.4974056 | AB105: 9.9895703 | AC105: =K105-AB105 -> 9.5636835
...

Sheet  Rate sheet  2
A1: ='Excl URS 3 '!A1:N1 -> Details of power purchase cost per unit of Thermal and Gas Power stations for MOD for the month of March 2026
A2: Sr. No. | B2: Name of Generating Stations | C2: Installed Capacity (MW) | D2: MPPMCL Share (MW) | E2: Cumulative capacity (MW) | F2: Normative Fixed Cost Rs. /kwh | G2: Variable rate at MP periphery in Rs./kwh | H2: Total rate (Fixed & Variable) Rs./ Kwh
A3: 1 | B3: KAWAS (NAPM) | C3: =VLOOKUP(B3,'rate sheet working'!$B$3:$C$158,2,0) -> 0 | D3: =VLOOKUP(B3,'rate sheet working'!$B$3:$D$158,3,0) -> 0 | E3: =D3+E4 -> 13028.414 | F3: =VLOOKUP(B3,'rate sheet working'!$B$3:$E$158,4,0) -> 0.85915096 | G3: =VLOOKUP(B3,'rate sheet periphery 1'!$B$5:$F$110,5,0) -> 37.274534 | H3: =F3+G3 -> 38.133685
A4: 2 | B4: GANDHAR (NAPM) | C4: =VLOOKUP(B4,'rate sheet working'!$B$3:$C$158,2,0) -> 0 | D4: =VLOOKUP(B4,'rate sheet working'!$B$3:$D$158,3,0) -> 0 | E4: =D4+E5 -> 13028.414 | F4: =VLOOKUP(B4,'rate sheet working'!$B$3:$E$158,4,0) -> 1.0465902 | G4: =VLOOKUP(B4,'rate sheet periphery 1'!$B$5:$F$110,5,0) -> 31.092279 | H4: =F4+G4 -> 32.138869 | I4: =H4-H5 -> 6.1248739
A5: 3 | B5: KAWAS (Liquid) | C5: =VLOOKUP(B5,'rate sheet working'!$B$3:$C$158,2,0) -> 0 | D5: =VLOOKUP(B5,'rate sheet working'!$B$3:$D$158,3,0) -> 0 | E5: =D5+E6 -> 13028.414 | F5: =VLOOKUP(B5,'rate sheet working'!$B$3:$E$158,4,0) -> 0.85915096 | G5: =VLOOKUP(B5,'rate sheet periphery 1'!$B$5:$F$110,5,0) -> 25.154844 | H5: =F5+G5 -> 26.013995 | I5: =H5-H6 -> 0.50635912
A6: 4 | B6: Dadri Liquid (NR) | C6: =VLOOKUP(B6,'rate sheet working'!$B$3:$C$158,2,0) -> 0 | D6: =VLOOKUP(B6,'rate sheet working'!$B$3:$D$158,3,0) -> 0 | E6: =D6+E7 -> 13028.414 | F6: =VLOOKUP(B6,'rate sheet working'!$B$3:$E$158,4,0) -> 0.52960707 | G6: =VLOOKUP(B6,'rate sheet periphery 1'!$B$5:$F$110,5,0) -> 24.978029 | H6: =F6+G6 -> 25.507636 | I6: =H6-H7 -> 5.3193821
A7: 5 | B7: Auraiya Liquid (NR) | C7: =VLOOKUP(B7,'rate sheet working'!$B$3:$C$158,2,0) -> 0 | D7: =VLOOKUP(B7,'rate sheet working'!$B$3:$D$158,3,0) -> 0 | E7: =D7+E8 -> 13028.414 | F7: =VLOOKUP(B7,'rate sheet working'!$B$3:$E$158,4,0) -> 0.635 | G7: =VLOOKUP(B7,'rate sheet periphery 1'!$B$5:$F$110,5,0) -> 19.553254 | H7: =F7+G7 -> 20.188254
A8: 6 | B8: Anta Liquid (NR) | C8: =VLOOKUP(B8,'rate sheet working'!$B$3:$C$158,2,0) -> 0 | D8: =VLOOKUP(B8,'rate sheet working'!$B$3:$D$158,3,0) -> 0 | E8: =D8+E9 -> 13028.414 | F8: =VLOOKUP(B8,'rate sheet working'!$B$3:$E$158,4,0) -> 0.709 | G8: =VLOOKUP(B8,'rate sheet periphery 1'!$B$5:$F$110,5,0) -> 18.307177 | H8: =F8+G8 -> 19.016177
A9: 7 | B9: GANDHAR (LNG) | C9: =VLOOKUP(B9,'rate sheet working'!$B$3:$C$158,2,0) -> 0 | D9: =VLOOKUP(B9,'rate sheet working'!$B$3:$D$158,3,0) -> 0 | E9: =D9+E10 -> 13028.414 | F9: =VLOOKUP(B9,'rate sheet working'!$B$3:$E$158,4,0) -> 1.0465902 | G9: =VLOOKUP(B9,'rate sheet periphery 1'!$B$5:$F$110,5,0) -> 13.649299 | H9: =F9+G9 -> 14.695889 | I9: =H9-H10 -> 1.225568
A10: 8 | B10: Auraiya CLNG (NR) | C10: =VLOOKUP(B10,'rate sheet working'!$B$3:$C$158,2,0) -> 0 | D10: =VLOOKUP(B10,'rate sheet working'!$B$3:$D$158,3,0) -> 0 | E10: =D10+E11 -> 13028.414 | F10: =VLOOKUP(B10,'rate sheet working'!$B$3:$E$158,4,0) -> 0.635 | G10: =VLOOKUP(B10,'rate sheet periphery 1'!$B$5:$F$110,5,0) -> 12.835321 | H10: =F10+G10 -> 13.470321 | I10: =H10-H11 -> 0.71744566
A11: 9 | B11: Dadri Comm LNG (NR) | C11: =VLOOKUP(B11,'rate sheet working'!$B$3:$C$158,2,0) -> 0 | D11: =VLOOKUP(B11,'rate sheet working'!$B$3:$D$158,3,0) -> 0 | E11: =D11+E12 -> 13028.414 | F11: =VLOOKUP(B11,'rate sheet working'!$B$3:$E$158,4,0) -> 0.52960707 | G11: =VLOOKUP(B11,'rate sheet periphery 1'!$B$5:$F$110,5,0) -> 12.223268 | H11: =F11+G11 -> 12.752876 | I11: =H11-#REF! -> #REF!
A12: 10 | B12: Auraiya LNG (NR) | C12: =VLOOKUP(B12,'rate sheet working'!$B$3:$C$158,2,0) -> 0 | D12: =VLOOKUP(B12,'rate sheet working'!$B$3:$D$158,3,0) -> 0 | E12: =D12+E13 -> 13028.414 | F12: =VLOOKUP(B12,'rate sheet working'!$B$3:$E$158,4,0) -> 0.635 | G12: =VLOOKUP(B12,'rate sheet periphery 1'!$B$5:$F$110,5,0) -> 11.929274 | H12: =F12+G12 -> 12.564274
A13: 11 | B13: Anta LNG (NR) | C13: =VLOOKUP(B13,'rate sheet working'!$B$3:$C$158,2,0) -> 0 | D13: =VLOOKUP(B13,'rate sheet working'!$B$3:$D$158,3,0) -> 0 | E13: =D13+E14 -> 13028.414 | F13: =VLOOKUP(B13,'rate sheet working'!$B$3:$E$158,4,0) -> 0.709 | G13: =VLOOKUP(B13,'rate sheet periphery 1'!$B$5:$F$110,5,0) -> 11.786985 | H13: =F13+G13 -> 12.495985 | I13: =H13-H14 -> 0.60521423
A14: 12 | B14: Dadri LNG (NR) | C14: =VLOOKUP(B14,'rate sheet working'!$B$3:$C$158,2,0) -> 0 | D14: =VLOOKUP(B14,'rate sheet working'!$B$3:$D$158,3,0) -> 0 | E14: =D14+E15 -> 13028.414 | F14: =VLOOKUP(B14,'rate sheet working'!$B$3:$E$158,4,0) -> 0.52960707 | G14: =VLOOKUP(B14,'rate sheet periphery 1'!$B$5:$F$110,5,0) -> 11.361163 | H14: =F14+G14 -> 11.89077 | I14: =H14-H15 -> 1.0106947
A15: 13 | B15: KAWAS (LNG) | C15: =VLOOKUP(B15,'rate sheet working'!$B$3:$C$158,2,0) -> 0 | D15: =VLOOKUP(B15,'rate sheet working'!$B$3:$D$158,3,0) -> 0 | E15: =D15+E16 -> 13028.414 | F15: =VLOOKUP(B15,'rate sheet working'!$B$3:$E$158,4,0) -> 0.85915096 | G15: =VLOOKUP(B15,'rate sheet periphery 1'!$B$5:$F$110,5,0) -> 10.020925 | H15: =F15+G15 -> 10.880076 | I15: =H15-#REF! -> #REF!
A16: 14 | B16: GANDHAR (CLNG) | C16: =VLOOKUP(B16,'rate sheet working'!$B$3:$C$158,2,0) -> 0 | D16: =VLOOKUP(B16,'rate sheet working'!$B$3:$D$158,3,0) -> 0 | E16: =D16+E17 -> 13028.414 | F16: =VLOOKUP(B16,'rate sheet working'!$B$3:$E$158,4,0) -> 1.0465902 | G16: =VLOOKUP(B16,'rate sheet periphery 1'!$B$5:$F$110,5,0) -> 9.3272651 | H16: =F16+G16 -> 10.373855 | I16: =H16-H17 -> 0.050919376
A17: 15 | B17: Anta CLNG (NR) | C17: =VLOOKUP(B17,'rate sheet working'!$B$3:$C$158,2,0) -> 0 | D17: =VLOOKUP(B17,'rate sheet working'!$B$3:$D$158,3,0) -> 0 | E17: =D17+E18 -> 13028.414 | F17: =VLOOKUP(B17,'rate sheet working'!$B$3:$E$158,4,0) -> 0.709 | G17: =VLOOKUP(B17,'rate sheet periphery 1'!$B$5:$F$110,5,0) -> 9.613936 | H17: =F17+G17 -> 10.322936
A18: 16 | B18: KAWAS (CLNG) | C18: =VLOOKUP(B18,'rate sheet working'!$B$3:$C$158,2,0) -> 0 | D18: =VLOOKUP(B18,'rate sheet working'!$B$3:$D$158,3,0) -> 0 | E18: =D18+E19 -> 13028.414 | F18: =VLOOKUP(B18,'rate sheet working'!$B$3:$E$158,4,0) -> 0.85915096 | G18: =VLOOKUP(B18,'rate sheet periphery 1'!$B$5:$F$110,5,0) -> 9.3680686 | H18: =F18+G18 -> 10.22722 | I18: =H18-H19 -> 1.6546698
A19: 17 | B19: Torrent (Indigenous) | C19: =VLOOKUP(B19,'rate sheet working'!$B$3:$C$158,2,0) -> 1115.9438 | D19: =VLOOKUP(B19,'rate sheet working'!$B$3:$D$158,3,0) -> 50 | E19: =D19+E20 -> 13028.414 | F19: =VLOOKUP(B19,'rate sheet working'!$B$3:$E$158,4,0) -> 0.89460463 | G19: =VLOOKUP(B19,'rate sheet periphery 1'!$B$5:$F$110,5,0) -> 7.6779452 | H19: =F19+G19 -> 8.5725498 | I19: =H19-H20 -> 1.6064572
A20: 18 | B20: Ghatampur Thermal Power Station (NUPPL) | C20: =VLOOKUP(B20,'rate sheet working'!$B$3:$C$158,2,0) -> 660 | D20: =VLOOKUP(B20,'rate sheet working'!$B$3:$D$158,3,0) -> 1.0626 | E20: =D20+E21 -> 12978.414 | F20: =VLOOKUP(B20,'rate sheet working'!$B$3:$E$158,4,0) -> 3.3963081 | G20: =VLOOKUP(B20,'rate sheet periphery 1'!$B$5:$F$110,5,0) -> 3.5697845 | H20: =F20+G20 -> 6.9660926 | I20: =H20-H22 -> 0.75023666
A21: 19 | B21: Solapur I | C21: =VLOOKUP(B21,'rate sheet working'!$B$3:$C$158,2,0) -> 1320 | D21: =VLOOKUP(B21,'rate sheet working'!$B$3:$D$158,3,0) -> 295.88 | E21: =D21+E22 -> 12977.351 | F21: =VLOOKUP(B21,'rate sheet working'!$B$3:$E$158,4,0) -> 1.9962859 | G21: =VLOOKUP(B21,'rate sheet periphery 1'!$B$5:$F$110,5,0) -> 4.2412187 | H21: =F21+G21 -> 6.2375045 | I21: =H21-H23 -> 0.22978847
A22: 20 | B22: Gadarwara | C22: =VLOOKUP(B22,'rate sheet working'!$B$3:$C$158,2,0) -> 1600 | D22: =VLOOKUP(B22,'rate sheet working'!$B$3:$D$158,3,0) -> 800 | E22: =D22+E23 -> 12681.471 | F22: =VLOOKUP(B22,'rate sheet working'!$B$3:$E$158,4,0) -> 2.0601461 | G22: =VLOOKUP(B22,'rate sheet periphery 1'!$B$5:$F$110,5,0) -> 4.1557098 | H22: =F22+G22 -> 6.2158559
A23: 21 | B23: Indira Gandhi STPS (Jhajjar) (NR) | C23: =VLOOKUP(B23,'rate sheet working'!$B$3:$C$158,2,0) -> 1500 | D23: =VLOOKUP(B23,'rate sheet working'!$B$3:$D$158,3,0) -> 1.8 | E23: =D23+E24 -> 11881.471 | F23: =VLOOKUP(B23,'rate sheet working'!$B$3:$E$158,4,0) -> 1.56 | G23: =VLOOKUP(B23,'rate sheet periphery 1'!$B$5:$F$110,5,0) -> 4.447716 | H23: =F23+G23 -> 6.007716 | I23: =H23-H25 -> 0.34482158
A24: 22 | B24: BLA | C24: =VLOOKUP(B24,'rate sheet working'!$B$3:$C$158,2,0) -> 90 | D24: =VLOOKUP(B24,'rate sheet working'!$B$3:$D$158,3,0) -> 27 | E24: =D24+E25 -> 11879.671 | F24: =VLOOKUP(B24,'rate sheet working'!$B$3:$E$158,4,0) -> 1.9177182 | G24: =VLOOKUP(B24,'rate sheet periphery 1'!$B$5:$F$110,5,0) -> 3.98201 | H24: =F24+G24 -> 5.8997282
A25: 23 | B25: Khargone | C25: =VLOOKUP(B25,'rate sheet working'!$B$3:$C$158,2,0) -> 1320 | D25: =VLOOKUP(B25,'rate sheet working'!$B$3:$D$158,3,0) -> 660 | E25: =D25+E26 -> 11852.671 | F25: =VLOOKUP(B25,'rate sheet working'!$B$3:$E$158,4,0) -> 2.0731461 | G25: =VLOOKUP(B25,'rate sheet periphery 1'!$B$5:$F$110,5,0) -> 3.5897484 | H25: =F25+G25 -> 5.6628945
A26: 24 | B26: Unchahar II (NR) | C26: =VLOOKUP(B26,'rate sheet working'!$B$3:$C$158,2,0) -> 420 | D26: =VLOOKUP(B26,'rate sheet working'!$B$3:$D$158,3,0) -> 1.008 | E26: =D26+E27 -> 11192.671 | F26: =VLOOKUP(B26,'rate sheet working'!$B$3:$E$158,4,0) -> 1.1206832 | G26: =VLOOKUP(B26,'rate sheet periphery 1'!$B$5:$F$110,5,0) -> 4.4444968 | H26: =F26+G26 -> 5.56518
A27: 25 | B27: JP Bina | C27: =VLOOKUP(B27,'rate sheet working'!$B$3:$C$158,2,0) -> 500 | D27: =VLOOKUP(B27,'rate sheet working'!$B$3:$D$158,3,0) -> 350 | E27: =D27+E28 -> 11191.663 | F27: =VLOOKUP(B27,'rate sheet working'!$B$3:$E$158,4,0) -> 1.9099997 | G27: =VLOOKUP(B27,'rate sheet periphery 1'!$B$5:$F$110,5,0) -> 3.59077 | H27: =F27+G27 -> 5.5007697
A28: 26 | B28: RKM Powergen (Talcher Field) (Medium Term) | C28: =VLOOKUP(B28,'rate sheet working'!$B$3:$C$158,2,0) -> 720 | D28: =VLOOKUP(B28,'rate sheet working'!$B$3:$D$158,3,0) -> 72.73 | E28: =D28+E29 -> 10841.663 | F28: =VLOOKUP(B28,'rate sheet working'!$B$3:$E$158,4,0) -> 2.761 | G28: =VLOOKUP(B28,'rate sheet periphery 1'!$B$5:$F$110,5,0) -> 2.6883239 | H28: =F28+G28 -> 5.4493239
A29: 27 | B29: Jindal Power Limited (Medium Term) | C29: =VLOOKUP(B29,'rate sheet working'!$B$3:$C$158,2,0) -> 2400 | D29: =VLOOKUP(B29,'rate sheet working'!$B$3:$D$158,3,0) -> 72.73 | E29: =D29+E30 -> 10768.933 | F29: =VLOOKUP(B29,'rate sheet working'!$B$3:$E$158,4,0) -> 2.6 | G29: =VLOOKUP(B29,'rate sheet periphery 1'!$B$5:$F$110,5,0) -> 2.7850262 | H29: =F29+G29 -> 5.3850262 | I29: =H29-H27 -> -0.11574357
A30: 28 | B30: RKM Powergen (IB Field) (Medium Term) | C30: =VLOOKUP(B30,'rate sheet working'!$B$3:$C$158,2,0) -> 720 | D30: =VLOOKUP(B30,'rate sheet working'!$B$3:$D$158,3,0) -> 72.73 | E30: =D30+E31 -> 10696.203 | F30: =VLOOKUP(B30,'rate sheet working'!$B$3:$E$158,4,0) -> 2.715 | G30: =VLOOKUP(B30,'rate sheet periphery 1'!$B$5:$F$110,5,0) -> 2.6412429 | H30: =F30+G30 -> 5.3562429
A31: 29 | B31: Meja (NR) | C31: =VLOOKUP(B31,'rate sheet working'!$B$3:$C$158,2,0) -> 1320 | D31: =VLOOKUP(B31,'rate sheet working'!$B$3:$D$158,3,0) -> 1.584 | E31: =D31+E32 -> 10623.473 | F31: =VLOOKUP(B31,'rate sheet working'!$B$3:$E$158,4,0) -> 2.2494753 | G31: =VLOOKUP(B31,'rate sheet periphery 1'!$B$5:$F$110,5,0) -> 3.0937435 | H31: =F31+G31 -> 5.3432187
A32: 30 | B32: TRN Energy Pvt. Ltd. (Medium Term) | C32: =VLOOKUP(B32,'rate sheet working'!$B$3:$C$158,2,0) -> 600 | D32: =VLOOKUP(B32,'rate sheet working'!$B$3:$D$158,3,0) -> 24.24 | E32: =D32+E33 -> 10621.889 | F32: =VLOOKUP(B32,'rate sheet working'!$B$3:$E$158,4,0) -> 2.16 | G32: =VLOOKUP(B32,'rate sheet periphery 1'!$B$5:$F$110,5,0) -> 3.0498012 | H32: =F32+G32 -> 5.2098012
A33: 31 | B33: Unchahar IV (NR) | C33: =VLOOKUP(B33,'rate sheet working'!$B$3:$C$158,2,0) -> 500 | D33: =VLOOKUP(B33,'rate sheet working'!$B$3:$D$158,3,0) -> 1.2 | E33: =D33+E34 -> 10597.649 | F33: =VLOOKUP(B33,'rate sheet working'!$B$3:$E$158,4,0) -> 1.6577601 | G33: =VLOOKUP(B33,'rate sheet periphery 1'!$B$5:$F$110,5,0) -> 3.5510387 | H33: =F33+G33 -> 5.2087988
A34: 32 | B34: SKS Power Generation (Medium Term) | C34: =VLOOKUP(B34,'rate sheet working'!$B$3:$C$158,2,0) -> 600 | D34: =VLOOKUP(B34,'rate sheet working'!$B$3:$D$158,3,0) -> 24.24 | E34: =D34+E35 -> 10596.449 | F34: =VLOOKUP(B34,'rate sheet working'!$B$3:$E$158,4,0) -> 2.253 | G34: =VLOOKUP(B34,'rate sheet periphery 1'!$B$5:$F$110,5,0) -> 2.8834484 | H34: =F34+G34 -> 5.1364484
A35: 33 | B35: Jindal India Thermal Power (Medium Term) | C35: =VLOOKUP(B35,'rate sheet working'!$B$3:$C$158,2,0) -> 1200 | D35: =VLOOKUP(B35,'rate sheet working'!$B$3:$D$158,3,0) -> 48.48 | E35: =D35+E36 -> 10572.209 | F35: =VLOOKUP(B35,'rate sheet working'!$B$3:$E$158,4,0) -> 2.57 | G35: =VLOOKUP(B35,'rate sheet periphery 1'!$B$5:$F$110,5,0) -> 2.5476041 | H35: =F35+G35 -> 5.1176041
A36: 34 | B36: Tanda II | C36: =VLOOKUP(B36,'rate sheet working'!$B$3:$C$158,2,0) -> 1320 | D36: =VLOOKUP(B36,'rate sheet working'!$B$3:$D$158,3,0) -> 2.112 | E36: =D36+E37 -> 10523.729 | F36: =VLOOKUP(B36,'rate sheet working'!$B$3:$E$158,4,0) -> 1.7669774 | G36: =VLOOKUP(B36,'rate sheet periphery 1'!$B$5:$F$110,5,0) -> 3.345345 | H36: =F36+G36 -> 5.1123224
A37: 35 | B37: Mauda-I | C37: =VLOOKUP(B37,'rate sheet working'!$B$3:$C$158,2,0) -> 1000 | D37: =VLOOKUP(B37,'rate sheet working'!$B$3:$D$158,3,0) -> 169.12 | E37: =D37+E38 -> 10521.617 | F37: =VLOOKUP(B37,'rate sheet working'!$B$3:$E$158,4,0) -> 1.6931572 | G37: =VLOOKUP(B37,'rate sheet periphery 1'!$B$5:$F$110,5,0) -> 3.3375183 | H37: =F37+G37 -> 5.0306755 | I37: =H37-H28 -> -0.41864837
A38: 36 | B38: MB Power | C38: =VLOOKUP(B38,'rate sheet working'!$B$3:$C$158,2,0) -> 1200 | D38: =VLOOKUP(B38,'rate sheet working'!$B$3:$D$158,3,0) -> 420 | E38: =D38+E39 -> 10352.497 | F38: =VLOOKUP(B38,'rate sheet working'!$B$3:$E$158,4,0) -> 1.6776554 | G38: =VLOOKUP(B38,'rate sheet periphery 1'!$B$5:$F$110,5,0) -> 3.327091 | H38: =F38+G38 -> 5.0047464
A39: 37 | B39: DVC (DTPS) (STOA LOI) | C39: =VLOOKUP(B39,'rate sheet working'!$B$3:$C$158,2,0) -> 1000 | D39: =VLOOKUP(B39,'rate sheet working'!$B$3:$D$158,3,0) -> 100 | E39: =D39+E40 -> 9932.4973 | F39: =VLOOKUP(B39,'rate sheet working'!$B$3:$E$158,4,0) -> 1.5060402 | G39: =VLOOKUP(B39,'rate sheet periphery 1'!$B$5:$F$110,5,0) -> 3.4702929 | H39: =F39+G39 -> 4.9763332
A40: 38 | B40: Mauda-II | C40: =VLOOKUP(B40,'rate sheet working'!$B$3:$C$158,2,0) -> 1320 | D40: =VLOOKUP(B40,'rate sheet working'!$B$3:$D$158,3,0) -> 235.04 | E40: =D40+E41 -> 9832.4973 | F40: =VLOOKUP(B40,'rate sheet working'!$B$3:$E$158,4,0) -> 1.5812064 | G40: =VLOOKUP(B40,'rate sheet periphery 1'!$B$5:$F$110,5,0) -> 3.3322471 | H40: =F40+G40 -> 4.9134535 | I40: =H40-H39 -> -0.062879657
A41: 39 | B41: Unchahar III (NR) | C41: =VLOOKUP(B41,'rate sheet working'!$B$3:$C$158,2,0) -> 210 | D41: =VLOOKUP(B41,'rate sheet working'!$B$3:$D$158,3,0) -> 0.483 | E41: =D41+E42 -> 9597.4573 | F41: =VLOOKUP(B41,'rate sheet working'!$B$3:$E$158,4,0) -> 1.2090519 | G41: =VLOOKUP(B41,'rate sheet periphery 1'!$B$5:$F$110,5,0) -> 3.6889117 | H41: =F41+G41 -> 4.8979636
A42: 40 | B42: National Capital Thermal Power Station Dadri II (NR) | C42: =VLOOKUP(B42,'rate sheet working'!$B$3:$C$158,2,0) -> 980 | D42: =VLOOKUP(B42,'rate sheet working'!$B$3:$D$158,3,0) -> 2.058 | E42: =D42+E43 -> 9596.9743 | F42: =VLOOKUP(B42,'rate sheet working'!$B$3:$E$158,4,0) -> 0.65153793 | G42: =VLOOKUP(B42,'rate sheet periphery 1'!$B$5:$F$110,5,0) -> 4.1246579 | H42: =F42+G42 -> 4.7761958
A43: 41 | B43: Unchahar I (NR) | C43: =VLOOKUP(B43,'rate sheet working'!$B$3:$C$158,2,0) -> 420 | D43: =VLOOKUP(B43,'rate sheet working'!$B$3:$D$158,3,0) -> 0.336 | E43: =D43+E44 -> 9594.9163 | F43: =VLOOKUP(B43,'rate sheet working'!$B$3:$E$158,4,0) -> 1.0459098 | G43: =VLOOKUP(B43,'rate sheet periphery 1'!$B$5:$F$110,5,0) -> 3.6992354 | H43: =F43+G43 -> 4.7451452 | I43: =H43-H45 -> 0.16771132
A44: 42 | B44: Jhabua Power | C44: =VLOOKUP(B44,'rate sheet working'!$B$3:$C$158,2,0) -> 600 | D44: =VLOOKUP(B44,'rate sheet working'!$B$3:$D$158,3,0) -> 180 | E44: =D44+E45 -> 9594.5803 | F44: =VLOOKUP(B44,'rate sheet working'!$B$3:$E$158,4,0) -> 1.7847334 | G44: =VLOOKUP(B44,'rate sheet periphery 1'!$B$5:$F$110,5,0) -> 2.866154 | H44: =F44+G44 -> 4.6508874
A45: 43 | B45: STPS Sarni 10 & 11 | C45: =VLOOKUP(B45,'rate sheet working'!$B$3:$C$158,2,0) -> 500 | D45: =VLOOKUP(B45,'rate sheet working'!$B$3:$D$158,3,0) -> 500 | E45: =D45+E46 -> 9414.5803 | F45: =VLOOKUP(B45,'rate sheet working'!$B$3:$E$158,4,0) -> 1.7914338 | G45: =VLOOKUP(B45,'rate sheet periphery 1'!$B$5:$F$110,5,0) -> 2.786 | H45: =F45+G45 -> 4.5774338 | I45: =H45-H46 -> 0.14748349
A46: 44 | B46: SSTPS Khandwa (Singaji) | C46: =VLOOKUP(B46,'rate sheet working'!$B$3:$C$158,2,0) -> 1200 | D46: =VLOOKUP(B46,'rate sheet working'!$B$3:$D$158,3,0) -> 1200 | E46: =D46+E47 -> 8914.5803 | F46: =VLOOKUP(B46,'rate sheet working'!$B$3:$E$158,4,0) -> 1.3029504 | G46: =VLOOKUP(B46,'rate sheet periphery 1'!$B$5:$F$110,5,0) -> 3.127 | H46: =F46+G46 -> 4.4299504 | I46: =H46-H47 -> 0.23467709
A47: 45 | B47: SSTPS Khandwa (Singaji) # 3 & 4 | C47: =VLOOKUP(B47,'rate sheet working'!$B$3:$C$158,2,0) -> 1320 | D47: =VLOOKUP(B47,'rate sheet working'!$B$3:$D$158,3,0) -> 1320 | E47: =D47+E48 -> 7714.5803 | F47: =VLOOKUP(B47,'rate sheet working'!$B$3:$E$158,4,0) -> 1.2692733 | G47: =VLOOKUP(B47,'rate sheet periphery 1'!$B$5:$F$110,5,0) -> 2.926 | H47: =F47+G47 -> 4.1952733 | I47: =H47-H49 -> 0.10770969
A48: 46 | B48: SGTPS -4x210 | C48: =VLOOKUP(B48,'rate sheet working'!$B$3:$C$158,2,0) -> 840 | D48: =VLOOKUP(B48,'rate sheet working'!$B$3:$D$158,3,0) -> 840 | E48: =D48+E49 -> 6394.5803 | F48: =VLOOKUP(B48,'rate sheet working'!$B$3:$E$158,4,0) -> 1.0462155 | G48: =VLOOKUP(B48,'rate sheet periphery 1'!$B$5:$F$110,5,0) -> 3.067 | H48: =F48+G48 -> 4.1132155
A49: 47 | B49: VSTPS-V | C49: =VLOOKUP(B49,'rate sheet working'!$B$3:$C$158,2,0) -> 500 | D49: =VLOOKUP(B49,'rate sheet working'!$B$3:$D$158,3,0) -> 127.86 | E49: =D49+E50 -> 5554.5803 | F49: =VLOOKUP(B49,'rate sheet working'!$B$3:$E$158,4,0) -> 1.7249287 | G49: =VLOOKUP(B49,'rate sheet periphery 1'!$B$5:$F$110,5,0) -> 2.3626348 | H49: =F49+G49 -> 4.0875636
A50: 48 | B50: VSTPS-IV | C50: =VLOOKUP(B50,'rate sheet working'!$B$3:$C$158,2,0) -> 1000 | D50: =VLOOKUP(B50,'rate sheet working'!$B$3:$D$158,3,0) -> 256.41 | E50: =D50+E51 -> 5426.7203 | F50: =VLOOKUP(B50,'rate sheet working'!$B$3:$E$158,4,0) -> 1.6494464 | G50: =VLOOKUP(B50,'rate sheet periphery 1'!$B$5:$F$110,5,0) -> 2.3194208 | H50: =F50+G50 -> 3.9688673
A51: 49 | B51: KAHALGAON-II | C51: =VLOOKUP(B51,'rate sheet working'!$B$3:$C$158,2,0) -> 1500 | D51: =VLOOKUP(B51,'rate sheet working'!$B$3:$D$158,3,0) -> 73.95 | E51: =D51+E52 -> 5170.3103 | F51: =VLOOKUP(B51,'rate sheet working'!$B$3:$E$158,4,0) -> 0.92016616 | G51: =VLOOKUP(B51,'rate sheet periphery 1'!$B$5:$F$110,5,0) -> 2.8876229 | H51: =F51+G51 -> 3.8077891
A52: 50 | B52: Lara | C52: =VLOOKUP(B52,'rate sheet working'!$B$3:$C$158,2,0) -> 1600 | D52: =VLOOKUP(B52,'rate sheet working'!$B$3:$D$158,3,0) -> 147.42 | E52: =D52+E53 -> 5096.3603 | F52: =VLOOKUP(B52,'rate sheet working'!$B$3:$E$158,4,0) -> 2.2835364 | G52: =VLOOKUP(B52,'rate sheet periphery 1'!$B$5:$F$110,5,0) -> 1.4353899 | H52: =F52+G52 -> 3.7189263 | I52: =H52-H53 -> 0.2175333
A53: 51 | B53: Khurja STPP | C53: =VLOOKUP(B53,'rate sheet working'!$B$3:$C$158,2,0) -> 1320 | D53: =VLOOKUP(B53,'rate sheet working'!$B$3:$D$158,3,0) -> 3.0377688 | E53: =D53+E54 -> 4948.9403 | F53: =VLOOKUP(B53,'rate sheet working'!$B$3:$E$158,4,0) -> 1.3848414 | G53: =VLOOKUP(B53,'rate sheet periphery 1'!$B$5:$F$110,5,0) -> 2.1165516 | H53: =F53+G53 -> 3.501393 | I53: =H53-H55 -> 0.19733522
A54: 52 | B54: VSTPS-I | C54: =VLOOKUP(B54,'rate sheet working'!$B$3:$C$158,2,0) -> 1260 | D54: =VLOOKUP(B54,'rate sheet working'!$B$3:$D$158,3,0) -> 417.26 | E54: =D54+E55 -> 4945.9025 | F54: =VLOOKUP(B54,'rate sheet working'!$B$3:$E$158,4,0) -> 0.9173352 | G54: =VLOOKUP(B54,'rate sheet periphery 1'!$B$5:$F$110,5,0) -> 2.4640256 | H54: =F54+G54 -> 3.3813608
A55: 53 | B55: SGTPS -1x500 | C55: =VLOOKUP(B55,'rate sheet working'!$B$3:$C$158,2,0) -> 500 | D55: =VLOOKUP(B55,'rate sheet working'!$B$3:$D$158,3,0) -> 500 | E55: =D55+E56 -> 4528.6425 | F55: =VLOOKUP(B55,'rate sheet working'!$B$3:$E$158,4,0) -> 0.90705778 | G55: =VLOOKUP(B55,'rate sheet periphery 1'!$B$5:$F$110,5,0) -> 2.397 | H55: =F55+G55 -> 3.3040578
A56: 54 | B56: VSTPS-III | C56: =VLOOKUP(B56,'rate sheet working'!$B$3:$C$158,2,0) -> 1000 | D56: =VLOOKUP(B56,'rate sheet working'!$B$3:$D$158,3,0) -> 225.47 | E56: =D56+E57 -> 4028.6425 | F56: =VLOOKUP(B56,'rate sheet working'!$B$3:$E$158,4,0) -> 0.91111985 | G56: =VLOOKUP(B56,'rate sheet periphery 1'!$B$5:$F$110,5,0) -> 2.3424844 | H56: =F56+G56 -> 3.2536043 | I56: =H56-H57 -> 0.011994177
A57: 55 | B57: GANDHAR (APM) | C57: =VLOOKUP(B57,'rate sheet working'!$B$3:$C$158,2,0) -> 657.39 | D57: =VLOOKUP(B57,'rate sheet working'!$B$3:$D$158,3,0) -> 0.15 | E57: =D57+E58 -> 3803.1725 | F57: =VLOOKUP(B57,'rate sheet working'!$B$3:$E$158,4,0) -> 1.0465902 | G57: =VLOOKUP(B57,'rate sheet periphery 1'!$B$5:$F$110,5,0) -> 2.1950199 | H57: =F57+G57 -> 3.2416101
A58: 56 | B58: VSTPS-II | C58: =VLOOKUP(B58,'rate sheet working'!$B$3:$C$158,2,0) -> 1000 | D58: =VLOOKUP(B58,'rate sheet working'!$B$3:$D$158,3,0) -> 298.47 | E58: =D58+E59 -> 3803.0225 | F58: =VLOOKUP(B58,'rate sheet working'!$B$3:$E$158,4,0) -> 0.78386922 | G58: =VLOOKUP(B58,'rate sheet periphery 1'!$B$5:$F$110,5,0) -> 2.3705448 | H58: =F58+G58 -> 3.154414
A59: 57 | B59: Rihand III (NR) | C59: =VLOOKUP(B59,'rate sheet working'!$B$3:$C$158,2,0) -> 1000 | D59: =VLOOKUP(B59,'rate sheet working'!$B$3:$D$158,3,0) -> 2.4 | E59: =D59+E60 -> 3504.5525 | F59: =VLOOKUP(B59,'rate sheet working'!$B$3:$E$158,4,0) -> 1.4694115 | G59: =VLOOKUP(B59,'rate sheet periphery 1'!$B$5:$F$110,5,0) -> 1.6331869 | H59: =F59+G59 -> 3.1025984 | I59: =H59-#REF! -> #REF!
A60: 58 | B60: ATPS (210MW) Chachai | C60: =VLOOKUP(B60,'rate sheet working'!$B$3:$C$158,2,0) -> 210 | D60: =VLOOKUP(B60,'rate sheet working'!$B$3:$D$158,3,0) -> 210 | E60: =D60+E61 -> 3502.1525 | F60: =VLOOKUP(B60,'rate sheet working'!$B$3:$E$158,4,0) -> 1.2209309 | G60: =VLOOKUP(B60,'rate sheet periphery 1'!$B$5:$F$110,5,0) -> 1.829 | H60: =F60+G60 -> 3.0499309
A61: 59 | B61: Korba Power Ltd. (FSA) | C61: =VLOOKUP(B61,'rate sheet working'!$B$3:$C$158,2,0) -> 273 | D61: =VLOOKUP(B61,'rate sheet working'!$B$3:$D$158,3,0) -> 273 | E61: =D61+E62 -> 3292.1525 | F61: =VLOOKUP(B61,'rate sheet working'!$B$3:$E$158,4,0) -> 1.033276 | G61: =VLOOKUP(B61,'rate sheet periphery 1'!$B$5:$F$110,5,0) -> 1.9654646 | H61: =F61+G61 -> 2.9987406 | I61: =H61-H60 -> -0.05119039
A62: 60 | B62: Auraiya APM (NR) | C62: =VLOOKUP(B62,'rate sheet working'!$B$3:$C$158,2,0) -> 663 | D62: =VLOOKUP(B62,'rate sheet working'!$B$3:$D$158,3,0) -> 1.5249 | E62: =D62+E63 -> 3019.1525 | F62: =VLOOKUP(B62,'rate sheet working'!$B$3:$E$158,4,0) -> 0.635 | G62: =VLOOKUP(B62,'rate sheet periphery 1'!$B$5:$F$110,5,0) -> 2.1814187 | H62: =F62+G62 -> 2.8164187 | I62: =H62-H63 -> 0.00078335859
A63: 61 | B63: Singrauli (NR) | C63: =VLOOKUP(B63,'rate sheet working'!$B$3:$C$158,2,0) -> 2000 | D63: =VLOOKUP(B63,'rate sheet working'!$B$3:$D$158,3,0) -> 3.8 | E63: =D63+E64 -> 3017.6276 | F63: =VLOOKUP(B63,'rate sheet working'!$B$3:$E$158,4,0) -> 0.76384627 | G63: =VLOOKUP(B63,'rate sheet periphery 1'!$B$5:$F$110,5,0) -> 2.0517891 | H63: =F63+G63 -> 2.8156353 | I63: =H63-H65 -> 0.093967635
A64: 62 | B64: Anta APM (NR) | C64: =VLOOKUP(B64,'rate sheet working'!$B$3:$C$158,2,0) -> 419 | D64: =VLOOKUP(B64,'rate sheet working'!$B$3:$D$158,3,0) -> 1.0056 | E64: =D64+E65 -> 3013.8276 | F64: =VLOOKUP(B64,'rate sheet working'!$B$3:$E$158,4,0) -> 0.709 | G64: =VLOOKUP(B64,'rate sheet periphery 1'!$B$5:$F$110,5,0) -> 2.0977192 | H64: =F64+G64 -> 2.8067192
A65: 63 | B65: Mahan Energen Ltd. (5%) | C65: =VLOOKUP(B65,'rate sheet working'!$B$3:$C$158,2,0) -> 1200 | D65: =VLOOKUP(B65,'rate sheet working'!$B$3:$D$158,3,0) -> 60 | E65: =D65+E66 -> 3012.822 | F65: =VLOOKUP(B65,'rate sheet working'!$B$3:$E$158,4,0) -> 0 | G65: =VLOOKUP(B65,'rate sheet periphery 1'!$B$5:$F$110,5,0) -> 2.7216677 | H65: =F65+G65 -> 2.7216677 | I65: =H65-H66 -> 0.047260472
A66: 64 | B66: Dadri APM (NR) | C66: =VLOOKUP(B66,'rate sheet working'!$B$3:$C$158,2,0) -> 830 | D66: =VLOOKUP(B66,'rate sheet working'!$B$3:$D$158,3,0) -> 1.992 | E66: =D66+E67 -> 2952.822 | F66: =VLOOKUP(B66,'rate sheet working'!$B$3:$E$158,4,0) -> 0.52960707 | G66: =VLOOKUP(B66,'rate sheet periphery 1'!$B$5:$F$110,5,0) -> 2.1448002 | H66: =F66+G66 -> 2.6744072 | I66: =H66-H67 -> 0.0067670647
A67: 65 | B67: SIPAT I | C67: =VLOOKUP(B67,'rate sheet working'!$B$3:$C$158,2,0) -> 1980 | D67: =VLOOKUP(B67,'rate sheet working'!$B$3:$D$158,3,0) -> 283 | E67: =D67+E68 -> 2950.83 | F67: =VLOOKUP(B67,'rate sheet working'!$B$3:$E$158,4,0) -> 1.2557147 | G67: =VLOOKUP(B67,'rate sheet periphery 1'!$B$5:$F$110,5,0) -> 1.4119255 | H67: =F67+G67 -> 2.6676402 | I67: =H67-#REF! -> #REF!
A68: 66 | B68: JP Nigrie | C68: =VLOOKUP(B68,'rate sheet working'!$B$3:$C$158,2,0) -> 1320 | D68: =VLOOKUP(B68,'rate sheet working'!$B$3:$D$158,3,0) -> 495 | E68: =D68+E69 -> 2667.83 | F68: =VLOOKUP(B68,'rate sheet working'!$B$3:$E$158,4,0) -> 1.7145489 | G68: =VLOOKUP(B68,'rate sheet periphery 1'!$B$5:$F$110,5,0) -> 0.92760701 | H68: =F68+G68 -> 2.6421559
A69: 67 | B69: KSTPS-III | C69: =VLOOKUP(B69,'rate sheet working'!$B$3:$C$158,2,0) -> 500 | D69: =VLOOKUP(B69,'rate sheet working'!$B$3:$D$158,3,0) -> 62.5 | E69: =D69+E70 -> 2172.83 | F69: =VLOOKUP(B69,'rate sheet working'!$B$3:$E$158,4,0) -> 1.1259324 | G69: =VLOOKUP(B69,'rate sheet periphery 1'!$B$5:$F$110,5,0) -> 1.4664778 | H69: =F69+G69 -> 2.5924101
A70: 68 | B70: KAWAS (APM) | C70: =VLOOKUP(B70,'rate sheet working'!$B$3:$C$158,2,0) -> 656.2 | D70: =VLOOKUP(B70,'rate sheet working'!$B$3:$D$158,3,0) -> 0.13 | E70: =D70+E71 -> 2110.33 | F70: =VLOOKUP(B70,'rate sheet working'!$B$3:$E$158,4,0) -> 0.85915096 | G70: =VLOOKUP(B70,'rate sheet periphery 1'!$B$5:$F$110,5,0) -> 1.6708516 | H70: =F70+G70 -> 2.5300026
A71: 69 | B71: Rihand I (NR) | C71: =VLOOKUP(B71,'rate sheet working'!$B$3:$C$158,2,0) -> 1000 | D71: =VLOOKUP(B71,'rate sheet working'!$B$3:$D$158,3,0) -> 2 | E71: =D71+E72 -> 2110.2 | F71: =VLOOKUP(B71,'rate sheet working'!$B$3:$E$158,4,0) -> 0.83038165 | G71: =VLOOKUP(B71,'rate sheet periphery 1'!$B$5:$F$110,5,0) -> 1.6678175 | H71: =F71+G71 -> 2.4981992
A72: 70 | B72: Rihand II (NR) | C72: =VLOOKUP(B72,'rate sheet working'!$B$3:$C$158,2,0) -> 1000 | D72: =VLOOKUP(B72,'rate sheet working'!$B$3:$D$158,3,0) -> 2.1 | E72: =D72+E73 -> 2108.2 | F72: =VLOOKUP(B72,'rate sheet working'!$B$3:$E$158,4,0) -> 0.77934853 | G72: =VLOOKUP(B72,'rate sheet periphery 1'!$B$5:$F$110,5,0) -> 1.655158 | H72: =F72+G72 -> 2.4345065
A73: 71 | B73: SIPAT II | C73: =VLOOKUP(B73,'rate sheet working'!$B$3:$C$158,2,0) -> 1000 | D73: =VLOOKUP(B73,'rate sheet working'!$B$3:$D$158,3,0) -> 168.47 | E73: =D73+E74 -> 2106.1 | F73: =VLOOKUP(B73,'rate sheet working'!$B$3:$E$158,4,0) -> 0.98415242 | G73: =VLOOKUP(B73,'rate sheet periphery 1'!$B$5:$F$110,5,0) -> 1.4166365 | H73: =F73+G73 -> 2.4007889
A74: 72 | B74: KSTPS | C74: =VLOOKUP(B74,'rate sheet working'!$B$3:$C$158,2,0) -> 2100 | D74: =VLOOKUP(B74,'rate sheet working'!$B$3:$D$158,3,0) -> 452.63 | E74: =D74+E75 -> 1937.63 | F74: =VLOOKUP(B74,'rate sheet working'!$B$3:$E$158,4,0) -> 0.75506732 | G74: =VLOOKUP(B74,'rate sheet periphery 1'!$B$5:$F$110,5,0) -> 1.5110332 | H74: =F74+G74 -> 2.2661005
A75: 73 | B75: Sasan | C75: =VLOOKUP(B75,'rate sheet working'!$B$3:$C$158,2,0) -> 3960 | D75: =VLOOKUP(B75,'rate sheet working'!$B$3:$D$158,3,0) -> 1485 | E75: =D75+E76 -> 1485 | F75: =VLOOKUP(B75,'rate sheet working'!$B$3:$E$158,4,0) -> 0.16570016 | G75: =VLOOKUP(B75,'rate sheet periphery 1'!$B$5:$F$110,5,0) -> 1.5560391 | H75: =F75+G75 -> 1.7217393

Sheet rate sheet periphery 1
G2: 10.04.2026
A3: ='Excl URS 3 '!A1:N1 -> Details of power purchase cost per unit of Thermal and Gas Power stations for MOD for the month of March 2026
A4: Sr. No. | B4: Name of Generating Stations | C4: Installed Capacity (MW) | D4: MPPMCL Share (MW) | E4: Cumulative capacity (MW) | F4: Variable rate at MP periphery in Rs./kwh (excl biomass) | G4: Remarks
A5: 1 | B5: Indira Gandhi STPS (Jhajjar) (NR) | C5: =VLOOKUP(B5,'rate sheet working'!$B$3:$C$158,2,0) -> 1500 | D5: =VLOOKUP(B5,'rate sheet working'!$B$3:$D$158,3,0) -> 1.8 | E5: =D5+E6 -> 12978.414 | F5: =VLOOKUP(B5,'Excl URS 3 '!$B$6:$N$61,13,FALSE) -> 4.447716 | G5: Above 8000 MW partially scheduled
A6: =A5+1 -> 2 | B6: Unchahar II (NR) | C6: =VLOOKUP(B6,'rate sheet working'!$B$3:$C$158,2,0) -> 420 | D6: =VLOOKUP(B6,'rate sheet working'!$B$3:$D$158,3,0) -> 1.008 | E6: =D6+E7 -> 12976.614 | F6: =VLOOKUP(B6,'Excl URS 3 '!$B$6:$N$61,13,FALSE) -> 4.4444968
A7: =A6+1 -> 3 | B7: Solapur I | C7: =VLOOKUP(B7,'rate sheet working'!$B$3:$C$158,2,0) -> 1320 | D7: =VLOOKUP(B7,'rate sheet working'!$B$3:$D$158,3,0) -> 295.88 | E7: =D7+E8 -> 12975.606 | F7: =VLOOKUP(B7,'Excl URS 3 '!$B$6:$N$61,13,FALSE) -> 4.2412187
A8: =A7+1 -> 4 | B8: Gadarwara | C8: =VLOOKUP(B8,'rate sheet working'!$B$3:$C$158,2,0) -> 1600 | D8: =VLOOKUP(B8,'rate sheet working'!$B$3:$D$158,3,0) -> 800 | E8: =D8+E9 -> 12679.726 | F8: =VLOOKUP(B8,'Excl URS 3 '!$B$6:$N$61,13,FALSE) -> 4.1557098
A9: =A8+1 -> 5 | B9: National Capital Thermal Power Station Dadri II (NR) | C9: =VLOOKUP(B9,'rate sheet working'!$B$3:$C$158,2,0) -> 980 | D9: =VLOOKUP(B9,'rate sheet working'!$B$3:$D$158,3,0) -> 2.058 | E9: =D9+E10 -> 11879.726 | F9: =VLOOKUP(B9,'Excl URS 3 '!$B$6:$N$61,13,FALSE) -> 4.1246579
A10: =A9+1 -> 6 | B10: BLA | C10: =VLOOKUP(B10,'rate sheet working'!$B$3:$C$158,2,0) -> 90 | D10: =VLOOKUP(B10,'rate sheet working'!$B$3:$D$158,3,0) -> 27 | E10: =D10+E11 -> 11877.668 | F10: =VLOOKUP(B10,'Excl URS 3 '!$B$6:$N$61,13,FALSE) -> 3.98201
A11: =A10+1 -> 7 | B11: Unchahar I (NR) | C11: =VLOOKUP(B11,'rate sheet working'!$B$3:$C$158,2,0) -> 420 | D11: =VLOOKUP(B11,'rate sheet working'!$B$3:$D$158,3,0) -> 0.336 | E11: =D11+E12 -> 11850.668 | F11: =VLOOKUP(B11,'Excl URS 3 '!$B$6:$N$61,13,FALSE) -> 3.6992354
A12: =A11+1 -> 8 | B12: Unchahar III (NR) | C12: =VLOOKUP(B12,'rate sheet working'!$B$3:$C$158,2,0) -> 210 | D12: =VLOOKUP(B12,'rate sheet working'!$B$3:$D$158,3,0) -> 0.483 | E12: =D12+E13 -> 11850.332 | F12: =VLOOKUP(B12,'Excl URS 3 '!$B$6:$N$61,13,FALSE) -> 3.6889117
A13: =A12+1 -> 9 | B13: JP Bina | C13: =VLOOKUP(B13,'rate sheet working'!$B$3:$C$158,2,0) -> 500 | D13: =VLOOKUP(B13,'rate sheet working'!$B$3:$D$158,3,0) -> 350 | E13: =D13+E14 -> 11849.849 | F13: =VLOOKUP(B13,'Excl URS 3 '!$B$6:$N$61,13,FALSE) -> 3.59077
A14: =A13+1 -> 10 | B14: Khargone | C14: =VLOOKUP(B14,'rate sheet working'!$B$3:$C$158,2,0) -> 1320 | D14: =VLOOKUP(B14,'rate sheet working'!$B$3:$D$158,3,0) -> 660 | E14: =D14+E15 -> 11499.849 | F14: =VLOOKUP(B14,'Excl URS 3 '!$B$6:$N$61,13,FALSE) -> 3.5897484
A15: =A14+1 -> 11 | B15: Ghatampur Thermal Power Station (NUPPL) | C15: =VLOOKUP(B15,'rate sheet working'!$B$3:$C$158,2,0) -> 660 | D15: =VLOOKUP(B15,'rate sheet working'!$B$3:$D$158,3,0) -> 1.0626 | E15: =D15+E16 -> 10839.849 | F15: =VLOOKUP(B15,'Excl URS 3 '!$B$6:$N$61,13,FALSE) -> 3.5697845
A16: =A15+1 -> 12 | B16: Unchahar IV (NR) | C16: =VLOOKUP(B16,'rate sheet working'!$B$3:$C$158,2,0) -> 500 | D16: =VLOOKUP(B16,'rate sheet working'!$B$3:$D$158,3,0) -> 1.2 | E16: =D16+E17 -> 10838.786 | F16: =VLOOKUP(B16,'Excl URS 3 '!$B$6:$N$61,13,FALSE) -> 3.5510387
A17: =A16+1 -> 13 | B17: DVC (DTPS) (STOA LOI) | C17: =VLOOKUP(B17,'rate sheet working'!$B$3:$C$158,2,0) -> 1000 | D17: =VLOOKUP(B17,'rate sheet working'!$B$3:$D$158,3,0) -> 100 | E17: =D17+E18 -> 10837.586 | F17: =VLOOKUP(B17,'Excl URS 3 '!$B$6:$N$61,13,FALSE) -> 3.4702929
... A24: =A23+1 -> 20 | B24: SGTPS -4x210 | C24: =VLOOKUP(B24,'rate sheet working'!$B$3:$C$158,2,0) -> 840 | D24: =VLOOKUP(B24,'rate sheet working'!$B$3:$D$158,3,0) -> 840 | E24: =D24+E25 -> 8709.7303 | F24: =VLOOKUP(B24,'Excl URS 3 '!$B$6:$N$61,13,FALSE) -> 3.067
A25: =A24+1 -> 21 | B25: TRN Energy Pvt. Ltd. (Medium Term) | C25: =VLOOKUP(B25,'rate sheet working'!$B$3:$C$158,2,0) -> 600 | D25: =VLOOKUP(B25,'rate sheet working'!$B$3:$D$158,3,0) -> 24.24 | E25: =D25+E26 -> 7869.7303 | F25: =VLOOKUP(B25,'Excl URS 3 '!$B$6:$N$61,13,FALSE) -> 3.0498012 | G25: Below 8000 MW normally scheduled round the year
A26: =A25+1 -> 22 | B26: SSTPS Khandwa (Singaji) # 3 & 4 | C26: =VLOOKUP(B26,'rate sheet working'!$B$3:$C$158,2,0) -> 1320 | D26: =VLOOKUP(B26,'rate sheet working'!$B$3:$D$158,3,0) -> 1320 | E26: =D26+E27 -> 7845.4903 | F26: =VLOOKUP(B26,'Excl URS 3 '!$B$6:$N$61,13,FALSE) -> 2.926
A27: =A26+1 -> 23 | B27: KAHALGAON-II | C27: =VLOOKUP(B27,'rate sheet working'!$B$3:$C$158,2,0) -> 1500 | D27: =VLOOKUP(B27,'rate sheet working'!$B$3:$D$158,3,0) -> 73.95 | E27: =D27+E28 -> 6525.4903 | F27: =VLOOKUP(B27,'Excl URS 3 '!$B$6:$N$61,13,FALSE) -> 2.8876229
A28: =A27+1 -> 24 | B28: SKS Power Generation (Medium Term) | C28: =VLOOKUP(B28,'rate sheet working'!$B$3:$C$158,2,0) -> 600 | D28: =VLOOKUP(B28,'rate sheet working'!$B$3:$D$158,3,0) -> 24.24 | E28: =D28+E29 -> 6451.5403 | F28: =VLOOKUP(B28,'Excl URS 3 '!$B$6:$N$61,13,FALSE) -> 2.8834484
A29: =A28+1 -> 25 | B29: Jhabua Power | C29: =VLOOKUP(B29,'rate sheet working'!$B$3:$C$158,2,0) -> 600 | D29: =VLOOKUP(B29,'rate sheet working'!$B$3:$D$158,3,0) -> 180 | E29: =D29+E30 -> 6427.3003 | F29: =VLOOKUP(B29,'Excl URS 3 '!$B$6:$N$61,13,FALSE) -> 2.866154
A30: =A29+1 -> 26 | B30: STPS Sarni 10 & 11 | C30: =VLOOKUP(B30,'rate sheet working'!$B$3:$C$158,2,0) -> 500 | D30: =VLOOKUP(B30,'rate sheet working'!$B$3:$D$158,3,0) -> 500 | E30: =D30+E31 -> 6247.3003 | F30: =VLOOKUP(B30,'Excl URS 3 '!$B$6:$N$61,13,FALSE) -> 2.786
A31: =A30+1 -> 27 | B31: Jindal Power Limited (Medium Term) | C31: =VLOOKUP(B31,'rate sheet working'!$B$3:$C$158,2,0) -> 2400 | D31: =VLOOKUP(B31,'rate sheet working'!$B$3:$D$158,3,0) -> 72.73 | E31: =D31+E32 -> 5747.3003 | F31: =VLOOKUP(B31,'Excl URS 3 '!$B$6:$N$61,13,FALSE) -> 2.7850262
A32: =A31+1 -> 28 | B32: Mahan Energen Ltd. (5%) | C32: =VLOOKUP(B32,'rate sheet working'!$B$3:$C$158,2,0) -> 1200 | D32: =VLOOKUP(B32,'rate sheet working'!$B$3:$D$158,3,0) -> 60 | E32: =D32+E33 -> 5674.5703 | F32: =VLOOKUP(B32,'Excl URS 3 '!$B$6:$N$61,13,FALSE) -> 2.7216677
A33: =A32+1 -> 29 | B33: RKM Powergen (Talcher Field) (Medium Term) | C33: =VLOOKUP(B33,'rate sheet working'!$B$3:$C$158,2,0) -> 720 | D33: =VLOOKUP(B33,'rate sheet working'!$B$3:$D$158,3,0) -> 72.73 | E33: =D33+E34 -> 5614.5703 | F33: =VLOOKUP(B33,'Excl URS 3 '!$B$6:$N$61,13,FALSE) -> 2.6883239
A34: =A33+1 -> 30 | B34: RKM Powergen (IB Field) (Medium Term) | C34: =VLOOKUP(B34,'rate sheet working'!$B$3:$C$158,2,0) -> 720 | D34: =VLOOKUP(B34,'rate sheet working'!$B$3:$D$158,3,0) -> 72.73 | E34: =D34+E35 -> 5541.8403 | F34: =VLOOKUP(B34,'Excl URS 3 '!$B$6:$N$61,13,FALSE) -> 2.6412429
A35: =A34+1 -> 31 | B35: Jindal India Thermal Power (Medium Term) | C35: =VLOOKUP(B35,'rate sheet working'!$B$3:$C$158,2,0) -> 1200 | D35: =VLOOKUP(B35,'rate sheet working'!$B$3:$D$158,3,0) -> 48.48 | E35: =D35+E36 -> 5469.1103 | F35: =VLOOKUP(B35,'Excl URS 3 '!$B$6:$N$61,13,FALSE) -> 2.5476041
A36: =A35+1 -> 32 | B36: VSTPS-I | C36: =VLOOKUP(B36,'rate sheet working'!$B$3:$C$158,2,0) -> 1260 | D36: =VLOOKUP(B36,'rate sheet working'!$B$3:$D$158,3,0) -> 417.26 | E36: =D36+E37 -> 5420.6303 | F36: =VLOOKUP(B36,'Excl URS 3 '!$B$6:$N$61,13,FALSE) -> 2.4640256
A37: =A36+1 -> 33 | B37: SGTPS -1x500 | C37: =VLOOKUP(B37,'rate sheet working'!$B$3:$C$158,2,0) -> 500 | D37: =VLOOKUP(B37,'rate sheet working'!$B$3:$D$158,3,0) -> 500 | E37: =D37+E38 -> 5003.3703 | F37: =VLOOKUP(B37,'Excl URS 3 '!$B$6:$N$61,13,FALSE) -> 2.397
... A60: =A59+1 -> 56 | B60: JP Nigrie | C60: =VLOOKUP(B60,'rate sheet working'!$B$3:$C$158,2,0) -> 1320 | D60: =VLOOKUP(B60,'rate sheet working'!$B$3:$D$158,3,0) -> 495 | E60: =D60+E61 -> 495 | F60: =VLOOKUP(B60,'Excl URS 3 '!$B$6:$N$61,13,FALSE) -> 0.92760701
B62: Details of power purchase cost per unit of Hydel Power Stations for MOD on the basis of rates available from bills of March 2026
A63: Sr. No. | B63: Name of Generating Stations | C63: Installed Capacity (MW) | D63: MPPMCL Share (MW) | E63: Cumulative Availibility (MW) | F63: Variable rate at MP periphery in Rs./kwh
A64: 1 | B64: ='Excl URS 3 '!B68 -> Koteshwar (NR) | C64: =VLOOKUP(B64,'rate sheet working'!$B$3:$C$158,2,0) -> 400 | D64: =VLOOKUP(B64,'rate sheet working'!$B$3:$D$158,3,0) -> 0.64 | E64: =D64+E65 -> 3351.4726 | F64: ='Excl URS 3 '!J68 -> 3.0864198
A65: =A64+1 -> 2 | B65: ='Excl URS 3 '!B69 -> Kishanganga (NR) | C65: =VLOOKUP(B65,'rate sheet working'!$B$3:$C$158,2,0) -> 330 | D65: =VLOOKUP(B65,'rate sheet working'!$B$3:$D$158,3,0) -> 0.759 | E65: =D65+E66 -> 3350.8326 | F65: ='Excl URS 3 '!J69 -> 2.4984306
A66: =A65+1 -> 3 | B66: ='Excl URS 3 '!B70 -> Dulhasti (NR) | C66: =VLOOKUP(B66,'rate sheet working'!$B$3:$C$158,2,0) -> 390 | D66: =VLOOKUP(B66,'rate sheet working'!$B$3:$D$158,3,0) -> 0.936 | E66: =D66+E67 -> 3350.0736 | F66: ='Excl URS 3 '!J70 -> 2.435656
A67: =A66+1 -> 4 | B67: ='Excl URS 3 '!B71 -> Koldam (NR) | C67: =VLOOKUP(B67,'rate sheet working'!$B$3:$C$158,2,0) -> 800 | D67: =VLOOKUP(B67,'rate sheet working'!$B$3:$D$158,3,0) -> 0.8 | E67: =D67+E68 -> 3349.1376 | F67: ='Excl URS 3 '!J71 -> 2.3278929
A68: =A67+1 -> 5 | B68: ='Excl URS 3 '!B72 -> URI II (NR) | C68: =VLOOKUP(B68,'rate sheet working'!$B$3:$C$158,2,0) -> 240 | D68: =VLOOKUP(B68,'rate sheet working'!$B$3:$D$158,3,0) -> 0.576 | E68: =D68+E69 -> 3348.3376 | F68: ='Excl URS 3 '!J72 -> 2.3090605
A69: =A68+1 -> 6 | B69: ='Excl URS 3 '!B73 -> Sewa II (NR) | C69: =VLOOKUP(B69,'rate sheet working'!$B$3:$C$158,2,0) -> 120 | D69: =VLOOKUP(B69,'rate sheet working'!$B$3:$D$158,3,0) -> 0.288 | E69: =D69+E70 -> 3347.7616 | F69: ='Excl URS 3 '!J73 -> 2.3080142
A70: =A69+1 -> 7 | B70: ='Excl URS 3 '!B74 -> Tehri I (NR) | C70: =VLOOKUP(B70,'rate sheet working'!$B$3:$C$158,2,0) -> 1000 | D70: =VLOOKUP(B70,'rate sheet working'!$B$3:$D$158,3,0) -> 1.6 | E70: =D70+E71 -> 3347.4736 | F70: ='Excl URS 3 '!J74 -> 2.212806
A71: =A70+1 -> 8 | B71: ='Excl URS 3 '!B75 -> Chamera III (NR) | C71: =VLOOKUP(B71,'rate sheet working'!$B$3:$C$158,2,0) -> 231 | D71: =VLOOKUP(B71,'rate sheet working'!$B$3:$D$158,3,0) -> 0.5544 | E71: =D71+E72 -> 3345.8736 | F71: ='Excl URS 3 '!J75 -> 2.1845574
A72: =A71+1 -> 9 | B72: ='Excl URS 3 '!B76 -> Rampur HEP (NR) | C72: =VLOOKUP(B72,'rate sheet working'!$B$3:$C$158,2,0) -> 412.02 | D72: =VLOOKUP(B72,'rate sheet working'!$B$3:$D$158,3,0) -> 0.659232 | E72: =D72+E73 -> 3345.3192 | F72: ='Excl URS 3 '!J76 -> 2.1772337
A73: =A72+1 -> 10 | B73: ='Excl URS 3 '!B77 -> ISP & OSP (25:11) | C73: =VLOOKUP(B73,'rate sheet working'!$B$3:$C$158,2,0) -> 1520 | D73: =VLOOKUP(B73,'rate sheet working'!$B$3:$D$158,3,0) -> 1520 | E73: =D73+E74 -> 3344.66 | F73: ='Excl URS 3 '!J77 -> 2.1584311
A74: =A73+1 -> 11 | B74: ='Excl URS 3 '!B78 -> Jawahar Sagar (Inter state project) | C74: =VLOOKUP(B74,'rate sheet working'!$B$3:$C$158,2,0) -> 99 | D74: =VLOOKUP(B74,'rate sheet working'!$B$3:$D$158,3,0) -> 49.5 | E74: =D74+E75 -> 1824.66 | F74: ='Excl URS 3 '!J78 -> 1.51
A75: =A74+1 -> 12 | B75: ='Excl URS 3 '!B79 -> R P sagar (Inter state project) | C75: =VLOOKUP(B75,'rate sheet working'!$B$3:$C$158,2,0) -> 172 | D75: =VLOOKUP(B75,'rate sheet working'!$B$3:$D$158,3,0) -> 86 | E75: =D75+E76 -> 1775.16 | F75: ='Excl URS 3 '!J79 -> 1.51
A76: =A75+1 -> 13 | B76: ='Excl URS 3 '!B80 -> Madikhera HPS | C76: =VLOOKUP(B76,'rate sheet working'!$B$3:$C$158,2,0) -> 60 | D76: =VLOOKUP(B76,'rate sheet working'!$B$3:$D$158,3,0) -> 60 | E76: =D76+E77 -> 1689.16 | F76: ='Excl URS 3 '!J80 -> 1.425
... A90: =A89+1 -> 27 | B90: ='Excl URS 3 '!B94 -> Bargi HPS | C90: =VLOOKUP(B90,'rate sheet working'!$B$3:$C$158,2,0) -> 90 | D90: =VLOOKUP(B90,'rate sheet working'!$B$3:$D$158,3,0) -> 90 | E90: =D90+E91 -> 90 | F90: ='Excl URS 3 '!J94 -> 0.19
B92: Details of power purchase cost per unit for high cost (ECR > Rs. 5) stations on the basis of rates available from bills of March 2026
A93: Sr. No. | B93: Name of Generating Stations | C93: Installed Capacity (MW) | D93: MPPMCL Share (MW) | E93: Cumulative Availibility (MW) | F93: Variable rate at MP periphery in Rs./kwh
A94: 1 | B94: ='Excl URS 3 '!B101 -> KAWAS (NAPM) | C94: =VLOOKUP(B94,'rate sheet working'!$B$3:$C$158,2,0) -> 0 | D94: =VLOOKUP(B94,'rate sheet working'!$B$3:$D$158,3,0) -> 0 | E94: =D94+E95 -> 50 | F94: ='Excl URS 3 '!K101 -> 37.274534
A95: =A94+1 -> 2 | B95: ='Excl URS 3 '!B102 -> GANDHAR (NAPM) | C95: =VLOOKUP(B95,'rate sheet working'!$B$3:$C$158,2,0) -> 0 | D95: =VLOOKUP(B95,'rate sheet working'!$B$3:$D$158,3,0) -> 0 | E95: =D95+E96 -> 50 | F95: ='Excl URS 3 '!K102 -> 31.092279
A96: =A95+1 -> 3 | B96: ='Excl URS 3 '!B103 -> KAWAS (Liquid) | C96: =VLOOKUP(B96,'rate sheet working'!$B$3:$C$158,2,0) -> 0 | D96: =VLOOKUP(B96,'rate sheet working'!$B$3:$D$158,3,0) -> 0 | E96: =D96+E97 -> 50 | F96: ='Excl URS 3 '!K103 -> 25.154844
A97: =A96+1 -> 4 | B97: ='Excl URS 3 '!B104 -> Dadri Liquid (NR) | C97: =VLOOKUP(B97,'rate sheet working'!$B$3:$C$158,2,0) -> 0 | D97: =VLOOKUP(B97,'rate sheet working'!$B$3:$D$158,3,0) -> 0 | E97: =D97+E98 -> 50 | F97: ='Excl URS 3 '!K104 -> 24.978029
A98: =A97+1 -> 5 | B98: ='Excl URS 3 '!B105 -> Auraiya Liquid (NR) | C98: =VLOOKUP(B98,'rate sheet working'!$B$3:$C$158,2,0) -> 0 | D98: =VLOOKUP(B98,'rate sheet working'!$B$3:$D$158,3,0) -> 0 | E98: =D98+E99 -> 50 | F98: ='Excl URS 3 '!K105 -> 19.553254
A99: =A98+1 -> 6 | B99: ='Excl URS 3 '!B106 -> Anta Liquid (NR) | C99: =VLOOKUP(B99,'rate sheet working'!$B$3:$C$158,2,0) -> 0 | D99: =VLOOKUP(B99,'rate sheet working'!$B$3:$D$158,3,0) -> 0 | E99: =D99+E100 -> 50 | F99: ='Excl URS 3 '!K106 -> 18.307177
A100: =A99+1 -> 7 | B100: ='Excl URS 3 '!B107 -> GANDHAR (LNG) | C100: =VLOOKUP(B100,'rate sheet working'!$B$3:$C$158,2,0) -> 0 | D100: =VLOOKUP(B100,'rate sheet working'!$B$3:$D$158,3,0) -> 0 | E100: =D100+E101 -> 50 | F100: ='Excl URS 3 '!K107 -> 13.649299
A101: =A100+1 -> 8 | B101: ='Excl URS 3 '!B108 -> Auraiya CLNG (NR) | C101: =VLOOKUP(B101,'rate sheet working'!$B$3:$C$158,2,0) -> 0 | D101: =VLOOKUP(B101,'rate sheet working'!$B$3:$D$158,3,0) -> 0 | E101: =D101+E102 -> 50 | F101: ='Excl URS 3 '!K108 -> 12.835321
A102: =A101+1 -> 9 | B102: ='Excl URS 3 '!B109 -> Dadri Comm LNG (NR) | C102: =VLOOKUP(B102,'rate sheet working'!$B$3:$C$158,2,0) -> 0 | D102: =VLOOKUP(B102,'rate sheet working'!$B$3:$D$158,3,0) -> 0 | E102: =D102+E103 -> 50 | F102: ='Excl URS 3 '!K109 -> 12.223268
A103: =A102+1 -> 10 | B103: ='Excl URS 3 '!B110 -> Auraiya LNG (NR) | C103: =VLOOKUP(B103,'rate sheet working'!$B$3:$C$158,2,0) -> 0 | D103: =VLOOKUP(B103,'rate sheet working'!$B$3:$D$158,3,0) -> 0 | E103: =D103+E104 -> 50 | F103: ='Excl URS 3 '!K110 -> 11.929274
A104: =A103+1 -> 11 | B104: ='Excl URS 3 '!B111 -> Anta LNG (NR) | C104: =VLOOKUP(B104,'rate sheet working'!$B$3:$C$158,2,0) -> 0 | D104: =VLOOKUP(B104,'rate sheet working'!$B$3:$D$158,3,0) -> 0 | E104: =D104+E105 -> 50 | F104: ='Excl URS 3 '!K111 -> 11.786985
A105: =A104+1 -> 12 | B105: ='Excl URS 3 '!B112 -> Dadri LNG (NR) | C105: =VLOOKUP(B105,'rate sheet working'!$B$3:$C$158,2,0) -> 0 | D105: =VLOOKUP(B105,'rate sheet working'!$B$3:$D$158,3,0) -> 0 | E105: =D105+E106 -> 50 | F105: ='Excl URS 3 '!K112 -> 11.361163
A106: =A105+1 -> 13 | B106: ='Excl URS 3 '!B113 -> KAWAS (LNG) | C106: =VLOOKUP(B106,'rate sheet working'!$B$3:$C$158,2,0) -> 0 | D106: =VLOOKUP(B106,'rate sheet working'!$B$3:$D$158,3,0) -> 0 | E106: =D106+E107 -> 50 | F106: ='Excl URS 3 '!K113 -> 10.020925
... A110: =A109+1 -> 17 | B110: ='Excl URS 3 '!B117 -> Torrent (Indigenous) | C110: =VLOOKUP(B110,'rate sheet working'!$B$3:$C$158,2,0) -> 1115.9438 | D110: =VLOOKUP(B110,'rate sheet working'!$B$3:$D$158,3,0) -> 50 | E110: =D110+E111 -> 50 | F110: ='Excl URS 3 '!K117 -> 7.6779452
B112: URS
A113: Sr. No. | B113: Name of Generating Stations | C113: Effective rate in Rs./kwh
A114: 1 | B114: ='URS 4'!B6 -> KAWAS (NAPM) | C114: ='URS 4'!M6 -> 38.133685
A115: =A114+1 -> 2 | B115: ='URS 4'!B7 -> GANDHAR (NAPM) | C115: ='URS 4'!M7 -> 32.138869
A116: =A115+1 -> 3 | B116: ='URS 4'!B8 -> KAWAS (Liquid) | C116: ='URS 4'!M8 -> 26.013995
A117: =A116+1 -> 4 | B117: ='URS 4'!B9 -> Dadri Liquid (NR) | C117: ='URS 4'!M9 -> 25.507636
A118: =A117+1 -> 5 | B118: ='URS 4'!B10 -> Auraiya Liquid (NR) | C118: ='URS 4'!M10 -> 20.188254
A119: =A118+1 -> 6 | B119: ='URS 4'!B11 -> Anta Liquid (NR) | C119: ='URS 4'!M11 -> 19.016177
A120: =A119+1 -> 7 | B120: ='URS 4'!B12 -> GANDHAR (LNG) | C120: ='URS 4'!M12 -> 14.695889
A121: =A120+1 -> 8 | B121: ='URS 4'!B13 -> Auraiya CLNG (NR) | C121: ='URS 4'!M13 -> 13.470321
A122: =A121+1 -> 9 | B122: ='URS 4'!B14 -> Dadri Comm LNG (NR) | C122: ='URS 4'!M14 -> 12.752876
A123: =A122+1 -> 10 | B123: ='URS 4'!B15 -> Auraiya LNG (NR) | C123: ='URS 4'!M15 -> 12.564274
A124: =A123+1 -> 11 | B124: ='URS 4'!B16 -> Anta LNG (NR) | C124: ='URS 4'!M16 -> 12.495985
A125: =A124+1 -> 12 | B125: ='URS 4'!B17 -> Dadri LNG (NR) | C125: ='URS 4'!M17 -> 11.89077
A126: =A125+1 -> 13 | B126: ='URS 4'!B18 -> KAWAS (LNG) | C126: ='URS 4'!M18 -> 10.880076
... A131: =A130+1 -> 18 | B131: ='URS 4'!B23 -> Solapur I | C131: ='URS 4'!M23 -> 6.2375045
A132: 19 | B132: ='URS 4'!B24 -> Gadarwara | C132: ='URS 4'!M24 -> 6.2158559
A133: =A134+1 -> 22 | B133: ='URS 4'!B25 -> Indira Gandhi STPS (Jhajjar) (NR) | C133: ='URS 4'!M25 -> 5.942716
A134: 21 | B134: ='URS 4'!B26 -> Khargone | C134: ='URS 4'!M26 -> 5.6628945
A135: 22 | B135: ='URS 4'!B27 -> Unchahar II (NR) | C135: ='URS 4'!M27 -> 5.56518
A136: =A135+1 -> 23 | B136: ='URS 4'!B28 -> Meja (NR) | C136: ='URS 4'!M28 -> 5.3526349
A137: =A136+1 -> 24 | B137: ='URS 4'!B29 -> Unchahar IV (NR) | C137: ='URS 4'!M29 -> 5.2087988
A138: =A137+1 -> 25 | B138: ='URS 4'!B30 -> Tanda II | C138: ='URS 4'!M30 -> 5.0483224
A139: 26 | B139: ='URS 4'!B31 -> Mauda-I | C139: ='URS 4'!M31 -> 5.0306755
A140: 27 | B140: ='URS 4'!B32 -> Mauda-II | C140: ='URS 4'!M32 -> 4.9134535
A141: =A140+1 -> 28 | B141: ='URS 4'!B33 -> Unchahar III (NR) | C141: ='URS 4'!M33 -> 4.8979636
A142: 29 | B142: ='URS 4'!B34 -> National Capital Thermal Power Station Dadri II (NR) | C142: ='URS 4'!M34 -> 4.7761958
A143: =A142+1 -> 30 | B143: ='URS 4'!B35 -> Unchahar I (NR) | C143: ='URS 4'!M35 -> 4.7451452
A144: =A143+1 -> 31 | B144: ='URS 4'!B36 -> VSTPS-IV | C144: ='URS 4'!M36 -> 3.9688673
A145: =A144+1 -> 32 | B145: ='URS 4'!B37 -> VSTPS-V | C145: ='URS 4'!M37 -> 3.8929622
A146: =A145+1 -> 33 | B146: ='URS 4'!B38 -> KAHALGAON-II | C146: ='URS 4'!M38 -> 3.8077891
A147: =A146+1 -> 34 | B147: ='URS 4'!B39 -> Lara | C147: ='URS 4'!M39 -> 3.7189263
A148: =A147+1 -> 35 | B148: ='URS 4'!B40 -> Khurja STPP | C148: ='URS 4'!M40 -> 3.501393
A149: =A148+1 -> 36 | B149: ='URS 4'!B41 -> VSTPS-I | C149: ='URS 4'!M41 -> 3.3813608
A150: =A149+1 -> 37 | B150: ='URS 4'!B42 -> VSTPS-III | C150: ='URS 4'!M42 -> 3.2536043
A151: =A150+1 -> 38 | B151: ='URS 4'!B43 -> GANDHAR (APM) | C151: ='URS 4'!M43 -> 3.2416101
A152: =A151+1 -> 39 | B152: ='URS 4'!B44 -> VSTPS-II | C152: ='URS 4'!M44 -> 3.154414
...

Sheet TOTAL MOD working incl Biomass
A1: Details of power purchase cost per unit for MOD on the basis of rates available from bills of Mar 2023
B2: Name of Generating Stations | C2: Energy Charges Rate for MOD Purpose Rs./kwh | D2: FCA Rs./kwh | E2: Effective Energy Charges (Rs./kwh) | F2: Transmission Losses beyond MP periphery (%) | G2: Variable cost incl. losses | H2: Cess on Intrastate sales | I2: ED & Cess on Auxiliary Consumption | J2: Trading Margin | K2: Transmission charges | L2: Sustenace allownace, Royalty, Clean energy cess etc. | M2: Normative fixed cost for URS | N2: Incentive p.u. | O2: Effective rate in Rs./kwh
G4: (Rs. per kwh)
A5: A | B5: B | C5: C | D5: D | E5: E=C+D | F5: F | G5: G=E/((100%-F)) | H5: H | I5: I | J5: J | K5: K | L5: L | M5: M | N5: N | O5: O=sum(G:N)
A6: 1 | B6: Arya Energy Limited (Biomass) | C6: 4.38 | E6: =C6+D6 -> 4.38 | G6: =E6/((100%-F6)) -> 4.38 | I6: =VLOOKUP(B6,'fixed cost'!$B$4:$R$116,17,0) -> 0 | O6: =SUM(G6:N6) -> 4.38
A7: =A6+1 -> 2 | B7: ATPS (210MW) Chachai | C7: 2.014 | D7: 0.002 | E7: =C7+D7 -> 2.016 | G7: =E7/((100%-F7)) -> 2.016 | I7: =VLOOKUP(B7,'fixed cost'!$B$4:$R$116,17,0) -> 0 | O7: =SUM(G7:N7) -> 2.016
A8: 2 | B8: ATPS (210MW) Chachai | C8: =C7 -> 2.014 | E8: =C8+D8 -> 2.014 | G8: =E8/((100%-F8)) -> 2.014 | I8: =VLOOKUP(B8,'fixed cost'!$B$4:$R$116,17,0) -> 0 | N8: 0.5 | O8: =SUM(G8:N8) -> 2.514
A9: 2 | B9: ATPS (210MW) Chachai | C9: =C8 -> 2.014 | E9: =C9+D9 -> 2.014 | G9: =E9/((100%-F9)) -> 2.014 | I9: =VLOOKUP(B9,'fixed cost'!$B$4:$R$116,17,0) -> 0 | N9: 0.65 | O9: =SUM(G9:N9) -> 2.664
A10: 3 | B10: Bansagar-I HPS | C10: 0.68 | E10: =C10+D10 -> 0.68 | G10: =E10/((100%-F10)) -> 0.68 | I10: =VLOOKUP(B10,'fixed cost'!$B$4:$R$116,17,0) -> 0 | O10: =SUM(G10:N10) -> 0.68
A11: =+A10+1 -> 4 | B11: Bansagar-II HPS | C11: 0.516 | E11: =C11+D11 -> 0.516 | G11: =E11/((100%-F11)) -> 0.516 | I11: =VLOOKUP(B11,'fixed cost'!$B$4:$R$116,17,0) -> 0 | O11: =SUM(G11:N11) -> 0.516
A12: =+A11+1 -> 5 | B12: Bansagar-III HPS | C12: 0.815 | E12: =C12+D12 -> 0.815 | G12: =E12/((100%-F12)) -> 0.815 | I12: =VLOOKUP(B12,'fixed cost'!$B$4:$R$116,17,0) -> 0 | O12: =SUM(G12:N12) -> 0.815
A13: =+A12+1 -> 6 | B13: Bargi HPS | C13: 0.183 | E13: =C13+D13 -> 0.183 | G13: =E13/((100%-F13)) -> 0.183 | I13: =VLOOKUP(B13,'fixed cost'!$B$4:$R$116,17,0) -> 0 | O13: =SUM(G13:N13) -> 0.183
A14: =+A13+1 -> 7 | B14: Birsinghpur HPS | C14: 0.606 | E14: =C14+D14 -> 0.606 | G14: =E14/((100%-F14)) -> 0.606 | I14: =VLOOKUP(B14,'fixed cost'!$B$4:$R$116,17,0) -> 0 | O14: =SUM(G14:N14) -> 0.606
A15: 8 | B15: BLA | C15: 4.105 | E15: =C15+D15 -> 4.105 | G15: =E15/((100%-F15)) -> 4.105 | H15: 0.15 | I15: =VLOOKUP(B15,'fixed cost'!$B$4:$R$116,17,0) -> 0.08001 | O15: =SUM(G15:N15) -> 4.33501
A16: 9 | B16: BLA II | C16: 4.037 | E16: =C16+D16 -> 4.037 | G16: =E16/((100%-F16)) -> 4.037 | H16: 0.15 | I16: =VLOOKUP(B16,'fixed cost'!$B$4:$R$116,17,0) -> 0.08001 | O16: =SUM(G16:N16) -> 4.26701
A17: 10 | B17: DVC (CTPS) (STOA LOI) | C17: 2.745 | E17: =C17+D17 -> 2.745 | F17: 0.0357 | G17: =E17/((100%-F17)) -> 2.8466245 | I17: =VLOOKUP(B17,'fixed cost'!$B$4:$R$116,17,0) -> 0 | K17: 0.024 | O17: =SUM(G17:N17) -> 2.8706245
A18: 11 | B18: DVC (DTPS) (STOA LOI) | C18: 3.582 | E18: =C18+D18 -> 3.582 | F18: =F17 -> 0.0357 | G18: =E18/((100%-F18)) -> 3.7146116 | I18: =VLOOKUP(B18,'fixed cost'!$B$4:$R$116,17,0) -> 0 | K18: 0 | O18: =SUM(G18:N18) -> 3.7146116
A19: 12 | B19: Mahan Energen Ltd. (5%) | C19: 2.675 | E19: =C19+D19 -> 2.675 | F19: =F18 -> 0.0357 | G19: =E19/((100%-F19)) -> 2.774033 | H19: 0.15 | I19: =VLOOKUP(B19,'fixed cost'!$B$4:$R$116,17,0) -> 0 | O19: =SUM(G19:N19) -> 2.924033
A20: 13 | B20: Gadarwara | C20: 4.023 | D20: -0.2 | E20: =C20+D20 -> 3.823 | F20: =F19 -> 0.0357 | G20: =E20/((100%-F20)) -> 3.9645339 | H20: 0.15 | I20: =VLOOKUP(B20,'fixed cost'!$B$4:$R$116,17,0) -> 0.058995 | O20: =SUM(G20:N20) -> 4.1735289
A21: =A20+1 -> 14 | B21: Gadarwara | C21: =C20 -> 4.023 | D21: =D20 -> -0.2 | E21: =C21+D21 -> 3.823 | F21: =F20 -> 0.0357 | G21: =E21/((100%-F21)) -> 3.9645339 | H21: =H20 -> 0.15 | I21: =VLOOKUP(B21,'fixed cost'!$B$4:$R$116,17,0) -> 0.058995 | M21: =VLOOKUP(B21,'fixed cost'!$B$4:$H$59,7,0) -> 2.0601461 | O21: =SUM(G21:N21) -> 6.233675
A22: =A21+1 -> 15 | B22: GANDHAR (APM) | C22: 1.595 | E22: =C22+D22 -> 1.595 | F22: =F21 -> 0.0357 | G22: =E22/((100%-F22)) -> 1.6540496 | I22: =VLOOKUP(B22,'fixed cost'!$B$4:$R$116,17,0) -> 0 | O22: =SUM(G22:N22) -> 1.6540496
A23: =A22+1 -> 16 | B23: GANDHAR (APM) | C23: =C22 -> 1.595 | D23: =D22 -> 0 | E23: =C23+D23 -> 1.595 | F23: =F22 -> 0.0357 | G23: =E23/((100%-F23)) -> 1.6540496 | I23: =VLOOKUP(B23,'fixed cost'!$B$4:$R$116,17,0) -> 0 | M23: =VLOOKUP(B23,'fixed cost'!$B$4:$H$59,7,0) -> 1.0465902 | O23: =SUM(G23:N23) -> 2.7006398
A24: =A23+1 -> 17 | B24: GANDHAR (CLNG) | C24: 7.898 | E24: =C24+D24 -> 7.898 | F24: =F23 -> 0.0357 | G24: =E24/((100%-F24)) -> 8.1903972 | I24: =VLOOKUP(B24,'fixed cost'!$B$4:$R$116,17,0) -> 0 | O24: =SUM(G24:N24) -> 8.1903972
A25: =A24+1 -> 18 | B25: GANDHAR (CLNG) | C25: =C24 -> 7.898 | D25: =D24 -> 0 | E25: =C25+D25 -> 7.898 | F25: =F24 -> 0.0357 | G25: =E25/((100%-F25)) -> 8.1903972 | I25: =VLOOKUP(B25,'fixed cost'!$B$4:$R$116,17,0) -> 0 | M25: =VLOOKUP(B25,'fixed cost'!$B$4:$H$59,7,0) -> 1.0465902 | O25: =SUM(G25:N25) -> 9.2369874
A26: =A25+1 -> 19 | B26: GANDHAR (LNG) | C26: 10.329 | E26: =C26+D26 -> 10.329 | F26: =F25 -> 0.0357 | G26: =E26/((100%-F26)) -> 10.711397 | I26: =VLOOKUP(B26,'fixed cost'!$B$4:$R$116,17,0) -> 0 | O26: =SUM(G26:N26) -> 10.711397
A27: =A26+1 -> 20 | B27: GANDHAR (LNG) | C27: =C26 -> 10.329 | D27: =D26 -> 0 | E27: =C27+D27 -> 10.329 | F27: =F26 -> 0.0357 | G27: =E27/((100%-F27)) -> 10.711397 | I27: =VLOOKUP(B27,'fixed cost'!$B$4:$R$116,17,0) -> 0 | M27: =VLOOKUP(B27,'fixed cost'!$B$4:$H$59,7,0) -> 1.0465902 | O27: =SUM(G27:N27) -> 11.757987
A28: =A27+1 -> 21 | B28: GANDHAR (NAPM) | C28: 29.718 | E28: =C28+D28 -> 29.718 | F28: =F27 -> 0.0357 | G28: =E28/((100%-F28)) -> 30.81821 | I28: =VLOOKUP(B28,'fixed cost'!$B$4:$R$116,17,0) -> 0 | O28: =SUM(G28:N28) -> 30.81821
A29: =A28+1 -> 22 | B29: GANDHAR (NAPM) | C29: =C28 -> 29.718 | D29: =D28 -> 0 | E29: =C29+D29 -> 29.718 | F29: =F28 -> 0.0357 | G29: =E29/((100%-F29)) -> 30.81821 | I29: =VLOOKUP(B29,'fixed cost'!$B$4:$R$116,17,0) -> 0 | M29: =VLOOKUP(B29,'fixed cost'!$B$4:$H$59,7,0) -> 1.0465902 | O29: =SUM(G29:N29) -> 31.8648
A30: =A29+1 -> 23 | B30: Gandhi Sagar HPS | C30: 0.209 | E30: =C30+D30 -> 0.209 | G30: =E30/((100%-F30)) -> 0.209 | I30: =VLOOKUP(B30,'fixed cost'!$B$4:$R$116,17,0) -> 0 | O30: =SUM(G30:N30) -> 0.209
A31: =A30+1 -> 24 | B31: ISP & OSP (25:11) | C31: =((1.983*25)+(2.351*11))/(25+11) -> 2.0954444 | E31: =C31+D31 -> 2.0954444 | G31: =E31/((100%-F31)) -> 2.0954444 | H31: 0.15 | I31: ='fixed cost'!R57 -> 0.00882 | O31: =SUM(G31:N31) -> 2.2542644
A32: =A31+1 -> 25 | B32: Jawahar Sagar (Inter state project) | C32: 1.51 | E32: =C32+D32 -> 1.51 | G32: =E32/((100%-F32)) -> 1.51 | I32: =VLOOKUP(B32,'fixed cost'!$B$4:$R$116,17,0) -> 0 | O32: =SUM(G32:N32) -> 1.51
A33: =A32+1 -> 26 | B33: Jhabua Power | C33: 2.851 | D33: 0.027 | E33: =C33+D33 -> 2.878 | F33: =F29 -> 0.0357 | G33: =E33/((100%-F33)) -> 2.9845484 | H33: 0.15 | O33: =SUM(G33:N33) -> 3.1345484
A34: =A33+1 -> 27 | B34: Jhinna HPS | C34: 0.608 | E34: =C34+D34 -> 0.608 | G34: =E34/((100%-F34)) -> 0.608 | I34: =VLOOKUP(B34,'fixed cost'!$B$4:$R$116,17,0) -> 0 | O34: =SUM(G34:N34) -> 0.608
A35: =A34+1 -> 28 | B35: JP Bina | C35: 3.526 | E35: =C35+D35 -> 3.526 | G35: =E35/((100%-F35)) -> 3.526 | H35: 0.15 | I35: =VLOOKUP(B35,'fixed cost'!$B$4:$R$116,17,0) -> 0.06477 | O35: =SUM(G35:N35) -> 3.74077
A36: =A35+1 -> 29 | B36: JP Nigrie | C36: 0.608 | E36: =C36+D36 -> 0.608 | F36: =F33 -> 0.0357 | G36: =E36/((100%-F36)) -> 0.63050918 | H36: 0.15 | I36: =VLOOKUP(B36,'fixed cost'!$B$4:$R$116,17,0) -> 0.040005 | O36: =SUM(G36:N36) -> 0.82051418
A37: =A36+1 -> 30 | B37: KAHALGAON-II | C37: 2.749 | D37: -0.068 | E37: =C37+D37 -> 2.681 | F37: =F36 -> 0.0357 | G37: =E37/((100%-F37)) -> 2.7802551 | I37: =VLOOKUP(B37,'fixed cost'!$B$4:$R$116,17,0) -> 0 | O37: =SUM(G37:N37) -> 2.7802551
A38: =A37+1 -> 31 | B38: KAHALGAON-II | C38: =C37 -> 2.749 | D38: =D37 -> -0.068 | E38: =C38+D38 -> 2.681 | F38: =F37 -> 0.0357 | G38: =E38/((100%-F38)) -> 2.7802551 | I38: =VLOOKUP(B38,'fixed cost'!$B$4:$R$116,17,0) -> 0 | M38: =VLOOKUP(B38,'fixed cost'!$B$4:$H$59,7,0) -> 0.92016616 | O38: =SUM(G38:N38) -> 3.7004213
A39: =A38+1 -> 32 | B39: KAWAS (APM) | C39: 1.597 | E39: =C39+D39 -> 1.597 | F39: =F38 -> 0.0357 | G39: =E39/((100%-F39)) -> 1.6561236 | I39: =VLOOKUP(B39,'fixed cost'!$B$4:$R$116,17,0) -> 0 | O39: =SUM(G39:N39) -> 1.6561236
A40: =A39+1 -> 33 | B40: KAWAS (APM) | C40: =C39 -> 1.597 | D40: =D39 -> 0 | E40: =C40+D40 -> 1.597 | F40: =F39 -> 0.0357 | G40: =E40/((100%-F40)) -> 1.6561236 | I40: =VLOOKUP(B40,'fixed cost'!$B$4:$R$116,17,0) -> 0 | M40: =VLOOKUP(B40,'fixed cost'!$B$4:$H$59,7,0) -> 0.85915096 | O40: =SUM(G40:N40) -> 2.5152746
A41: =A40+1 -> 34 | B41: KAWAS (CLNG) | C41: 8.735 | E41: =C41+D41 -> 8.735 | F41: =F40 -> 0.0357 | G41: =E41/((100%-F41)) -> 9.0583843 | I41: =VLOOKUP(B41,'fixed cost'!$B$4:$R$116,17,0) -> 0 | O41: =SUM(G41:N41) -> 9.0583843
A42: =A41+1 -> 35 | B42: KAWAS (CLNG) | C42: =C41 -> 8.735 | E42: =C42+D42 -> 8.735 | F42: =F41 -> 0.0357 | G42: =E42/((100%-F42)) -> 9.0583843 | I42: =VLOOKUP(B42,'fixed cost'!$B$4:$R$116,17,0) -> 0 | M42: =VLOOKUP(B42,'fixed cost'!$B$4:$H$59,7,0) -> 0.85915096 | O42: =SUM(G42:N42) -> 9.9175353
A43: =A42+1 -> 36 | B43: KAWAS (LNG) | C43: 10.339 | E43: =C43+D43 -> 10.339 | F43: =F42 -> 0.0357 | G43: =E43/((100%-F43)) -> 10.721767 | I43: =VLOOKUP(B43,'fixed cost'!$B$4:$R$116,17,0) -> 0 | O43: =SUM(G43:N43) -> 10.721767
A44: =A43+1 -> 37 | B44: KAWAS (LNG) | C44: =C43 -> 10.339 | D44: =D43 -> 0 | E44: =C44+D44 -> 10.339 | F44: =F43 -> 0.0357 | G44: =E44/((100%-F44)) -> 10.721767 | I44: =VLOOKUP(B44,'fixed cost'!$B$4:$R$116,17,0) -> 0 | M44: =VLOOKUP(B44,'fixed cost'!$B$4:$H$59,7,0) -> 0.85915096 | O44: =SUM(G44:N44) -> 11.580918
A45: =A44+1 -> 38 | B45: KAWAS (Liquid) | C45: 21.764 | E45: =C45+D45 -> 21.764 | F45: =F44 -> 0.0357 | G45: =E45/((100%-F45)) -> 22.56974 | I45: =VLOOKUP(B45,'fixed cost'!$B$4:$R$116,17,0) -> 0 | O45: =SUM(G45:N45) -> 22.56974
A46: =A45+1 -> 39 | B46: KAWAS (Liquid) | C46: =C45 -> 21.764 | D46: =D45 -> 0 | E46: =C46+D46 -> 21.764 | F46: =F45 -> 0.0357 | G46: =E46/((100%-F46)) -> 22.56974 | I46: =VLOOKUP(B46,'fixed cost'!$B$4:$R$116,17,0) -> 0 | M46: =M44 -> 0.85915096 | O46: =SUM(G46:N46) -> 23.428891
A47: =A44+1 -> 38 | B47: KAWAS (NAPM) | C47: 35.627 | E47: =C47+D47 -> 35.627 | F47: =F46 -> 0.0357 | G47: =E47/((100%-F47)) -> 36.945971 | I47: =VLOOKUP(B47,'fixed cost'!$B$4:$R$116,17,0) -> 0 | O47: =SUM(G47:N47) -> 36.945971
A48: =A47+1 -> 39 | B48: KAWAS (NAPM) | C48: =C47 -> 35.627 | D48: =D47 -> 0 | E48: =E47 -> 35.627 | F48: =F47 -> 0.0357 | G48: =E48/((100%-F48)) -> 36.945971 | I48: =VLOOKUP(B48,'fixed cost'!$B$4:$R$116,17,0) -> 0 | M48: =VLOOKUP(B48,'fixed cost'!$B$4:$H$59,7,0) -> 0.85915096 | O48: =SUM(G48:N48) -> 37.805122
A49: =A46+1 -> 40 | B49: Khargone | C49: 3.911 | E49: =C49+D49 -> 3.911 | F49: =F48 -> 0.0357 | G49: =E49/((100%-F49)) -> 4.0557918 | H49: 0.15 | I49: =VLOOKUP(B49,'fixed cost'!$B$4:$R$116,17,0) -> 0.052785 | O49: =SUM(G49:N49) -> 4.2585768
A50: =A49+1 -> 41 | B50: Khargone | C50: =C49 -> 3.911 | D50: =D49 -> 0 | E50: =C50+D50 -> 3.911 | F50: =F49 -> 0.0357 | G50: =E50/((100%-F50)) -> 4.0557918 | H50: =H49 -> 0.15 | I50: =VLOOKUP(B50,'fixed cost'!$B$4:$R$116,17,0) -> 0.052785 | M50: =VLOOKUP(B50,'fixed cost'!$B$4:$H$59,7,0) -> 2.0731461 | O50: =SUM(G50:N50) -> 6.3317229
A51: =A50+1 -> 42 | B51: KSTPS | C51: 1.504 | D51: 0.004 | E51: =C51+D51 -> 1.508 | F51: =F50 -> 0.0357 | G51: =E51/((100%-F51)) -> 1.5638287 | I51: =VLOOKUP(B51,'fixed cost'!$B$4:$R$116,17,0) -> 0.13208364 | O51: =SUM(G51:N51) -> 1.6959123
A52: =A51+1 -> 43 | B52: KSTPS | C52: =C51 -> 1.504 | D52: =D51 -> 0.004 | E52: =C52+D52 -> 1.508 | F52: =F51 -> 0.0357 | G52: =E52/((100%-F52)) -> 1.5638287 | I52: =VLOOKUP(B52,'fixed cost'!$B$4:$R$116,17,0) -> 0.13208364 | M52: =VLOOKUP(B52,'fixed cost'!$B$4:$H$59,7,0) -> 0.75506732 | O52: =SUM(G52:N52) -> 2.4509796
A53: =A52+1 -> 44 | B53: =B52 -> KSTPS | C53: =C52 -> 1.504 | D53: =D52 -> 0.004 | E53: =C53+D53 -> 1.508 | F53: =F52 -> 0.0357 | G53: =E53/((100%-F53)) -> 1.5638287 | I53: =VLOOKUP(B53,'fixed cost'!$B$4:$R$116,17,0) -> 0.13208364 | N53: 0.5 | O53: =SUM(G53:N53) -> 2.1959123
A54: =A53+1 -> 45 | B54: =B53 -> KSTPS | C54: =C53 -> 1.504 | D54: =D53 -> 0.004 | E54: =C54+D54 -> 1.508 | F54: =F53 -> 0.0357 | G54: =E54/((100%-F54)) -> 1.5638287 | I54: =VLOOKUP(B54,'fixed cost'!$B$4:$R$116,17,0) -> 0.13208364 | N54: 0.65 | O54: =SUM(G54:N54) -> 2.3459123
A55: =A53+1 -> 45 | B55: KSTPS-III | C55: 1.477 | D55: 0.00299 | E55: =C55+D55 -> 1.47999 | F55: =F54 -> 0.0357 | G55: =E55/((100%-F55)) -> 1.5347817 | I55: =VLOOKUP(B55,'fixed cost'!$B$4:$R$116,17,0) -> 0.11369475 | O55: =SUM(G55:N55) -> 1.6484765
A56: =A55+1 -> 46 | B56: KSTPS-III | C56: =C55 -> 1.477 | D56: =D55 -> 0.00299 | E56: =C56+D56 -> 1.47999 | F56: =F55 -> 0.0357 | G56: =E56/((100%-F56)) -> 1.5347817 | I56: =VLOOKUP(B56,'fixed cost'!$B$4:$R$116,17,0) -> 0.11369475 | M56: =VLOOKUP(B56,'fixed cost'!$B$4:$H$59,7,0) -> 1.1259324 | O56: =SUM(G56:N56) -> 2.7744088
A57: =A56+1 -> 47 | B57: =B56 -> KSTPS-III | C57: =C56 -> 1.477 | D57: =D56 -> 0.00299 | E57: =C57+D57 -> 1.47999 | F57: =F56 -> 0.0357 | G57: =E57/((100%-F57)) -> 1.5347817 | I57: =VLOOKUP(B57,'fixed cost'!$B$4:$R$116,17,0) -> 0.11369475 | N57: 0.5 | O57: =SUM(G57:N57) -> 2.1484765
A58: =A57+1 -> 48 | B58: =B57 -> KSTPS-III | C58: =C57 -> 1.477 | D58: =D57 -> 0.00299 | E58: =C58+D58 -> 1.47999 | F58: =F57 -> 0.0357 | G58: =E58/((100%-F58)) -> 1.5347817 | I58: =VLOOKUP(B58,'fixed cost'!$B$4:$R$116,17,0) -> 0.11369475 | N58: 0.65 | O58: =SUM(G58:N58) -> 2.2984765
A59: =A57+1 -> 48 | B59: Lanco Amarkantak (FSA) | C59: 1.865 | D59: -0.003 | E59: =C59+D59 -> 1.862 | F59: =F58 -> 0.0357 | G59: =E59/((100%-F59)) -> 1.9309344 | I59: =VLOOKUP(B59,'fixed cost'!$B$4:$R$116,17,0) -> #N/A | J59: 0.05 | O59: =SUM(G59:N59) -> #N/A
A60: =A58+1 -> 49 | B60: Lanco Amarkantak (Non - FSA) | C60: 11.531 | E60: =C60+D60 -> 11.531 | F60: =F59 -> 0.0357 | G60: =E60/((100%-F60)) -> 11.957897 | I60: =VLOOKUP(B60,'fixed cost'!$B$4:$R$116,17,0) -> #N/A | J60: 0.05 | O60: =SUM(G60:N60) -> #N/A
A61: =A59+1 -> 49 | B61: Lanco Amarkantak (Imported Coal) | C61: 15.63 | E61: =C61+D61 -> 15.63 | F61: =F60 -> 0.0357 | G61: =E61/((100%-F61)) -> 16.208649 | I61: =I60 -> #N/A | J61: 0.05 | O61: =SUM(G61:N61) -> #N/A
A62: =A59+1 -> 49 | B62: Lara | C62: 1.288 | E62: =C62+D62 -> 1.288 | F62: =F59 -> 0.0357 | G62: =E62/((100%-F62)) -> 1.3356839 | I62: =VLOOKUP(B62,'fixed cost'!$B$4:$R$116,17,0) -> 0.11369475 | O62: =SUM(G62:N62) -> 1.4493787
A63: =A62+1 -> 50 | B63: Lara | C63: =C62 -> 1.288 | D63: =D62 -> 0 | E63: =C63+D63 -> 1.288 | F63: =F62 -> 0.0357 | G63: =E63/((100%-F63)) -> 1.3356839 | I63: =VLOOKUP(B63,'fixed cost'!$B$4:$R$116,17,0) -> 0.11369475 | M63: =VLOOKUP(B63,'fixed cost'!$B$4:$H$59,7,0) -> 2.2835364 | O63: =SUM(G63:N63) -> 3.7329151
A64: =A63+1 -> 51 | B64: Madikhera HPS | C64: 1.293 | E64: =C64+D64 -> 1.293 | G64: =E64/((100%-F64)) -> 1.293 | I64: =VLOOKUP(B64,'fixed cost'!$B$4:$R$116,17,0) -> 0 | O64: =SUM(G64:N64) -> 1.293
A65: =A64+1 -> 52 | B65: Mauda-I | C65: 3.86 | E65: =C65+D65 -> 3.86 | F65: =F63 -> 0.0357 | G65: =E65/((100%-F65)) -> 4.0029037 | I65: =VLOOKUP(B65,'fixed cost'!$B$4:$R$116,17,0) -> 0 | O65: =SUM(G65:N65) -> 4.0029037
A66: =A65+1 -> 53 | B66: Mauda-I | C66: =C65 -> 3.86 | D66: =D65 -> 0 | E66: =C66+D66 -> 3.86 | F66: =F65 -> 0.0357 | G66: =E66/((100%-F66)) -> 4.0029037 | I66: =VLOOKUP(B66,'fixed cost'!$B$4:$R$116,17,0) -> 0 | M66: =VLOOKUP(B66,'fixed cost'!$B$4:$H$62,7,0) -> 1.6931572 | O66: =SUM(G66:N66) -> 5.6960609
A67: =A66+1 -> 54 | B67: Mauda-II | C67: 3.815 | E67: =C67+D67 -> 3.815 | F67: =F66 -> 0.0357 | G67: =E67/((100%-F67)) -> 3.9562377 | I67: =VLOOKUP(B67,'fixed cost'!$B$4:$R$116,17,0) -> 0 | O67: =SUM(G67:N67) -> 3.9562377
A68: =A67+1 -> 55 | B68: Mauda-II | C68: =C67 -> 3.815 | D68: =D67 -> 0 | E68: =C68+D68 -> 3.815 | F68: =F67 -> 0.0357 | G68: =E68/((100%-F68)) -> 3.9562377 | I68: =VLOOKUP(B68,'fixed cost'!$B$4:$R$116,17,0) -> 0 | M68: =VLOOKUP(B68,'fixed cost'!$B$4:$H$62,7,0) -> 1.5812064 | O68: =SUM(G68:N68) -> 5.5374441
A69: =A68+1 -> 56 | B69: MB Power | C69: 2.445 | E69: =C69+D69 -> 2.445 | F69: =F68 -> 0.0357 | G69: =E69/((100%-F69)) -> 2.535518 | H69: 0.15 | I69: =VLOOKUP(B69,'fixed cost'!$B$4:$R$116,17,0) -> 0.047625 | O69: =SUM(G69:N69) -> 2.733143
A70: =A69+1 -> 57 | B70: Orient Green Power (Biomass) | C70: 4.38 | E70: =C70+D70 -> 4.38 | G70: =E70/((100%-F70)) -> 4.38 | I70: =VLOOKUP(B70,'fixed cost'!$B$4:$R$116,17,0) -> 0 | O70: =SUM(G70:N70) -> 4.38
A71: =A70+1 -> 58 | B71: Pench HPS | C71: 0.519 | E71: =C71+D71 -> 0.519 | G71: =E71/((100%-F71)) -> 0.519 | I71: =VLOOKUP(B71,'fixed cost'!$B$4:$R$116,17,0) -> 0 | O71: =SUM(G71:N71) -> 0.519
A72: =A71+1 -> 59 | B72: R P sagar (Inter state project) | C72: 1.51 | E72: =C72+D72 -> 1.51 | G72: =E72/((100%-F72)) -> 1.51 | I72: =VLOOKUP(B72,'fixed cost'!$B$4:$R$116,17,0) -> 0 | O72: =SUM(G72:N72) -> 1.51
A73: =A72+1 -> 60 | B73: Rajghat HPS | C73: 1.252 | E73: =C73+D73 -> 1.252 | G73: =E73/((100%-F73)) -> 1.252 | I73: =VLOOKUP(B73,'fixed cost'!$B$4:$R$116,17,0) -> 0 | O73: =SUM(G73:N73) -> 1.252
A74: =A73+1 -> 61 | B74: Sasan | C74: 1.1494 | E74: =C74+D74 -> 1.1494 | F74: =F69 -> 0.0357 | G74: =E74/((100%-F74)) -> 1.1919527 | H74: 0.15 | I74: =VLOOKUP(B74,'fixed cost'!$B$4:$R$116,17,0) -> 0.038347439 | L74: 0.165 | O74: =SUM(G74:N74) -> 1.5453002
A75: =A74+1 -> 62 | B75: Sasan | C75: =C74 -> 1.1494 | D75: =D74 -> 0 | E75: =C75+D75 -> 1.1494 | F75: =F74 -> 0.0357 | G75: =E75/((100%-F75)) -> 1.1919527 | H75: 0.15 | I75: =VLOOKUP(B75,'fixed cost'!$B$4:$R$116,17,0) -> 0.038347439 | L75: =L74 -> 0.165 | M75: 0.1674 | O75: =SUM(G75:N75) -> 1.7127002
A76: =A75+1 -> 63 | B76: SGTPS -1x500 | C76: 2.82 | D76: -0.001 | E76: =C76+D76 -> 2.819 | G76: =E76/((100%-F76)) -> 2.819 | I76: =VLOOKUP(B76,'fixed cost'!$B$4:$R$116,17,0) -> 0 | O76: =SUM(G76:N76) -> 2.819
A77: =A76+1 -> 64 | B77: SGTPS -1x500 | C77: =C76 -> 2.82 | E77: =C77+D77 -> 2.82 | G77: =E77/((100%-F77)) -> 2.82 | I77: =VLOOKUP(B77,'fixed cost'!$B$4:$R$116,17,0) -> 0 | N77: 0.5 | O77: =SUM(G77:N77) -> 3.32
A78: =A77+1 -> 65 | B78: SGTPS -1x500 | C78: =C77 -> 2.82 | E78: =C78+D78 -> 2.82 | G78: =E78/((100%-F78)) -> 2.82 | I78: =VLOOKUP(B78,'fixed cost'!$B$4:$R$116,17,0) -> 0 | N78: 0.65 | O78: =SUM(G78:N78) -> 3.47
A79: =A77+1 -> 65 | B79: SGTPS -4x210 | C79: 2.998 | D79: 0.002 | E79: =C79+D79 -> 3 | G79: =E79/((100%-F79)) -> 3 | I79: =VLOOKUP(B79,'fixed cost'!$B$4:$R$116,17,0) -> 0 | O79: =SUM(G79:N79) -> 3
A80: =A79+1 -> 66 | B80: SIPAT I | C80: 1.536 | E80: =C80+D80 -> 1.536 | F80: =F75 -> 0.0357 | G80: =E80/((100%-F80)) -> 1.5928653 | I80: =VLOOKUP(B80,'fixed cost'!$B$4:$R$116,17,0) -> 0.11823725 | O80: =SUM(G80:N80) -> 1.7111025
A81: =A80+1 -> 67 | B81: SIPAT I | C81: =C80 -> 1.536 | D81: =D80 -> 0 | E81: =C81+D81 -> 1.536 | F81: =F80 -> 0.0357 | G81: =E81/((100%-F81)) -> 1.5928653 | I81: =VLOOKUP(B81,'fixed cost'!$B$4:$R$116,17,0) -> 0.11823725 | M81: =VLOOKUP(B81,'fixed cost'!$B$4:$H$59,7,0) -> 1.2557147 | O81: =SUM(G81:N81) -> 2.9668172
A82: =A81+1 -> 68 | B82: =B81 -> SIPAT I | C82: =C81 -> 1.536 | D82: =D81 -> 0 | E82: =C82+D82 -> 1.536 | F82: =F81 -> 0.0357 | G82: =E82/((100%-F82)) -> 1.5928653 | I82: =VLOOKUP(B82,'fixed cost'!$B$4:$R$116,17,0) -> 0.11823725 | N82: 0.5 | O82: =SUM(G82:N82) -> 2.2111025
A83: =A82+1 -> 69 | B83: =B82 -> SIPAT I | C83: =C82 -> 1.536 | D83: =D82 -> 0 | E83: =C83+D83 -> 1.536 | F83: =F82 -> 0.0357 | G83: =E83/((100%-F83)) -> 1.5928653 | I83: =VLOOKUP(B83,'fixed cost'!$B$4:$R$116,17,0) -> 0.11823725 | N83: 0.65 | O83: =SUM(G83:N83) -> 2.3611025
A84: =A82+1 -> 69 | B84: SIPAT II | C84: 1.586 | E84: =C84+D84 -> 1.586 | F84: =F83 -> 0.0357 | G84: =E84/((100%-F84)) -> 1.6447164 | I84: =VLOOKUP(B84,'fixed cost'!$B$4:$R$116,17,0) -> 0.11823725 | O84: =SUM(G84:N84) -> 1.7629536
A85: =A84+1 -> 70 | B85: SIPAT II | C85: =C84 -> 1.586 | D85: =D84 -> 0 | E85: =C85+D85 -> 1.586 | F85: =F84 -> 0.0357 | G85: =E85/((100%-F85)) -> 1.6447164 | I85: =VLOOKUP(B85,'fixed cost'!$B$4:$R$116,17,0) -> 0.11823725 | M85: =VLOOKUP(B85,'fixed cost'!$B$4:$H$59,7,0) -> 0.98415242 | O85: =SUM(G85:N85) -> 2.747106
A86: =A85+1 -> 71 | B86: =B85 -> SIPAT II | C86: =C85 -> 1.586 | D86: =D85 -> 0 | E86: =C86+D86 -> 1.586 | F86: =F85 -> 0.0357 | G86: =E86/((100%-F86)) -> 1.6447164 | I86: =VLOOKUP(B86,'fixed cost'!$B$4:$R$116,17,0) -> 0.11823725 | N86: 0.5 | O86: =SUM(G86:N86) -> 2.2629536
A87: =A86+1 -> 72 | B87: =B86 -> SIPAT II | C87: =C86 -> 1.586 | D87: =D86 -> 0 | E87: =C87+D87 -> 1.586 | F87: =F86 -> 0.0357 | G87: =E87/((100%-F87)) -> 1.6447164 | I87: =VLOOKUP(B87,'fixed cost'!$B$4:$R$116,17,0) -> 0.11823725 | N87: 0.65 | O87: =SUM(G87:N87) -> 2.4129536
A88: =A86+1 -> 72 | B88: Solapur I | C88: 4.584 | D88: 0.12799 | E88: =C88+D88 -> 4.71199 | F88: =F87 -> 0.0357 | G88: =E88/((100%-F88)) -> 4.8864358 | I88: =VLOOKUP(B88,'fixed cost'!$B$4:$R$116,17,0) -> 0 | O88: =SUM(G88:N88) -> 4.8864358
A89: =A88+1 -> 73 | B89: Solapur I | C89: =C88 -> 4.584 | D89: =D88 -> 0.12799 | E89: =C89+D89 -> 4.71199 | F89: =F88 -> 0.0357 | G89: =E89/((100%-F89)) -> 4.8864358 | I89: =VLOOKUP(B89,'fixed cost'!$B$4:$R$116,17,0) -> 0 | M89: =VLOOKUP(B89,'fixed cost'!$B$4:$H$59,7,0) -> 1.9962859 | O89: =SUM(G89:N89) -> 6.8827216
A90: =A89+1 -> 74 | B90: SSP | C90: 0.82 | E90: =C90+D90 -> 0.82 | F90: =F89 -> 0.0357 | G90: =E90/((100%-F90)) -> 0.85035777 | I90: =VLOOKUP(B90,'fixed cost'!$B$4:$R$116,17,0) -> 0 | O90: =SUM(G90:N90) -> 0.85035777
A91: =A90+1 -> 75 | B91: SSTPS Khandwa (Singaji) | C91: 3.311 | D91: -0.017 | E91: =C91+D91 -> 3.294 | G91: =E91/((100%-F91)) -> 3.294 | I91: =VLOOKUP(B91,'fixed cost'!$B$4:$R$116,17,0) -> 0 | O91: =SUM(G91:N91) -> 3.294
A92: =A91+1 -> 76 | B92: SSTPS Khandwa (Singaji) # 3 & 4 | C92: 3.025 | D92: -0.003 | E92: =C92+D92 -> 3.022 | G92: =E92/((100%-F92)) -> 3.022 | I92: =VLOOKUP(B92,'fixed cost'!$B$4:$R$116,17,0) -> 0 | O92: =SUM(G92:N92) -> 3.022
A93: =A92+1 -> 77 | B93: STPS Sarni | C93: 3.95 | D93: 0.026 | E93: =C93+D93 -> 3.976 | G93: =E93/((100%-F93)) -> 3.976 | I93: =VLOOKUP(B93,'fixed cost'!$B$4:$R$116,17,0) -> 0 | O93: =SUM(G93:N93) -> 3.976
A94: =A93+1 -> 78 | B94: STPS Sarni 10 & 11 | C94: 2.88 | D94: 0.01 | E94: =C94+D94 -> 2.89 | G94: =E94/((100%-F94)) -> 2.89 | I94: =VLOOKUP(B94,'fixed cost'!$B$4:$R$116,17,0) -> 0 | O94: =SUM(G94:N94) -> 2.89
A95: =A94+1 -> 79 | B95: STPS Sarni 10 & 11 | C95: =C94 -> 2.88 | D95: =D94 -> 0.01 | E95: =C95+D95 -> 2.89 | G95: =E95/((100%-F95)) -> 2.89 | I95: =VLOOKUP(B95,'fixed cost'!$B$4:$R$116,17,0) -> 0 | N95: 0.5 | O95: =SUM(G95:N95) -> 3.39
A96: =A95+1 -> 80 | B96: STPS Sarni 10 & 11 | C96: =C95 -> 2.88 | D96: =D95 -> 0.01 | E96: =C96+D96 -> 2.89 | G96: =E96/((100%-F96)) -> 2.89 | I96: =VLOOKUP(B96,'fixed cost'!$B$4:$R$116,17,0) -> 0 | N96: 0.65 | O96: =SUM(G96:N96) -> 3.54
A97: =A95+1 -> 80 | B97: Torrent (Indigenous) | C97: 9.85 | E97: =C97+D97 -> 9.85 | F97: =F90 -> 0.0357 | G97: =E97/((100%-F97)) -> 10.214663 | I97: =VLOOKUP(B97,'fixed cost'!$B$4:$R$116,17,0) -> 0 | J97: 0.05 | O97: =SUM(G97:N97) -> 10.264663
A98: =A97+1 -> 81 | B98: VSTPS-I | C98: 1.686 | D98: -0.0159 | E98: =C98+D98 -> 1.6701 | F98: =F97 -> 0.0357 | G98: =E98/((100%-F98)) -> 1.7319299 | H98: 0.15 | I98: =VLOOKUP(B98,'fixed cost'!$B$4:$R$116,17,0) -> 0.091908 | O98: =SUM(G98:N98) -> 1.9738379
A99: =A98+1 -> 82 | B99: VSTPS-I | C99: =C98 -> 1.686 | D99: =D98 -> -0.0159 | E99: =C99+D99 -> 1.6701 | F99: =F98 -> 0.0357 | G99: =E99/((100%-F99)) -> 1.7319299 | H99: 0.15 | I99: =VLOOKUP(B99,'fixed cost'!$B$4:$R$116,17,0) -> 0.091908 | M99: =VLOOKUP(B99,'fixed cost'!$B$4:$H$59,7,0) -> 0.9173352 | O99: =SUM(G99:N99) -> 2.8911731
A100: =A99+1 -> 83 | B100: VSTPS-I | C100: =C99 -> 1.686 | D100: =D99 -> -0.0159 | E100: =C100+D100 -> 1.6701 | F100: =F99 -> 0.0357 | G100: =E100/((100%-F100)) -> 1.7319299 | H100: 0.15 | I100: =VLOOKUP(B100,'fixed cost'!$B$4:$R$116,17,0) -> 0.091908 | N100: 0.5 | O100: =SUM(G100:N100) -> 2.4738379
A101: 84 | B101: VSTPS-I | C101: =C100 -> 1.686 | D101: =D100 -> -0.0159 | E101: =E100 -> 1.6701 | F101: =F100 -> 0.0357 | G101: =G100 -> 1.7319299 | H101: =H100 -> 0.15 | I101: =I100 -> 0.091908 | N101: 0.65 | O101: =SUM(G101:N101) -> 2.6238379
...

Sheet Excl URS incl biomass
A1: Details of power purchase cost per unit of Thermal and Gas Power stations for MOD for the month of Mar 2023
A2: Sr. No. | B2: Name of Generating Stations | C2: Energy Charges Rate for MOD Purpose Rs./kwh | D2: FCA Rs./kwh | E2: Effective Energy Charges (Rs./kwh) | F2: Transmission Losses beyond MP Periphery | G2: Variable cost incl. losses | H2: Cess on Intrastate sales | I2: ED & Cess on Auxiliary Consumption | J2: Trading Margin | K2: Transmission charges | L2: Sustenace allownace, Royalty, Clean energy cess etc. | M2: Incentive p.u. | N2: Effective rate in Rs./kwh
G4: (Rs. per kwh)
A5: A | B5: B | C5: C | D5: D | E5: E=C+D | F5: F | G5: G=E/(100%-F) | H5: H | I5: I | J5: J | K5: K | L5: L | M5: M | N5: N=sum(H:L)
A6: 1 | B6: ATPS (210MW) Chachai | C6: 2.014 | D6: 0.002 | E6: =C6+D6 -> 2.016 | G6: =E6/((100%-F6)) -> 2.016 | I6: 0 | N6: =SUM(G6:M6) -> 2.016 | O6: 3.849 | P6: =N6-O6 -> -1.833 | Q6: =N6-N7 -> -2.31901 | R6: =N6-N7 -> -2.31901 | S6: =N6-N7 -> -2.31901 | T6: 3.914 | U6: =N6-T6 -> -1.898 | V6: 1.657 | W6: =N6-V6 -> 0.359 | X6: 2.016 | Y6: =N6-X6 -> 0
A7: =+A6+1 -> 2 | B7: BLA | C7: 4.105 | E7: =C7+D7 -> 4.105 | G7: =E7/((100%-F7)) -> 4.105 | H7: 0.15 | I7: 0.08001 | N7: =SUM(G7:M7) -> 4.33501 | O7: 3.415474 | P7: =N7-O7 -> 0.91953598 | Q7: =N7-#REF! -> #REF! | R7: =N7-#REF! -> #REF! | S7: =N7-#REF! -> #REF! | T7: 3.849 | U7: =N7-T7 -> 0.48601 | V7: 4.21901 | W7: =N7-V7 -> 0.116 | X7: 4.33501 | Y7: =N7-X7 -> 0
A8: =+A7+1 -> 3 | B8: DVC (DTPS) (STOA LOI) | C8: 3.582 | E8: =C8+D8 -> 3.582 | F8: 0.0357 | G8: =E8/((100%-F8)) -> 3.7146116 | I8: 0 | K8: 0 | N8: =SUM(G8:M8) -> 3.7146116 | O8: 2.9165641 | P8: =N8-O8 -> 0.79804757 | Q8: =N8-N9 -> 0.79057866 | R8: =N8-N9 -> 0.79057866 | S8: =N8-N9 -> 0.79057866 | T8: 2.8281883 | U8: =N8-T8 -> 0.8864233 | V8: 4.09701 | W8: =N8-V8 -> -0.38239836 | X8: 3.7146116 | Y8: =N8-X8 -> 0
A9: =+A8+1 -> 4 | B9: Mahan Energen Ltd. (5%) | C9: 2.675 | E9: =C9+D9 -> 2.675 | F9: 0.0357 | G9: =E9/((100%-F9)) -> 2.774033 | H9: 0.15 | I9: 0 | N9: =SUM(G9:M9) -> 2.924033 | O9: 2.872606 | P9: =N9-O9 -> 0.051426942 | Q9: =N9-N10 -> -1.2538759 | R9: =N9-N10 -> -1.2538759 | S9: =N9-N10 -> -1.2538759 | T9: 1.9803711 | U9: =N9-T9 -> 0.94366191 | V9: 4.4699081 | W9: =N9-V9 -> -1.5458751 | X9: 2.924033 | Y9: =N9-X9 -> 0
A10: =+A9+1 -> 5 | B10: Gadarwara | C10: 4.023 | D10: -0.2 | E10: =C10+D10 -> 3.823 | F10: 0.0357 | G10: =E10/((100%-F10)) -> 3.9645339 | H10: 0.15 | I10: 0.063375 | N10: =SUM(G10:M10) -> 4.1779089 | O10: 2.7761089 | P10: =N10-O10 -> 1.4018 | Q10: =N10-N11 -> 2.5238593 | R10: =N10-N11 -> 2.5238593 | S10: =N10-N11 -> 2.5238593 | T10: 2.6892371 | U10: =N10-T10 -> 1.4886718 | V10: 2.6781305 | W10: =N10-V10 -> 1.4997784 | X10: 4.1779089 | Y10: =N10-X10 -> 0
A11: =+A10+1 -> 6 | B11: GANDHAR (APM) | C11: 1.595 | E11: =C11+D11 -> 1.595 | F11: 0.0357 | G11: =E11/((100%-F11)) -> 1.6540496 | I11: 0 | N11: =SUM(G11:M11) -> 1.6540496 | O11: 3.31 | P11: =N11-O11 -> -1.6559504 | Q11: =N11-N12 -> -1.4804988 | R11: =N11-N12 -> -1.4804988 | S11: =N11-N12 -> -1.4804988 | T11: 1.6656273 | U11: =N11-T11 -> -0.011577704 | V11: 5.000485 | W11: =N11-V11 -> -3.3464354 | X11: 1.6540496 | Y11: =N11-X11 -> 0
A12: =+A11+1 -> 7 | B12: Jhabua Power | C12: 2.851 | D12: 0.027 | E12: =C12+D12 -> 2.878 | F12: 0.0357 | G12: =E12/((100%-F12)) -> 2.9845484 | H12: 0.15 | N12: =SUM(G12:M12) -> 3.1345484 | O12: 0.65704658 | P12: =N12-O12 -> 2.4775018 | Q12: =N12-N13 -> -0.60622162 | R12: =N12-N13 -> -0.60622162 | S12: =N12-N13 -> -0.60622162 | T12: 2.5527492 | U12: =N12-T12 -> 0.58179918 | V12: 2.9233935 | W12: =N12-V12 -> 0.21115492 | X12: 3.1345484 | Y12: =N12-X12 -> 0
A13: =+A12+1 -> 8 | B13: JP Bina | C13: 3.526 | E13: =C13+D13 -> 3.526 | G13: =E13/((100%-F13)) -> 3.526 | H13: 0.15 | I13: 0.06477 | N13: =SUM(G13:M13) -> 3.74077 | O13: 2.1547486 | P13: =N13-O13 -> 1.5860214 | Q13: =N13-N14 -> 2.9202558 | R13: =N13-N14 -> 2.9202558 | S13: =N13-N14 -> 2.9202558 | T13: 1.6698888 | U13: =N13-T13 -> 2.0708812 | V13: 3.85077 | W13: =N13-V13 -> -0.11 | X13: 3.74077 | Y13: =N13-X13 -> 0
A14: =+A13+1 -> 9 | B14: JP Nigrie | C14: 0.608 | E14: =C14+D14 -> 0.608 | F14: 0.0357 | G14: =E14/((100%-F14)) -> 0.63050918 | H14: 0.15 | I14: 0.040005 | N14: =SUM(G14:M14) -> 0.82051418 | O14: 2.872606 | P14: =N14-O14 -> -2.0520919 | Q14: =N14-N15 -> -1.9597409 | R14: =N14-N15 -> -1.9597409 | S14: =N14-N15 -> -1.9597409 | T14: 2.6954734 | U14: =N14-T14 -> -1.8749593 | V14: 0.80423025 | W14: =N14-V14 -> 0.016283927 | X14: 0.82051418 | Y14: =N14-X14 -> 0
A15: =+A14+1 -> 10 | B15: KAHALGAON-II | C15: 2.749 | D15: -0.068 | E15: =C15+D15 -> 2.681 | F15: 0.0357 | G15: =E15/((100%-F15)) -> 2.7802551 | I15: 0 | N15: =SUM(G15:M15) -> 2.7802551 | O15: 2.9216755 | P15: =N15-O15 -> -0.14142036 | Q15: =N15-N16 -> 1.1241315 | R15: =N15-N16 -> 1.1241315 | S15: =N15-N16 -> 1.1241315 | T15: 3.372 | U15: =N15-T15 -> -0.59174489 | V15: 4.0528543 | W15: =N15-V15 -> -1.2725992 | X15: 2.7802551 | Y15: =N15-X15 -> 0
A16: =+A15+1 -> 11 | B16: KAWAS (APM) | C16: 1.597 | E16: =C16+D16 -> 1.597 | F16: 0.0357 | G16: =E16/((100%-F16)) -> 1.6561236 | I16: 0 | N16: =SUM(G16:M16) -> 1.6561236 | O16: 1.5871379 | P16: =N16-O16 -> 0.068985688 | Q16: =N16-N17 -> -2.6055432 | R16: =N16-N17 -> -2.6055432 | S16: =N16-N17 -> -2.6055432 | T16: 0.70503586 | U16: =N16-T16 -> 0.95108775 | V16: 1.650989 | W16: =N16-V16 -> 0.005134607 | X16: 1.6561236 | Y16: =N16-X16 -> 0
A17: =+A16+1 -> 12 | B17: Khargone | C17: 3.911 | E17: =C17+D17 -> 3.911 | F17: 0.0357 | G17: =E17/((100%-F17)) -> 4.0557918 | H17: 0.15 | I17: 0.055875 | N17: =SUM(G17:M17) -> 4.2616668 | O17: 1.5590809 | P17: =N17-O17 -> 2.7025859 | Q17: =N17-N18 -> 2.5661056 | R17: =N17-N18 -> 2.5661056 | S17: =N17-N18 -> 2.5661056 | T17: 2.1505041 | U17: =N17-T17 -> 2.1111627 | V17: 1.6072498 | W17: =N17-V17 -> 2.654417 | X17: 4.2616668 | Y17: =N17-X17 -> 0
A18: =+A17+1 -> 13 | B18: KSTPS | C18: 1.504 | D18: 0.004 | E18: =C18+D18 -> 1.508 | F18: 0.0357 | G18: =E18/((100%-F18)) -> 1.5638287 | I18: 0.13173248 | N18: =SUM(G18:M18) -> 1.6955612 | O18: 2.0296503 | P18: =N18-O18 -> -0.33408915 | Q18: =N18-N19 -> 0.043829457 | R18: =N18-N19 -> 0.043829457 | S18: =N18-N19 -> 0.043829457 | T18: 1.5863216 | U18: =N18-T18 -> 0.10923958 | V18: 2.3703257 | W18: =N18-V18 -> -0.67476455 | X18: 1.6955612 | Y18: =N18-X18 -> 0
A19: =+A18+1 -> 14 | B19: KSTPS-III | C19: 1.477 | D19: 0.00299 | E19: =C19+D19 -> 1.47999 | F19: 0.0357 | G19: =E19/((100%-F19)) -> 1.5347817 | I19: 0.11695 | N19: =SUM(G19:M19) -> 1.6517317 | O19: 2.4071804 | P19: =N19-O19 -> -0.75544872 | Q19: =N19-N20 -> -0.38257265 | R19: =N19-N20 -> -0.38257265 | S19: =N19-N20 -> -0.38257265 | T19: 2.6057582 | U19: =N19-T19 -> -0.95402653 | V19: 3.9901661 | W19: =N19-V19 -> -2.3384344 | X19: 1.6517317 | Y19: =N19-X19 -> 0
A20: =+A19+1 -> 15 | B20: Lanco Amarkantak (FSA) | C20: 1.865 | D20: -0.003 | E20: =C20+D20 -> 1.862 | F20: 0.0357 | G20: =E20/((100%-F20)) -> 1.9309344 | I20: 0.05337 | J20: 0.05 | N20: =SUM(G20:M20) -> 2.0343044 | O20: 3.4208333 | P20: =N20-O20 -> -1.3865289 | Q20: =N20-N21 -> 0.58167044 | R20: =N20-N21 -> 0.58167044 | S20: =N20-N21 -> 0.58167044 | T20: 1.6800748 | U20: =N20-T20 -> 0.35422952 | V20: 3.3451423 | W20: =N20-V20 -> -1.3108379 | X20: 2.0343044 | Y20: =N20-X20 -> 0
A21: =+A20+1 -> 16 | B21: Lara | C21: 1.288 | E21: =C21+D21 -> 1.288 | F21: 0.0357 | G21: =E21/((100%-F21)) -> 1.3356839 | I21: 0.11695 | N21: =SUM(G21:M21) -> 1.4526339 | O21: 3.4980879 | P21: =N21-O21 -> -2.045454 | Q21: =N21-N22 -> -2.5502697 | R21: =N21-N22 -> -2.5502697 | S21: =N21-N22 -> -2.5502697 | T21: 2.8181218 | U21: =N21-T21 -> -1.3654879 | V21: 1.5394732 | W21: =N21-V21 -> -0.086839259 | X21: 1.4526339 | Y21: =N21-X21 -> 0
A22: =+A21+1 -> 17 | B22: Mauda-I | C22: 3.86 | E22: =C22+D22 -> 3.86 | F22: 0.0357 | G22: =E22/((100%-F22)) -> 4.0029037 | I22: 0 | N22: =SUM(G22:M22) -> 4.0029037 | O22: 2.5944007 | P22: =N22-O22 -> 1.408503 | Q22: =N22-N23 -> 0.046665975 | R22: =N22-N23 -> 0.046665975 | S22: =N22-N23 -> 0.046665975 | T22: 1.5424592 | U22: =N22-T22 -> 2.4604445 | V22: 2.052 | W22: =N22-V22 -> 1.9509037 | X22: 4.0029037 | Y22: =N22-X22 -> 0
A23: =+A22+1 -> 18 | B23: Mauda-II | C23: 3.815 | E23: =C23+D23 -> 3.815 | F23: 0.0357 | G23: =E23/((100%-F23)) -> 3.9562377 | I23: 0 | N23: =SUM(G23:M23) -> 3.9562377 | O23: 2.5933627 | P23: =N23-O23 -> 1.362875 | Q23: =N23-N24 -> 1.2230947 | R23: =N23-N24 -> 1.2230947 | S23: =N23-N24 -> 1.2230947 | T23: 1.5112774 | U23: =N23-T23 -> 2.4449603 | V23: 2.601 | W23: =N23-V23 -> 1.3552377 | X23: 3.9562377 | Y23: =N23-X23 -> 0
A24: =+A23+1 -> 19 | B24: MB Power | C24: 2.445 | E24: =C24+D24 -> 2.445 | F24: 0.0357 | G24: =E24/((100%-F24)) -> 2.535518 | H24: 0.15 | I24: 0.047625 | N24: =SUM(G24:M24) -> 2.733143 | O24: 1.5003771 | P24: =N24-O24 -> 1.2327659 | Q24: =N24-N25 -> 1.1878428 | R24: =N24-N25 -> 1.1878428 | S24: =N24-N25 -> 1.1878428 | T24: 1.8335984 | U24: =N24-T24 -> 0.89954461 | V24: 3.2283224 | W24: =N24-V24 -> -0.49517937 | X24: 2.733143 | Y24: =N24-X24 -> 0
A25: =+A24+1 -> 20 | B25: Sasan | C25: 1.1494 | E25: =C25+D25 -> 1.1494 | F25: 0.0357 | G25: =E25/((100%-F25)) -> 1.1919527 | H25: 0.15 | I25: 0.038347439 | L25: 0.165 | N25: =SUM(G25:M25) -> 1.5453002 | O25: 1.907 | P25: =N25-O25 -> -0.36169985 | Q25: =N25-#REF! -> #REF! | R25: =N25-#REF! -> #REF! | S25: =N25-#REF! -> #REF! | T25: 2.1025881 | U25: =N25-T25 -> -0.55728794 | V25: 3.4801031 | W25: =N25-V25 -> -1.9348029 | X25: 1.5453002 | Y25: =N25-X25 -> 0
A26: =+A25+1 -> 21 | B26: SGTPS -1x500 | C26: 2.82 | D26: -0.001 | E26: =C26+D26 -> 2.819 | G26: =E26/((100%-F26)) -> 2.819 | I26: 0 | N26: =SUM(G26:M26) -> 2.819 | O26: 1.6171688 | P26: =N26-O26 -> 1.2018312 | Q26: =N26-N27 -> -0.181 | R26: =N26-N27 -> -0.181 | S26: =N26-N27 -> -0.181 | T26: 3.0703669 | U26: =N26-T26 -> -0.25136691 | V26: 3.465 | W26: =N26-V26 -> -0.646 | X26: 2.819 | Y26: =N26-X26 -> 0
A27: =+A26+1 -> 22 | B27: SGTPS -4x210 | C27: 2.998 | D27: 0.002 | E27: =C27+D27 -> 3 | G27: =E27/((100%-F27)) -> 3 | I27: 0 | N27: =SUM(G27:M27) -> 3 | O27: 1.6656119 | P27: =N27-O27 -> 1.3343881 | Q27: =N27-N28 -> 1.283041 | R27: =N27-N28 -> 1.283041 | S27: =N27-N28 -> 1.283041 | T27: 2.6528583 | U27: =N27-T27 -> 0.34714167 | V27: 3.115 | W27: =N27-V27 -> -0.115 | X27: 3 | Y27: =N27-X27 -> 0
A28: =+A27+1 -> 23 | B28: SIPAT I | C28: 1.536 | E28: =C28+D28 -> 1.536 | F28: 0.0357 | G28: =E28/((100%-F28)) -> 1.5928653 | I28: 0.12409375 | N28: =SUM(G28:M28) -> 1.716959 | O28: 3.3988187 | P28: =N28-O28 -> -1.6818596 | Q28: =N28-N29 -> -0.051851084 | R28: =N28-N29 -> -0.051851084 | S28: =N28-N29 -> -0.051851084 | T28: 2.6570159 | U28: =N28-T28 -> -0.94005686 | V28: 2.981 | W28: =N28-V28 -> -1.264041 | X28: 1.716959 | Y28: =N28-X28 -> 0
A29: =+A28+1 -> 24 | B29: SIPAT II | C29: 1.586 | E29: =C29+D29 -> 1.586 | F29: 0.0357 | G29: =E29/((100%-F29)) -> 1.6447164 | I29: 0.12409375 | N29: =SUM(G29:M29) -> 1.7688101 | O29: 2.839 | P29: =N29-O29 -> -1.0701899 | Q29: =N29-N30 -> -3.1176256 | R29: =N29-N30 -> -3.1176256 | S29: =N29-N30 -> -3.1176256 | T29: 4.38 | U29: =N29-T29 -> -2.6111899 | V29: 2.423 | W29: =N29-V29 -> -0.65418988 | X29: 1.7688101 | Y29: =N29-X29 -> 0
A30: =+A29+1 -> 25 | B30: Solapur I | C30: 4.584 | D30: 0.12799 | E30: =C30+D30 -> 4.71199 | F30: 0.0357 | G30: =E30/((100%-F30)) -> 4.8864358 | I30: 0 | N30: =SUM(G30:M30) -> 4.8864358 | O30: 2.681 | P30: =N30-O30 -> 2.2054358 | Q30: =N30-N31 -> 1.5924358 | R30: =N30-N31 -> 1.5924358 | S30: =N30-N31 -> 1.5924358 | T30: 1.5141564 | U30: =N30-T30 -> 3.3722793 | V30: 1.8737889 | W30: =N30-V30 -> 3.0126469 | X30: 4.8864358 | Y30: =N30-X30 -> 0
A31: =+A30+1 -> 26 | B31: SSTPS Khandwa (Singaji) | C31: 3.311 | D31: -0.017 | E31: =C31+D31 -> 3.294 | G31: =E31/((100%-F31)) -> 3.294 | I31: 0 | N31: =SUM(G31:M31) -> 3.294 | O31: 2.781 | P31: =N31-O31 -> 0.513 | Q31: =N31-N32 -> 0.272 | R31: =N31-N32 -> 0.272 | S31: =N31-N32 -> 0.272 | T31: 1.998 | U31: =N31-T31 -> 1.296 | V31: 1.7904668 | W31: =N31-V31 -> 1.5035332 | X31: 3.294 | Y31: =N31-X31 -> 0
A32: =+A31+1 -> 27 | B32: SSTPS Khandwa (Singaji) # 3 & 4 | C32: 3.025 | D32: -0.003 | E32: =C32+D32 -> 3.022 | G32: =E32/((100%-F32)) -> 3.022 | I32: 0 | N32: =SUM(G32:M32) -> 3.022 | O32: 2.332 | P32: =N32-O32 -> 0.69 | Q32: =N32-N33 -> -0.954 | R32: =N32-N33 -> -0.954 | S32: =N32-N33 -> -0.954 | T32: 2.368 | U32: =N32-T32 -> 0.654 | V32: 1.7731048 | W32: =N32-V32 -> 1.2488952 | X32: 3.022 | Y32: =N32-X32 -> 0
A33: =+A32+1 -> 28 | B33: STPS Sarni | C33: 3.95 | D33: 0.026 | E33: =C33+D33 -> 3.976 | G33: =E33/((100%-F33)) -> 3.976 | I33: 0 | N33: =SUM(G33:M33) -> 3.976 | O33: 2.0943216 | P33: =N33-O33 -> 1.8816784 | Q33: =N33-N34 -> 1.086 | R33: =N33-N34 -> 1.086 | S33: =N33-N34 -> 1.086 | T33: 1.5486956 | U33: =N33-T33 -> 2.4273044 | V33: 1.7534908 | W33: =N33-V33 -> 2.2225092 | X33: 3.976 | Y33: =N33-X33 -> 0
A34: =+A33+1 -> 29 | B34: STPS Sarni 10 & 11 | C34: 2.88 | D34: 0.01 | E34: =C34+D34 -> 2.89 | G34: =E34/((100%-F34)) -> 2.89 | I34: 0 | N34: =SUM(G34:M34) -> 2.89 | O34: 2.0259908 | P34: =N34-O34 -> 0.86400918 | Q34: =N34-N35 -> 0.9172421 | R34: =N34-N35 -> 0.9172421 | S34: =N34-N35 -> 0.9172421 | T34: 1.5964972 | U34: =N34-T34 -> 1.2935028 | V34: 1.8088725 | W34: =N34-V34 -> 1.0811275 | X34: 2.89 | Y34: =N34-X34 -> 0
A35: =+A34+1 -> 30 | B35: VSTPS-I | C35: 1.686 | D35: -0.0159 | E35: =C35+D35 -> 1.6701 | F35: 0.0357 | G35: =E35/((100%-F35)) -> 1.7319299 | H35: 0.15 | I35: 0.090828 | N35: =SUM(G35:M35) -> 1.9727579 | O35: 2.0094258 | P35: =N35-O35 -> -0.036667878 | Q35: =N35-N36 -> 0.082937722 | R35: =N35-N36 -> 0.082937722 | S35: =N35-N36 -> 0.082937722 | T35: 3.0620518 | U35: =N35-T35 -> -1.0892939 | V35: 2.0703685 | W35: =N35-V35 -> -0.097610638 | X35: 1.9727579 | Y35: =N35-X35 -> 0
A36: =+A35+1 -> 31 | B36: VSTPS-II | C36: 1.624 | D36: -0.0149 | E36: =C36+D36 -> 1.6091 | F36: 0.0357 | G36: =E36/((100%-F36)) -> 1.6686716 | H36: 0.15 | I36: 0.0711486 | N36: =SUM(G36:M36) -> 1.8898202 | O36: 1.9866488 | P36: =N36-O36 -> -0.09682867 | Q36: =N36-N37 -> 0.023732627 | R36: =N36-N37 -> 0.023732627 | S36: =N36-N37 -> 0.023732627 | T36: 2.855 | U36: =N36-T36 -> -0.96517982 | V36: 2.1523692 | W36: =N36-V36 -> -0.26254898 | X36: 1.8898202 | Y36: =N36-X36 -> 0
A37: =+A36+1 -> 32 | B37: VSTPS-III | C37: 1.61 | D37: -0.016 | E37: =C37+D37 -> 1.594 | F37: 0.0357 | G37: =E37/((100%-F37)) -> 1.6530125 | H37: 0.15 | I37: 0.063075 | N37: =SUM(G37:M37) -> 1.8660875 | O37: 2.0425559 | P37: =N37-O37 -> -0.17646831 | Q37: =N37-N38 -> 0.01959971 | R37: =N37-N38 -> 0.01959971 | S37: =N37-N38 -> 0.01959971 | T37: 2.71 | U37: =N37-T37 -> -0.84391245 | V37: 2.1492722 | W37: =N37-V37 -> -0.28318467 | X37: 1.8660875 | Y37: =N37-X37 -> 0
A38: =+A37+1 -> 33 | B38: VSTPS-IV | C38: 1.59 | D38: -0.0149 | E38: =C38+D38 -> 1.5751 | F38: 0.0357 | G38: =E38/((100%-F38)) -> 1.6334128 | H38: 0.15 | I38: 0.063075 | N38: =SUM(G38:M38) -> 1.8464878 | O38: 3.6159989 | P38: =N38-O38 -> -1.7695111 | Q38: =N38-N39 -> -0.067128192 | R38: =N38-N39 -> -0.067128192 | S38: =N38-N39 -> -0.067128192 | T38: 3.297 | U38: =N38-T38 -> -1.4505122 | V38: 3.5490864 | W38: =N38-V38 -> -1.7025986 | X38: 1.8464878 | Y38: =N38-X38 -> 0
A39: =+A38+1 -> 34 | B39: VSTPS-V | C39: 1.646 | D39: -0.0159 | E39: =C39+D39 -> 1.6301 | F39: 0.0357 | G39: =E39/((100%-F39)) -> 1.690449 | H39: 0.15 | I39: 0.073167 | N39: =SUM(G39:M39) -> 1.913616 | O39: 3.7038663 | P39: =N39-O39 -> -1.7902502 | Q39: =N39-N40 -> -0.16561243 | R39: =N39-N40 -> -0.16561243 | S39: =N39-N40 -> -0.16561243 | T39: 2.588 | U39: =N39-T39 -> -0.67438397 | V39: 1.6238257 | W39: =N39-V39 -> 0.28979028 | X39: 1.913616 | Y39: =N39-X39 -> 0
A40: =+A39+1 -> 35 | B40: Anta APM (NR) | C40: 2.005 | E40: =C40+D40 -> 2.005 | F40: 0.0357 | G40: =E40/((100%-F40)) -> 2.0792285 | I40: 0 | N40: =SUM(G40:M40) -> 2.0792285 | O40: 3.5840426 | P40: =N40-O40 -> -1.5048141 | Q40: =N40-N41 -> -0.082961734 | R40: =N40-N41 -> -0.082961734 | S40: =N40-N41 -> -0.082961734 | T40: 2.1061376 | U40: =N40-T40 -> -0.02690916 | V40: 1.6062765 | W40: =N40-V40 -> 0.472952 | X40: 2.0792285 | Y40: =N40-X40 -> 0
A41: =+A40+1 -> 36 | B41: Auraiya APM (NR) | C41: 2.085 | E41: =C41+D41 -> 2.085 | F41: 0.0357 | G41: =E41/((100%-F41)) -> 2.1621902 | I41: 0 | N41: =SUM(G41:M41) -> 2.1621902 | O41: 3.7238268 | P41: =N41-O41 -> -1.5616366 | Q41: =N41-N42 -> 0.036295759 | R41: =N41-N42 -> 0.036295759 | S41: =N41-N42 -> 0.036295759 | T41: 2.0333697 | U41: =N41-T41 -> 0.12882048 | V41: 1.5856302 | W41: =N41-V41 -> 0.57655996 | X41: 2.1621902 | Y41: =N41-X41 -> 0
A42: =+A41+1 -> 37 | B42: Dadri APM (NR) | C42: 2.05 | E42: =C42+D42 -> 2.05 | F42: 0.0357 | G42: =E42/((100%-F42)) -> 2.1258944 | I42: 0 | N42: =SUM(G42:M42) -> 2.1258944 | O42: 0 | P42: =N42-O42 -> 2.1258944 | Q42: =N42-N44 -> -0.74976667 | R42: =N42-N43 -> -2.5614435 | S42: =N42-N43 -> -2.5614435 | T42: 2.0228822 | U42: =N42-T42 -> 0.10301219 | V42: 1.5206978 | W42: =N42-V42 -> 0.60519659 | X42: 2.1258944 | Y42: =N42-X42 -> 0
A43: =+A42+1 -> 38 | B43: Indira Gandhi STPS (Jhajjar) (NR) | C43: 4.52 | E43: =C43+D43 -> 4.52 | F43: 0.0357 | G43: =E43/((100%-F43)) -> 4.687338 | I43: 0 | N43: =SUM(G43:M43) -> 4.687338 | R43: =N43-N44 -> 1.8116769 | S43: =N43-N44 -> 1.8116769 | T43: 1.9928334 | U43: =N43-T43 -> 2.6945046 | V43: 4.7698176 | W43: =N43-V43 -> -0.082479594 | X43: 4.687338 | Y43: =N43-X43 -> 0
A44: =+A43+1 -> 39 | B44: Meja (NR) | C44: 2.773 | E44: =C44+D44 -> 2.773 | F44: 0.0357 | G44: =E44/((100%-F44)) -> 2.8756611 | I44: 0 | N44: =SUM(G44:M44) -> 2.8756611 | O44: 4.1641135 | P44: =N44-O44 -> -1.2884524 | Q44: =N44-N43 -> -1.8116769 | R44: =N44-N45 -> 1.2319817 | S44: =N44-N45 -> 1.2319817 | T44: 2.014671 | U44: =N44-T44 -> 0.86099007 | V44: 5.3731806 | W44: =N44-V44 -> -2.4975194 | X44: 2.8756611 | Y44: =N44-X44 -> 0
A45: =+A44+1 -> 40 | B45: Rihand I (NR) | C45: 1.585 | E45: =C45+D45 -> 1.585 | F45: 0.0357 | G45: =E45/((100%-F45)) -> 1.6436794 | I45: 0 | N45: =SUM(G45:M45) -> 1.6436794 | O45: 1.3621614 | P45: =N45-O45 -> 0.28151799 | Q45: =N45-N46 -> 0.0041480867 | R45: =N45-N46 -> 0.0041480867 | S45: =N45-N46 -> 0.0041480867 | T45: 2.0902193 | U45: =N45-T45 -> -0.44653996 | V45: 5.4196346 | W45: =N45-V45 -> -3.7759552 | X45: 1.6436794 | Y45: =N45-X45 -> 0
A46: =+A45+1 -> 41 | B46: Rihand II (NR) | C46: 1.581 | E46: =C46+D46 -> 1.581 | F46: 0.0357 | G46: =E46/((100%-F46)) -> 1.6395313 | I46: 0 | N46: =SUM(G46:M46) -> 1.6395313 | O46: 1.345537 | P46: =N46-O46 -> 0.2939943 | Q46: =N46-N51 -> -2.2140413 | R46: =N46-N51 -> -2.2140413 | S46: =N46-N51 -> -2.2140413 | T46: 2.1619374 | U46: =N46-T46 -> -0.52240616 | V46: 5.3731806 | W46: =N46-V46 -> -3.7336493 | X46: 1.6395313 | Y46: =N46-X46 -> 0
A47: =+A46+1 -> 42 | B47: Rihand III (NR) | C47: 1.561 | E47: =C47+D47 -> 1.561 | F47: 0.0357 | G47: =E47/((100%-F47)) -> 1.6187908 | I47: 0 | N47: =SUM(G47:M47) -> 1.6187908 | X47: 1.6187908 | Y47: =N47-X47 -> 0
A48: =+A47+1 -> 43 | B48: Singrauli (NR) | C48: 1.512 | E48: =C48+D48 -> 1.512 | F48: 0.0357 | G48: =E48/((100%-F48)) -> 1.5679768 | I48: 0 | N48: =SUM(G48:M48) -> 1.5679768 | X48: 1.5679768 | Y48: =N48-X48 -> 0
A49: =+A48+1 -> 44 | B49: Tanda II | C49: 3.444 | E49: =C49+D49 -> 3.444 | F49: 0.0357 | G49: =E49/((100%-F49)) -> 3.5715026 | I49: 0 | K49: 0.2465 | N49: =SUM(G49:M49) -> 3.8180026 | X49: 3.8180026 | Y49: =N49-X49 -> 0
A50: =+A49+1 -> 45 | B50: Unchahar I (NR) | C50: 4.211 | E50: =C50+D50 -> 4.211 | F50: 0.0357 | G50: =E50/((100%-F50)) -> 4.3668983 | I50: 0 | N50: =SUM(G50:M50) -> 4.3668983 | X50: 4.3668983 | Y50: =N50-X50 -> 0
A51: =+A50+1 -> 46 | B51: Unchahar II (NR) | C51: 3.716 | E51: =C51+D51 -> 3.716 | F51: 0.0357 | G51: =E51/((100%-F51)) -> 3.8535725 | I51: 0 | N51: =SUM(G51:M51) -> 3.8535725 | O51: 1.3995663 | P51: =N51-O51 -> 2.4540063 | Q51: =N51-#REF! -> #REF! | R51: =N51-#REF! -> #REF! | S51: =N51-#REF! -> #REF! | T51: 3.4985968 | U51: =N51-T51 -> 0.35497572 | V51: 5.0645195 | W51: =N51-V51 -> -1.2109469 | X51: 3.8535725 | Y51: =N51-X51 -> 0
A52: =+A51+1 -> 47 | B52: Unchahar III (NR) | C52: 4.16 | E52: =C52+D52 -> 4.16 | F52: 0.0357 | G52: =E52/((100%-F52)) -> 4.3140102 | I52: 0 | N52: =SUM(G52:M52) -> 4.3140102 | X52: 4.3140102 | Y52: =N52-X52 -> 0
A53: =+A52+1 -> 48 | B53: Unchahar IV (NR) | C53: 3.991 | E53: =C53+D53 -> 3.991 | F53: 0.0357 | G53: =E53/((100%-F53)) -> 4.1387535 | I53: 0 | N53: =SUM(G53:M53) -> 4.1387535 | X53: 4.1387535 | Y53: =N53-X53 -> 0
A54: =+A53+1 -> 49 | B54: National Capital Thermal Power Station Dadri II (NR) | C54: 5.476 | E54: =C54+D54 -> 5.476 | F54: 0.0357 | G54: =E54/((100%-F54)) -> 5.6787307 | I54: 0 | N54: =SUM(G54:M54) -> 5.6787307

Sheet Comparison
A3: Details showing comparison of efective rates including and excluding Biomass at MP periphery for the month of March 2026
A4: Sr. No. | B4: Name of Generating Stations | C4: Variable rate at MP periphery in Rs./kwh (excl biomass) | D4: Variable rate at MP periphery in Rs./kwh (incl biomass) | E4: Difference (Rs. / kwh) | F4: % Change
A5: 1 | B5: Anta APM (NR) | C5: =VLOOKUP(B5,'Excl URS 3 '!$B$6:$N$61,13,FALSE) -> 2.0977192 | D5: 2.0977192 | E5: =D5-C5 -> 0 | F5: =E5/C5 -> 0
A6: =A5+1 -> 2 | B6: ATPS (210MW) Chachai | C6: =VLOOKUP(B6,'Excl URS 3 '!$B$6:$N$61,13,FALSE) -> 1.829 | D6: 1.829 | E6: =D6-C6 -> 0 | F6: =E6/C6 -> 0
A7: =A6+1 -> 3 | B7: Auraiya APM (NR) | C7: =VLOOKUP(B7,'Excl URS 3 '!$B$6:$N$61,13,FALSE) -> 2.1814187 | D7: 2.1814187 | E7: =D7-C7 -> 0 | F7: =E7/C7 -> 0
A8: =A7+1 -> 4 | B8: BLA | C8: =VLOOKUP(B8,'Excl URS 3 '!$B$6:$N$61,13,FALSE) -> 3.98201 | D8: 3.98201 | E8: =D8-C8 -> 0 | F8: =E8/C8 -> 0
A9: =A8+1 -> 5 | B9: Dadri APM (NR) | C9: =VLOOKUP(B9,'Excl URS 3 '!$B$6:$N$61,13,FALSE) -> 2.1448002 | D9: 2.1448002 | E9: =D9-C9 -> 0 | F9: =E9/C9 -> 0
A10: =A9+1 -> 6 | B10: DVC (DTPS) (STOA LOI) | C10: =VLOOKUP(B10,'Excl URS 3 '!$B$6:$N$61,13,FALSE) -> 3.4702929 | D10: 3.4702929 | E10: =D10-C10 -> 0 | F10: =E10/C10 -> 0
A11: =A10+1 -> 7 | B11: Gadarwara | C11: =VLOOKUP(B11,'Excl URS 3 '!$B$6:$N$61,13,FALSE) -> 4.1557098 | D11: 4.244 | E11: =D11-C11 -> 0.088290206 | F11: =E11/C11 -> 0.021245518
A12: =A11+1 -> 8 | B12: GANDHAR (APM) | C12: =VLOOKUP(B12,'Excl URS 3 '!$B$6:$N$61,13,FALSE) -> 2.1950199 | D12: 2.1950199 | E12: =D12-C12 -> 0 | F12: =E12/C12 -> 0
A13: =A12+1 -> 9 | B13: Ghatampur Thermal Power Station (NUPPL) | C13: =VLOOKUP(B13,'Excl URS 3 '!$B$6:$N$61,13,FALSE) -> 3.5697845 | D13: 3.5697845 | E13: =D13-C13 -> 0 | F13: =E13/C13 -> 0
A14: =A13+1 -> 10 | B14: Indira Gandhi STPS (Jhajjar) (NR) | C14: =VLOOKUP(B14,'Excl URS 3 '!$B$6:$N$61,13,FALSE) -> 4.447716 | D14: 4.567 | E14: =D14-C14 -> 0.11928395 | F14: =E14/C14 -> 0.026819147
A15: =A14+1 -> 11 | B15: Jhabua Power | C15: =VLOOKUP(B15,'Excl URS 3 '!$B$6:$N$61,13,FALSE) -> 2.866154 | D15: 2.866154 | E15: =D15-C15 -> 0 | F15: =E15/C15 -> 0
A16: =A15+1 -> 12 | B16: Jindal India Thermal Power (Medium Term) | C16: =VLOOKUP(B16,'Excl URS 3 '!$B$6:$N$61,13,FALSE) -> 2.5476041 | D16: 2.5476041 | E16: =D16-C16 -> 0 | F16: =E16/C16 -> 0
A17: =A16+1 -> 13 | B17: Jindal Power Limited (Medium Term) | C17: =VLOOKUP(B17,'Excl URS 3 '!$B$6:$N$61,13,FALSE) -> 2.7850262 | D17: 2.7850262 | E17: =D17-C17 -> 0 | F17: =E17/C17 -> 0
... A60: =A59+1 -> 56 | B60: VSTPS-V | C60: =VLOOKUP(B60,'Excl URS 3 '!$B$6:$N$61,13,FALSE) -> 2.3626348 | D60: 2.387 | E60: =D60-C60 -> 0.024365165 | F60: =E60/C60 -> 0.010312709

Sheet TOTAL MOD working (2)
A1: Details of power purchase cost per unit for MOD on the basis of rates available from bills of July 2022
B2: Name of Generating Stations | C2: Energy Charges Rate for MOD Purpose Rs./kwh | D2: FCA Rs./kwh | E2: Effective Energy Charges (Rs./kwh) | F2: Transmission Losses beyond MP periphery (%) | G2: Variable cost incl. losses | H2: Cess on Intrastate sales | I2: ED & Cess on Auxiliary Consumption | J2: Trading Margin | K2: Transmission charges | L2: Sustenace allownace, Royalty, Clean energy cess etc. | M2: Normative fixed cost for URS | N2: Incentive p.u. | O2: Effective rate in Rs./kwh | Q2: Energy Charges Rate for June 2022
G4: (Rs. per kwh)
A5: A | B5: B | C5: C | D5: D | E5: E=C+D | F5: F | G5: G=E/((100%-F)) | H5: H | I5: I | J5: J | K5: K | L5: L | M5: M | N5: N | O5: O=sum(G:N) | Q5: C | R5: Difference | S5: % difference
A6: 1 | B6: Arya Energy Limited (Biomass) | C6: 4.38 | E6: =C6+D6 -> 4.38 | G6: =E6/((100%-F6)) -> 4.38 | I6: =VLOOKUP(B6,'fixed cost'!$B$4:$R$116,17,0) -> 0 | O6: =SUM(G6:N6) -> 4.38 | Q6: 4.38 | R6: =C6-Q6 -> 0 | S6: =R6/Q6 -> 0
A7: =A6+1 -> 2 | B7: ATPS (210MW) Chachai | C7: 1.852 | E7: =C7+D7 -> 1.852 | G7: =E7/((100%-F7)) -> 1.852 | I7: =VLOOKUP(B7,'fixed cost'!$B$4:$R$116,17,0) -> 0 | O7: =SUM(G7:N7) -> 1.852 | Q7: 1.579 | R7: =C7-Q7 -> 0.273 | S7: =R7/Q7 -> 0.17289424
A8: 2 | B8: ATPS (210MW) Chachai | C8: =C7 -> 1.852 | E8: =C8+D8 -> 1.852 | G8: =E8/((100%-F8)) -> 1.852 | I8: =VLOOKUP(B8,'fixed cost'!$B$4:$R$116,17,0) -> 0 | N8: 0.5 | O8: =SUM(G8:N8) -> 2.352 | Q8: 1.579 | R8: =C8-Q8 -> 0.273 | S8: =R8/Q8 -> 0.17289424
A9: 2 | B9: ATPS (210MW) Chachai | C9: =C8 -> 1.852 | E9: =C9+D9 -> 1.852 | G9: =E9/((100%-F9)) -> 1.852 | I9: =VLOOKUP(B9,'fixed cost'!$B$4:$R$116,17,0) -> 0 | N9: 0.65 | O9: =SUM(G9:N9) -> 2.502 | Q9: 1.579 | R9: =C9-Q9 -> 0.273 | S9: =R9/Q9 -> 0.17289424
A10: 3 | B10: Bansagar-I HPS | C10: 0.672 | E10: =C10+D10 -> 0.672 | G10: =E10/((100%-F10)) -> 0.672 | I10: =VLOOKUP(B10,'fixed cost'!$B$4:$R$116,17,0) -> 0 | O10: =SUM(G10:N10) -> 0.672 | Q10: 0.672 | R10: =C10-Q10 -> 0 | S10: =R10/Q10 -> 0
A11: =+A10+1 -> 4 | B11: Bansagar-II HPS | C11: 0.51 | E11: =C11+D11 -> 0.51 | G11: =E11/((100%-F11)) -> 0.51 | I11: =VLOOKUP(B11,'fixed cost'!$B$4:$R$116,17,0) -> 0 | O11: =SUM(G11:N11) -> 0.51 | Q11: 0.51 | R11: =C11-Q11 -> 0 | S11: =R11/Q11 -> 0
A12: =+A11+1 -> 5 | B12: Bansagar-III HPS | C12: 0.806 | E12: =C12+D12 -> 0.806 | G12: =E12/((100%-F12)) -> 0.806 | I12: =VLOOKUP(B12,'fixed cost'!$B$4:$R$116,17,0) -> 0 | O12: =SUM(G12:N12) -> 0.806 | Q12: 0.806 | R12: =C12-Q12 -> 0 | S12: =R12/Q12 -> 0
A13: =+A12+1 -> 6 | B13: Bargi HPS | C13: 0.179 | E13: =C13+D13 -> 0.179 | G13: =E13/((100%-F13)) -> 0.179 | I13: =VLOOKUP(B13,'fixed cost'!$B$4:$R$116,17,0) -> 0 | O13: =SUM(G13:N13) -> 0.179 | Q13: 0.179 | R13: =C13-Q13 -> 0 | S13: =R13/Q13 -> 0
A14: =+A13+1 -> 7 | B14: Birsinghpur HPS | C14: 0.599 | E14: =C14+D14 -> 0.599 | G14: =E14/((100%-F14)) -> 0.599 | I14: =VLOOKUP(B14,'fixed cost'!$B$4:$R$116,17,0) -> 0 | O14: =SUM(G14:N14) -> 0.599 | Q14: 0.599 | R14: =C14-Q14 -> 0 | S14: =R14/Q14 -> 0
A15: 8 | B15: BLA I | C15: 3.989 | E15: =C15+D15 -> 3.989 | G15: =E15/((100%-F15)) -> 3.989 | H15: 0.15 | I15: =VLOOKUP(B15,'fixed cost'!$B$4:$R$116,17,0) -> #N/A | O15: =SUM(G15:N15) -> #N/A | Q15: 3.989 | R15: =C15-Q15 -> 0 | S15: =R15/Q15 -> 0
A16: 9 | B16: BLA II | C16: 3.28 | E16: =C16+D16 -> 3.28 | G16: =E16/((100%-F16)) -> 3.28 | H16: 0.15 | I16: =VLOOKUP(B16,'fixed cost'!$B$4:$R$116,17,0) -> 0.08001 | O16: =SUM(G16:N16) -> 3.51001 | Q16: 3.786 | R16: =C16-Q16 -> -0.506 | S16: =R16/Q16 -> -0.13365029
A17: 10 | B17: DVC (CTPS) (STOA LOI) | C17: 2.745 | E17: =C17+D17 -> 2.745 | F17: 0.0316 | G17: =E17/((100%-F17)) -> 2.8345725 | I17: =VLOOKUP(B17,'fixed cost'!$B$4:$R$116,17,0) -> 0 | K17: 0.024 | O17: =SUM(G17:N17) -> 2.8585725 | Q17: 2.745 | R17: =C17-Q17 -> 0 | S17: =R17/Q17 -> 0
A18: 11 | B18: DVC (DTPS) (STOA LOI) | C18: 4.307 | E18: =C18+D18 -> 4.307 | F18: =F17 -> 0.0316 | G18: =E18/((100%-F18)) -> 4.4475423 | I18: =VLOOKUP(B18,'fixed cost'!$B$4:$R$116,17,0) -> 0 | K18: 0 | O18: =SUM(G18:N18) -> 4.4475423 | Q18: 5.12 | R18: =C18-Q18 -> -0.813 | S18: =R18/Q18 -> -0.15878906
A19: 12 | B19: Essar Power (5%) | C19: 2.449 | E19: =C19+D19 -> 2.449 | F19: =F18 -> 0.0316 | G19: =E19/((100%-F19)) -> 2.5289137 | H19: 0.15 | I19: =VLOOKUP(B19,'fixed cost'!$B$4:$R$116,17,0) -> #N/A | O19: =SUM(G19:N19) -> #N/A | Q19: 2.378 | R19: =C19-Q19 -> 0.071 | S19: =R19/Q19 -> 0.029857023
A20: 13 | B20: Gadarwara | C20: 4.874 | E20: =C20+D20 -> 4.874 | F20: =F19 -> 0.0316 | G20: =E20/((100%-F20)) -> 5.0330442 | H20: 0.15 | I20: =VLOOKUP(B20,'fixed cost'!$B$4:$R$116,17,0) -> 0.058995 | O20: =SUM(G20:N20) -> 5.2420392 | Q20: 4.249 | R20: =C20-Q20 -> 0.625 | S20: =R20/Q20 -> 0.14709343
A21: =A20+1 -> 14 | B21: Gadarwara | C21: =C20 -> 4.874 | D21: =D20 -> 0 | E21: =C21+D21 -> 4.874 | F21: =F20 -> 0.0316 | G21: =E21/((100%-F21)) -> 5.0330442 | H21: =H20 -> 0.15 | I21: =VLOOKUP(B21,'fixed cost'!$B$4:$R$116,17,0) -> 0.058995 | M21: =VLOOKUP(B21,'fixed cost'!$B$4:$H$59,7,0) -> 2.0601461 | O21: =SUM(G21:N21) -> 7.3021853 | Q21: 4.249 | R21: =C21-Q21 -> 0.625 | S21: =R21/Q21 -> 0.14709343
A22: =A21+1 -> 15 | B22: GANDHAR (APM) | C22: 1.595 | E22: =C22+D22 -> 1.595 | F22: =F21 -> 0.0316 | G22: =E22/((100%-F22)) -> 1.6470467 | I22: =VLOOKUP(B22,'fixed cost'!$B$4:$R$116,17,0) -> 0 | O22: =SUM(G22:N22) -> 1.6470467 | Q22: 1.595 | R22: =C22-Q22 -> 0 | S22: =R22/Q22 -> 0
A23: =A22+1 -> 16 | B23: GANDHAR (APM) | C23: =C22 -> 1.595 | D23: =D22 -> 0 | E23: =C23+D23 -> 1.595 | F23: =F22 -> 0.0316 | G23: =E23/((100%-F23)) -> 1.6470467 | I23: =VLOOKUP(B23,'fixed cost'!$B$4:$R$116,17,0) -> 0 | M23: =VLOOKUP(B23,'fixed cost'!$B$4:$H$59,7,0) -> 1.0465902 | O23: =SUM(G23:N23) -> 2.6936369 | Q23: 1.595 | R23: =C23-Q23 -> 0 | S23: =R23/Q23 -> 0
A24: =A23+1 -> 17 | B24: GANDHAR (CLNG) | C24: 13.61 | E24: =C24+D24 -> 13.61 | F24: =F23 -> 0.0316 | G24: =E24/((100%-F24)) -> 14.05411 | I24: =VLOOKUP(B24,'fixed cost'!$B$4:$R$116,17,0) -> 0 | O24: =SUM(G24:N24) -> 14.05411 | Q24: 13.61 | R24: =C24-Q24 -> 0 | S24: =R24/Q24 -> 0
A25: =A24+1 -> 18 | B25: GANDHAR (CLNG) | C25: =C24 -> 13.61 | D25: =D24 -> 0 | E25: =C25+D25 -> 13.61 | F25: =F24 -> 0.0316 | G25: =E25/((100%-F25)) -> 14.05411 | I25: =VLOOKUP(B25,'fixed cost'!$B$4:$R$116,17,0) -> 0 | M25: =VLOOKUP(B25,'fixed cost'!$B$4:$H$59,7,0) -> 1.0465902 | O25: =SUM(G25:N25) -> 15.1007 | Q25: 13.61 | R25: =C25-Q25 -> 0 | S25: =R25/Q25 -> 0
A26: =A25+1 -> 19 | B26: GANDHAR (LNG) | C26: 12.861 | D26: 1.2545 | E26: =C26+D26 -> 14.1155 | F26: =F25 -> 0.0316 | G26: =E26/((100%-F26)) -> 14.576105 | I26: =VLOOKUP(B26,'fixed cost'!$B$4:$R$116,17,0) -> 0 | O26: =SUM(G26:N26) -> 14.576105 | Q26: 12.549 | R26: =C26-Q26 -> 0.312 | S26: =R26/Q26 -> 0.024862539
A27: =A26+1 -> 20 | B27: GANDHAR (LNG) | C27: =C26 -> 12.861 | D27: =D26 -> 1.2545 | E27: =C27+D27 -> 14.1155 | F27: =F26 -> 0.0316 | G27: =E27/((100%-F27)) -> 14.576105 | I27: =VLOOKUP(B27,'fixed cost'!$B$4:$R$116,17,0) -> 0 | M27: =VLOOKUP(B27,'fixed cost'!$B$4:$H$59,7,0) -> 1.0465902 | O27: =SUM(G27:N27) -> 15.622695 | Q27: 12.549 | R27: =C27-Q27 -> 0.312 | S27: =R27/Q27 -> 0.024862539
A28: =A27+1 -> 21 | B28: GANDHAR (NAPM) | C28: 24.557 | E28: =C28+D28 -> 24.557 | F28: =F27 -> 0.0316 | G28: =E28/((100%-F28)) -> 25.358323 | I28: =VLOOKUP(B28,'fixed cost'!$B$4:$R$116,17,0) -> 0 | O28: =SUM(G28:N28) -> 25.358323 | Q28: 18.946 | R28: =C28-Q28 -> 5.611 | S28: =R28/Q28 -> 0.2961575
A29: =A28+1 -> 22 | B29: GANDHAR (NAPM) | C29: =C28 -> 24.557 | D29: =D28 -> 0 | E29: =C29+D29 -> 24.557 | F29: =F28 -> 0.0316 | G29: =E29/((100%-F29)) -> 25.358323 | I29: =VLOOKUP(B29,'fixed cost'!$B$4:$R$116,17,0) -> 0 | M29: =VLOOKUP(B29,'fixed cost'!$B$4:$H$59,7,0) -> 1.0465902 | O29: =SUM(G29:N29) -> 26.404913 | Q29: 18.946 | R29: =C29-Q29 -> 5.611 | S29: =R29/Q29 -> 0.2961575
A30: =A29+1 -> 23 | B30: Gandhi Sagar HPS | C30: 0.203 | E30: =C30+D30 -> 0.203 | G30: =E30/((100%-F30)) -> 0.203 | I30: =VLOOKUP(B30,'fixed cost'!$B$4:$R$116,17,0) -> 0 | O30: =SUM(G30:N30) -> 0.203 | Q30: 0.203 | R30: =C30-Q30 -> 0 | S30: =R30/Q30 -> 0
A31: =A30+1 -> 24 | B31: ISP & OSP (25:11) | C31: =((1.9*25)+(2.314*11))/(25+11) -> 2.0265 | E31: =C31+D31 -> 2.0265 | G31: =E31/((100%-F31)) -> 2.0265 | H31: 0.15 | I31: ='fixed cost'!R57 -> 0.00882 | O31: =SUM(G31:N31) -> 2.18532 | P31: =2.314+0.15 -> 2.464 | Q31: 2.0265 | R31: =C31-Q31 -> 0 | S31: =R31/Q31 -> 0
A32: =A31+1 -> 25 | B32: Jawahar Sagar (Inter state project) | C32: 1.51 | E32: =C32+D32 -> 1.51 | G32: =E32/((100%-F32)) -> 1.51 | I32: =VLOOKUP(B32,'fixed cost'!$B$4:$R$116,17,0) -> 0 | O32: =SUM(G32:N32) -> 1.51 | Q32: 1.51 | R32: =C32-Q32 -> 0 | S32: =R32/Q32 -> 0
A33: =A32+1 -> 26 | B33: Jhabua Power | C33: 2.653 | E33: =C33+D33 -> 2.653 | F33: =F29 -> 0.0316 | G33: =E33/((100%-F33)) -> 2.7395704 | H33: 0.15 | I33: =VLOOKUP(B33,'fixed cost'!$B$4:$R$116,17,0) -> 0.05635 | O33: =SUM(G33:N33) -> 2.9459204 | Q33: 2.624 | R33: =C33-Q33 -> 0.029 | S33: =R33/Q33 -> 0.011051829
A34: =A33+1 -> 27 | B34: Jhinna HPS | C34: 0.603 | E34: =C34+D34 -> 0.603 | G34: =E34/((100%-F34)) -> 0.603 | I34: =VLOOKUP(B34,'fixed cost'!$B$4:$R$116,17,0) -> 0 | O34: =SUM(G34:N34) -> 0.603 | Q34: 0.603 | R34: =C34-Q34 -> 0 | S34: =R34/Q34 -> 0
A35: =A34+1 -> 28 | B35: JP Bina | C35: 3.322 | E35: =C35+D35 -> 3.322 | G35: =E35/((100%-F35)) -> 3.322 | H35: 0.15 | I35: =VLOOKUP(B35,'fixed cost'!$B$4:$R$116,17,0) -> 0.06477 | O35: =SUM(G35:N35) -> 3.53677 | Q35: 3.14 | R35: =C35-Q35 -> 0.182 | S35: =R35/Q35 -> 0.057961783
A36: =A35+1 -> 29 | B36: JP Nigrie | C36: 0.582 | E36: =C36+D36 -> 0.582 | F36: =F33 -> 0.0316 | G36: =E36/((100%-F36)) -> 0.60099133 | H36: 0.15 | I36: =VLOOKUP(B36,'fixed cost'!$B$4:$R$116,17,0) -> 0.040005 | O36: =SUM(G36:N36) -> 0.79099633 | Q36: 0.583 | R36: =C36-Q36 -> -0.001 | S36: =R36/Q36 -> -0.0017152659
A37: =A36+1 -> 30 | B37: KAHALGAON-II | C37: 3.788 | D37: 0.116 | E37: =C37+D37 -> 3.904 | F37: =F36 -> 0.0316 | G37: =E37/((100%-F37)) -> 4.031392 | I37: =VLOOKUP(B37,'fixed cost'!$B$4:$R$116,17,0) -> 0 | O37: =SUM(G37:N37) -> 4.031392 | Q37: 3.628 | R37: =C37-Q37 -> 0.16 | S37: =R37/Q37 -> 0.044101433
A38: =A37+1 -> 31 | B38: KAHALGAON-II | C38: =C37 -> 3.788 | D38: =D37 -> 0.116 | E38: =C38+D38 -> 3.904 | F38: =F37 -> 0.0316 | G38: =E38/((100%-F38)) -> 4.031392 | I38: =VLOOKUP(B38,'fixed cost'!$B$4:$R$116,17,0) -> 0 | M38: =VLOOKUP(B38,'fixed cost'!$B$4:$H$59,7,0) -> 0.92016616 | O38: =SUM(G38:N38) -> 4.9515581 | Q38: 3.628 | R38: =C38-Q38 -> 0.16 | S38: =R38/Q38 -> 0.044101433
A39: =A38+1 -> 32 | B39: KAWAS (APM) | C39: 1.597 | D39: =0.88/100 -> 0.0088 | E39: =C39+D39 -> 1.6058 | F39: =F38 -> 0.0316 | G39: =E39/((100%-F39)) -> 1.6581991 | I39: =VLOOKUP(B39,'fixed cost'!$B$4:$R$116,17,0) -> 0 | O39: =SUM(G39:N39) -> 1.6581991 | Q39: 1.597 | R39: =C39-Q39 -> 0 | S39: =R39/Q39 -> 0
A40: =A39+1 -> 33 | B40: KAWAS (APM) | C40: =C39 -> 1.597 | D40: =D39 -> 0.0088 | E40: =C40+D40 -> 1.6058 | F40: =F39 -> 0.0316 | G40: =E40/((100%-F40)) -> 1.6581991 | I40: =VLOOKUP(B40,'fixed cost'!$B$4:$R$116,17,0) -> 0 | M40: =VLOOKUP(B40,'fixed cost'!$B$4:$H$59,7,0) -> 0.85915096 | O40: =SUM(G40:N40) -> 2.5173501 | Q40: 1.597 | R40: =C40-Q40 -> 0 | S40: =R40/Q40 -> 0
A41: =A40+1 -> 34 | B41: KAWAS (CLNG) | C41: 13.602 | E41: =C41+D41 -> 13.602 | F41: =F40 -> 0.0316 | G41: =E41/((100%-F41)) -> 14.045849 | I41: =VLOOKUP(B41,'fixed cost'!$B$4:$R$116,17,0) -> 0 | O41: =SUM(G41:N41) -> 14.045849 | Q41: 13.602 | R41: =C41-Q41 -> 0 | S41: =R41/Q41 -> 0
A42: =A41+1 -> 35 | B42: KAWAS (CLNG) | C42: =C41 -> 13.602 | D42: =D41 -> 0 | E42: =C42+D42 -> 13.602 | F42: =F41 -> 0.0316 | G42: =E42/((100%-F42)) -> 14.045849 | I42: =VLOOKUP(B42,'fixed cost'!$B$4:$R$116,17,0) -> 0 | M42: =VLOOKUP(B42,'fixed cost'!$B$4:$H$59,7,0) -> 0.85915096 | O42: =SUM(G42:N42) -> 14.905 | Q42: 13.602 | R42: =C42-Q42 -> 0 | S42: =R42/Q42 -> 0
A43: =A42+1 -> 36 | B43: KAWAS (LNG) | C43: 13.038 | D43: -0.00899 | E43: =C43+D43 -> 13.02901 | F43: =F42 -> 0.0316 | G43: =E43/((100%-F43)) -> 13.454162 | I43: =VLOOKUP(B43,'fixed cost'!$B$4:$R$116,17,0) -> 0 | O43: =SUM(G43:N43) -> 13.454162 | Q43: 12.715 | R43: =C43-Q43 -> 0.323 | S43: =R43/Q43 -> 0.025403067
A44: =A43+1 -> 37 | B44: KAWAS (LNG) | C44: =C43 -> 13.038 | D44: =D43 -> -0.00899 | E44: =C44+D44 -> 13.02901 | F44: =F43 -> 0.0316 | G44: =E44/((100%-F44)) -> 13.454162 | I44: =VLOOKUP(B44,'fixed cost'!$B$4:$R$116,17,0) -> 0 | M44: =VLOOKUP(B44,'fixed cost'!$B$4:$H$59,7,0) -> 0.85915096 | O44: =SUM(G44:N44) -> 14.313312 | Q44: 12.715 | R44: =C44-Q44 -> 0.323 | S44: =R44/Q44 -> 0.025403067
A45: =A44+1 -> 38 | B45: KAWAS (Liquid) | C45: 17.686 | D45: 3.3233 | E45: =C45+D45 -> 21.0093 | F45: =F44 -> 0.0316 | G45: =E45/((100%-F45)) -> 21.694857 | I45: =VLOOKUP(B45,'fixed cost'!$B$4:$R$116,17,0) -> 0 | O45: =SUM(G45:N45) -> 21.694857 | Q45: 16.676 | R45: =C45-Q45 -> 1.01 | S45: =R45/Q45 -> 0.060566083
A46: =A45+1 -> 39 | B46: KAWAS (Liquid) | C46: =C45 -> 17.686 | D46: =D45 -> 3.3233 | E46: =C46+D46 -> 21.0093 | F46: =F45 -> 0.0316 | G46: =E46/((100%-F46)) -> 21.694857 | I46: =VLOOKUP(B46,'fixed cost'!$B$4:$R$116,17,0) -> 0 | M46: =M44 -> 0.85915096 | O46: =SUM(G46:N46) -> 22.554008 | Q46: 16.676 | R46: =C46-Q46 -> 1.01 | S46: =R46/Q46 -> 0.060566083
A47: =A44+1 -> 38 | B47: KAWAS (NAPM) | C47: 24.782 | D47: 0.274 | E47: =C47+D47 -> 25.056 | F47: =F46 -> 0.0316 | G47: =E47/((100%-F47)) -> 25.873606 | I47: =VLOOKUP(B47,'fixed cost'!$B$4:$R$116,17,0) -> 0 | O47: =SUM(G47:N47) -> 25.873606 | Q47: 19.069 | R47: =C47-Q47 -> 5.713 | S47: =R47/Q47 -> 0.2995962
A48: =A47+1 -> 39 | B48: KAWAS (NAPM) | C48: =C47 -> 24.782 | D48: =D47 -> 0.274 | E48: =E47 -> 25.056 | F48: =F47 -> 0.0316 | G48: =E48/((100%-F48)) -> 25.873606 | I48: =VLOOKUP(B48,'fixed cost'!$B$4:$R$116,17,0) -> 0 | M48: =VLOOKUP(B48,'fixed cost'!$B$4:$H$59,7,0) -> 0.85915096 | O48: =SUM(G48:N48) -> 26.732757 | Q48: 19.069 | R48: =C48-Q48 -> 5.713 | S48: =R48/Q48 -> 0.2995962
A49: =A46+1 -> 40 | B49: Khargone | C49: 5.81 | E49: =C49+D49 -> 5.81 | F49: =F48 -> 0.0316 | G49: =E49/((100%-F49)) -> 5.9995869 | H49: 0.15 | I49: =VLOOKUP(B49,'fixed cost'!$B$4:$R$116,17,0) -> 0.052785 | O49: =SUM(G49:N49) -> 6.2023719 | Q49: 5.213 | R49: =C49-Q49 -> 0.597 | S49: =R49/Q49 -> 0.11452139
A50: =A49+1 -> 41 | B50: Khargone | C50: =C49 -> 5.81 | D50: =D49 -> 0 | E50: =C50+D50 -> 5.81 | F50: =F49 -> 0.0316 | G50: =E50/((100%-F50)) -> 5.9995869 | H50: =H49 -> 0.15 | I50: =VLOOKUP(B50,'fixed cost'!$B$4:$R$116,17,0) -> 0.052785 | M50: =VLOOKUP(B50,'fixed cost'!$B$4:$H$59,7,0) -> 2.0731461 | O50: =SUM(G50:N50) -> 8.275518 | Q50: 5.213 | R50: =C50-Q50 -> 0.597 | S50: =R50/Q50 -> 0.11452139
A51: =A50+1 -> 42 | B51: KSTPS | C51: 1.804 | D51: 0.0359 | E51: =C51+D51 -> 1.8399 | F51: =F50 -> 0.0316 | G51: =E51/((100%-F51)) -> 1.899938 | I51: =VLOOKUP(B51,'fixed cost'!$B$4:$R$116,17,0) -> 0.13208364 | O51: =SUM(G51:N51) -> 2.0320217 | Q51: 1.676 | R51: =C51-Q51 -> 0.128 | S51: =R51/Q51 -> 0.076372315
A52: =A51+1 -> 43 | B52: KSTPS | C52: =C51 -> 1.804 | D52: =D51 -> 0.0359 | E52: =C52+D52 -> 1.8399 | F52: =F51 -> 0.0316 | G52: =E52/((100%-F52)) -> 1.899938 | I52: =VLOOKUP(B52,'fixed cost'!$B$4:$R$116,17,0) -> 0.13208364 | M52: =VLOOKUP(B52,'fixed cost'!$B$4:$H$59,7,0) -> 0.75506732 | O52: =SUM(G52:N52) -> 2.787089 | Q52: 1.676 | R52: =C52-Q52 -> 0.128 | S52: =R52/Q52 -> 0.076372315
A53: =A52+1 -> 44 | B53: =B52 -> KSTPS | C53: =C52 -> 1.804 | D53: =D52 -> 0.0359 | E53: =C53+D53 -> 1.8399 | F53: =F52 -> 0.0316 | G53: =E53/((100%-F53)) -> 1.899938 | I53: =VLOOKUP(B53,'fixed cost'!$B$4:$R$116,17,0) -> 0.13208364 | N53: 0.5 | O53: =SUM(G53:N53) -> 2.5320217 | Q53: 1.676 | R53: =C53-Q53 -> 0.128 | S53: =R53/Q53 -> 0.076372315
A54: =A53+1 -> 45 | B54: =B53 -> KSTPS | C54: =C53 -> 1.804 | D54: =D53 -> 0.0359 | E54: =C54+D54 -> 1.8399 | F54: =F53 -> 0.0316 | G54: =E54/((100%-F54)) -> 1.899938 | I54: =VLOOKUP(B54,'fixed cost'!$B$4:$R$116,17,0) -> 0.13208364 | N54: 0.65 | O54: =SUM(G54:N54) -> 2.6820217 | Q54: 1.676 | R54: =C54-Q54 -> 0.128 | S54: =R54/Q54 -> 0.076372315
A55: =A53+1 -> 45 | B55: KSTPS-III | C55: 1.546 | D55: 0.0349 | E55: =C55+D55 -> 1.5809 | F55: =F54 -> 0.0316 | G55: =E55/((100%-F55)) -> 1.6324866 | I55: =VLOOKUP(B55,'fixed cost'!$B$4:$R$116,17,0) -> 0.11369475 | O55: =SUM(G55:N55) -> 1.7461813 | Q55: 1.309 | R55: =C55-Q55 -> 0.237 | S55: =R55/Q55 -> 0.18105424
A56: =A55+1 -> 46 | B56: KSTPS-III | C56: =C55 -> 1.546 | D56: =D55 -> 0.0349 | E56: =C56+D56 -> 1.5809 | F56: =F55 -> 0.0316 | G56: =E56/((100%-F56)) -> 1.6324866 | I56: =VLOOKUP(B56,'fixed cost'!$B$4:$R$116,17,0) -> 0.11369475 | M56: =VLOOKUP(B56,'fixed cost'!$B$4:$H$59,7,0) -> 1.1259324 | O56: =SUM(G56:N56) -> 2.8721137 | Q56: 1.309 | R56: =C56-Q56 -> 0.237 | S56: =R56/Q56 -> 0.18105424
A57: =A56+1 -> 47 | B57: =B56 -> KSTPS-III | C57: =C56 -> 1.546 | D57: =D56 -> 0.0349 | E57: =C57+D57 -> 1.5809 | F57: =F56 -> 0.0316 | G57: =E57/((100%-F57)) -> 1.6324866 | I57: =VLOOKUP(B57,'fixed cost'!$B$4:$R$116,17,0) -> 0.11369475 | N57: 0.5 | O57: =SUM(G57:N57) -> 2.2461813 | Q57: 1.309 | R57: =C57-Q57 -> 0.237 | S57: =R57/Q57 -> 0.18105424
